Workbook

Sheet Entenda a planilha
B2: ABAIXO É EXPLICADO O QUE CONSTA EM CADA ABA DA PLANILHA:
B4: CAIXA
C5: Nesta aba é exibido o valor que consta em cada caixa do Núcleo no último dia do mês, ou seja, o valor em espécie e o valor em cada conta bancária, mês a mês.
B7: DISTRIB. VALORES
C8: Nesta aba mostra como o dinheiro do Núcleo está distribuído, mês a mês, considerando o valor operacional para uso da Tesouraria, Beneficência, Novo Encanto, Plantio, Fundo de Reserva de Bilhete Aéreo e Fundo de Reserva para Construções. É possível visualizar quanto tivemos de receita e despesa para cada linha, bem como o saldo atual.
B10: DINHEIRO
C11: Nesta aba consta a movimentação em dinheiro, mês a mês. Observação: - Quando há um depósito em dinheiro cujo valor sai do caixa em espécie e entra para uma conta bancária do núcleo, irá constar uma despesa nessa aba e uma receita na aba "TRANSF. ENTRE CONTAS". - Quando há um saque de dinheiro de alguma conta bancária do núcleo, irá constar uma receita nessa aba e uma despesa na aba "TRANSF. ENTRE CONTAS".
B13: TRANSF. ENTRE CONTAS
C14: Nesta aba consta a movimentação entre contas bancárias do núcleo, mês a mês. Observação: - Quando há um depósito em dinheiro cujo valor sai do caixa em espécie e entra para uma conta do núcleo, irá constar uma despesa nessa aba e uma receita na aba "TRANSF. ENTRE CONTAS". - Quando há um saque de dinheiro de alguma conta bancária do núcleo, irá constar uma receita nessa aba e uma despesa na aba "TRANSF. ENTRE CONTAS".
B16: ANO-MÊS-RECEITAS
C17: Nesta aba constam todas as receitas do Núcleo no referido mês, indicando a data da receita, se a receita foi efetivada ou não e em qual caixa a receita "entrou". Haverá uma aba desta para cada mês.
B19: ANO-MÊS-DESPESAS
C20: Nesta aba constam todas as despesas do Núcleo no referido mês, indicando a data da despesa, se a receita foi efetivada ou não, a partir de qual caixa a despesa foi paga e o link para acesso ao comprovante. Haverá uma aba desta para cada mês.
B22: INADIMPLÊNCIA
C23: Nesta aba consta a relação dos sócios inadimplentes no momento, bem como os respectivos valores.
B25: ANO-PREVISTO
C26: Nesta aba consta uma visão consolidada de todas as receitas e despesas previstas para o ano, mês a mês, possibilitando obter uma projeção financeira para o Núcleo ao longo do ano.
B28: ANO-REALIZADO
C29: Nesta aba consta uma visão consolidada de todas as receitas e despesas realizadas no ano, mês a mês, possibilitando obter uma visão gerencial da saúde financeira do Núcleo ao longo do ano.
B31: REUNIÃO DE DIRETORIA
C32: Nesta aba consta o material a ser apresentado na reunião de diretoria.

Sheet Caixa
B2: CAIXAS | C2: SALDO FINAL NOV/23 | D2: 2025
D3: JAN | E3: FEV | F3: MAR | G3: ABR | H3: MAI | I3: JUN | J3: JUL | K3: AGO | L3: SET | M3: OUT | N3: NOV | O3: DEZ
B4: Tesouraria | C4: =SUM(C5:C7) -> 33064.72 | D4: =SUM(D5:D8) -> 6618.93 | E4: =SUM(E5:E8) -> 6154.35 | F4: =SUM(F5:F8) -> 2892.19 | G4: =SUM(G5:G8) -> 6114.32 | H4: =SUM(H5:H8) -> 9821.9 | I4: =SUM(I5:I8) -> 27053.57 | J4: =SUM(J5:J8) -> 9510.64 | K4: =SUM(K5:K8) -> 9510.64 | ... O4: =SUM(O5:O8) -> 9510.64
B5: Dinheiro em espécie | C5: 1076.55 | D5: =2724.62+Dinheiro!D4 -> 5534.2 | E5: =D5+Dinheiro!E4 -> 1684.2 | F5: =E5+Dinheiro!F4 -> 727.2 | G5: =F5+Dinheiro!G4 -> 422.2 | H5: =G5+Dinheiro!H4 -> 534.2 | I5: =H5+Dinheiro!I4 -> 614.2 | J5: 614.2 | K5: =J5+Dinheiro!K4 -> 614.2 | L5: =K5+Dinheiro!L4 -> 614.2 | M5: =L5+Dinheiro!M4 -> 614.2 | N5: =M5+Dinheiro!N4 -> 614.2 | O5: =N5+Dinheiro!O4 -> 614.2
B6: Banco - Cora | C6: =582.43 -> 582.43 | D6: =10726.18+SUMIF('JAN-Receitas'!$H:$H,$B$6,'JAN-Receitas'!$F:$F)-SUMIF('JAN-Despesas'!$H:$H,$B$6,'JAN-Despesas'!$F:$F)-'Mov. entre Contas'!C11+'Mov. entre Contas'!C6 -> 849.26 | E6: =D6+SUMIF('FEV-Receitas'!$H:$H,$B$6,'FEV-Receitas'!$F:$F)-SUMIF('FEV-Despesas'!$H:$H,$B$6,'FEV-Despesas'!$F:$F)-'Mov. entre Contas'!D11+'Mov. entre Contas'!D6 -> 3970.15 | F6: =E6+SUMIF('MAR-Receitas'!$H:$H,$B$6,'MAR-Receitas'!$F:$F)-SUMIF('MAR-Despesas'!$H:$H,$B$6,'MAR-Despesas'!$F:$F)-'Mov. entre Contas'!E11+'Mov. entre Contas'!E6 -> 186.57 | G6: =F6+SUMIF('ABR-Receitas'!$H:$H,$B$6,'ABR-Receitas'!$F:$F)-SUMIF('ABR-Despesas'!$H:$H,$B$6,'ABR-Despesas'!$F:$F)-'Mov. entre Contas'!F11+'Mov. entre Contas'!F6 -> 3875.76 | H6: =G6+SUMIF('MAI-Receitas'!$H:$H,$B$6,'MAI-Receitas'!$F:$F)-SUMIF('MAI-Despesas'!$H:$H,$B$6,'MAI-Despesas'!$F:$F)-'Mov. entre Contas'!G11+'Mov. entre Contas'!G6 -> 5906.89 | I6: =H6+SUMIF('JUN-Receitas'!$H:$H,$B$6,'JUN-Receitas'!$F:$F)-SUMIF('JUN-Despesas'!$H:$H,$B$6,'JUN-Despesas'!$F:$F)-'Mov. entre Contas'!H11+'Mov. entre Contas'!H6 -> 12222.97 | J6: 8025.67 | K6: =J6+SUMIF('AGO-Receitas'!$H:$H,$B$6,'AGO-Receitas'!$F:$F)-SUMIF('AGO-Despesas'!$H:$H,$B$6,'AGO-Despesas'!$F:$F)-'Mov. entre Contas'!J11+'Mov. entre Contas'!J6 -> 8025.67 | L6: =K6+SUMIF('SET-Receitas'!$H:$H,$B$6,'SET-Receitas'!$F:$F)-SUMIF('SET-Despesas'!$H:$H,$B$6,'SET-Despesas'!$F:$F)-'Mov. entre Contas'!K11+'Mov. entre Contas'!K6 -> 8025.67 | M6: =L6+SUMIF('OUT-Receitas'!$H:$H,$B$6,'OUT-Receitas'!$F:$F)-SUMIF('OUT-Despesas'!$H:$H,$B$6,'OUT-Despesas'!$F:$F)-'Mov. entre Contas'!L11+'Mov. entre Contas'!L6 -> 8025.67 | N6: =M6+SUMIF('NOV-Receitas'!$H:$H,$B$6,'NOV-Receitas'!$F:$F)-SUMIF('NOV-Despesas'!$H:$H,$B$6,'NOV-Despesas'!$F:$F)-'Mov. entre Contas'!M11+'Mov. entre Contas'!M6 -> 8025.67 | O6: =N6+SUMIF('DEZ-Receitas'!$H:$H,$B$6,'DEZ-Receitas'!$F:$F)-SUMIF('DEZ-Despesas'!$H:$H,$B$6,'DEZ-Despesas'!$F:$F)-'Mov. entre Contas'!N11+'Mov. entre Contas'!N6 -> 8025.67
B7: Banco - Pagbank | C7: 31405.74 | D7: =876.739999999969+SUMIF('JAN-Receitas'!$H:$H,$B$7,'JAN-Receitas'!$F:$F)-SUMIF('JAN-Despesas'!$H:$H,$B$7,'JAN-Despesas'!$F:$F)-'Mov. entre Contas'!C12+'Mov. entre Contas'!C7 -> 220.47 | E7: =D7+SUMIF('FEV-Receitas'!$H:$H,$B$7,'FEV-Receitas'!$F:$F)-SUMIF('FEV-Despesas'!$H:$H,$B$7,'FEV-Despesas'!$F:$F)-'Mov. entre Contas'!D12+'Mov. entre Contas'!D7 -> 500 | F7: =E7+SUMIF('MAR-Receitas'!$H:$H,$B$7,'MAR-Receitas'!$F:$F)-SUMIF('MAR-Despesas'!$H:$H,$B$7,'MAR-Despesas'!$F:$F)-'Mov. entre Contas'!E12+'Mov. entre Contas'!E7 -> 1005.12 | G7: =F7+SUMIF('ABR-Receitas'!$H:$H,$B$7,'ABR-Receitas'!$F:$F)-SUMIF('ABR-Despesas'!$H:$H,$B$7,'ABR-Despesas'!$F:$F)-'Mov. entre Contas'!F12+'Mov. entre Contas'!F7 -> 452.55 | H7: =G7+SUMIF('MAI-Receitas'!$H:$H,$B$7,'MAI-Receitas'!$F:$F)-SUMIF('MAI-Despesas'!$H:$H,$B$7,'MAI-Despesas'!$F:$F)-'Mov. entre Contas'!G12+'Mov. entre Contas'!G7 -> -2.9558578e-11 | I7: =H7+SUMIF('JUN-Receitas'!$H:$H,$B$7,'JUN-Receitas'!$F:$F)-SUMIF('JUN-Despesas'!$H:$H,$B$7,'JUN-Despesas'!$F:$F)-'Mov. entre Contas'!H12+'Mov. entre Contas'!H7 -> 11980.44 | J7: 712.77 | K7: =J7+SUMIF('AGO-Receitas'!$H:$H,$B$7,'AGO-Receitas'!$F:$F)-SUMIF('AGO-Despesas'!$H:$H,$B$7,'AGO-Despesas'!$F:$F)-'Mov. entre Contas'!J12+'Mov. entre Contas'!J7 -> 712.77 | L7: =K7+SUMIF('SET-Receitas'!$H:$H,$B$7,'SET-Receitas'!$F:$F)-SUMIF('SET-Despesas'!$H:$H,$B$7,'SET-Despesas'!$F:$F)-'Mov. entre Contas'!K12+'Mov. entre Contas'!K7 -> 712.77 | M7: =L7+SUMIF('OUT-Receitas'!$H:$H,$B$7,'OUT-Receitas'!$F:$F)-SUMIF('OUT-Despesas'!$H:$H,$B$7,'OUT-Despesas'!$F:$F)-'Mov. entre Contas'!L12+'Mov. entre Contas'!L7 -> 712.77 | N7: =M7+SUMIF('NOV-Receitas'!$H:$H,$B$7,'NOV-Receitas'!$F:$F)-SUMIF('NOV-Despesas'!$H:$H,$B$7,'NOV-Despesas'!$F:$F)-'Mov. entre Contas'!M12+'Mov. entre Contas'!M7 -> 712.77 | O7: =N7+SUMIF('DEZ-Receitas'!$H:$H,$B$7,'DEZ-Receitas'!$F:$F)-SUMIF('DEZ-Despesas'!$H:$H,$B$7,'DEZ-Despesas'!$F:$F)-'Mov. entre Contas'!N12+'Mov. entre Contas'!N7 -> 712.77
B8: Banco - Stone | D8: =343+SUMIF('JAN-Receitas'!$H:$H,$B$8,'JAN-Receitas'!$F:$F)-SUMIF('JAN-Despesas'!$H:$H,$B$8,'JAN-Despesas'!$F:$F)-'Mov. entre Contas'!C13+'Mov. entre Contas'!C8 -> 15 | E8: =D8+SUMIF('FEV-Receitas'!$H:$H,$B$8,'FEV-Receitas'!$F:$F)-SUMIF('FEV-Despesas'!$H:$H,$B$8,'FEV-Despesas'!$F:$F)-'Mov. entre Contas'!D13+'Mov. entre Contas'!D8 -> 0 | F8: =E8+SUMIF('MAR-Receitas'!$H:$H,$B$8,'MAR-Receitas'!$F:$F)-SUMIF('MAR-Despesas'!$H:$H,$B$8,'MAR-Despesas'!$F:$F)-'Mov. entre Contas'!E13+'Mov. entre Contas'!E8 -> 973.3 | G8: =F8+SUMIF('ABR-Receitas'!$H:$H,$B$8,'ABR-Receitas'!$F:$F)-SUMIF('ABR-Despesas'!$H:$H,$B$8,'ABR-Despesas'!$F:$F)-'Mov. entre Contas'!F13+'Mov. entre Contas'!F8 -> 1363.81 | H8: =G8+SUMIF('MAI-Receitas'!$H:$H,$B$8,'MAI-Receitas'!$F:$F)-SUMIF('MAI-Despesas'!$H:$H,$B$8,'MAI-Despesas'!$F:$F)-'Mov. entre Contas'!G13+'Mov. entre Contas'!G8 -> 3380.81 | I8: =H8+SUMIF('JUN-Receitas'!$H:$H,$B$8,'JUN-Receitas'!$F:$F)-SUMIF('JUN-Despesas'!$H:$H,$B$8,'JUN-Despesas'!$F:$F)-'Mov. entre Contas'!H13+'Mov. entre Contas'!H8 -> 2235.96 | J8: 158 | K8: =J8+SUMIF('AGO-Receitas'!$H:$H,$B$8,'AGO-Receitas'!$F:$F)-SUMIF('AGO-Despesas'!$H:$H,$B$8,'AGO-Despesas'!$F:$F)-'Mov. entre Contas'!J13+'Mov. entre Contas'!J8 -> 158 | L8: =K8+SUMIF('SET-Receitas'!$H:$H,$B$8,'SET-Receitas'!$F:$F)-SUMIF('SET-Despesas'!$H:$H,$B$8,'SET-Despesas'!$F:$F)-'Mov. entre Contas'!K13+'Mov. entre Contas'!K8 -> 158 | M8: =L8+SUMIF('OUT-Receitas'!$H:$H,$B$8,'OUT-Receitas'!$F:$F)-SUMIF('OUT-Despesas'!$H:$H,$B$8,'OUT-Despesas'!$F:$F)-'Mov. entre Contas'!L13+'Mov. entre Contas'!L8 -> 158 | N8: =M8+SUMIF('NOV-Receitas'!$H:$H,$B$8,'NOV-Receitas'!$F:$F)-SUMIF('NOV-Despesas'!$H:$H,$B$8,'NOV-Despesas'!$F:$F)-'Mov. entre Contas'!M13+'Mov. entre Contas'!M8 -> 158 | O8: =N8+SUMIF('DEZ-Receitas'!$H:$H,$B$8,'DEZ-Receitas'!$F:$F)-SUMIF('DEZ-Despesas'!$H:$H,$B$8,'DEZ-Despesas'!$F:$F)-'Mov. entre Contas'!N13+'Mov. entre Contas'!N8 -> 158

Sheet Distrib. Valores
B2: DISTRIB. VALORES | C2: SALDO ATUAL | D2: 2025
D3: JAN | E3: FEV | F3: MAR | G3: ABR | H3: MAI | I3: JUN | J3: JUL | K3: AGO | L3: SET | M3: OUT | N3: NOV | O3: DEZ
B4: SALDO | C4: =SUM(C6:C11) -> 9510.64 | D4: =D5-D13 -> -8051.61 | E4: =E5-E13 -> -464.58 | F4: =F5-F13 -> -3262.16 | G4: =G5-G13 -> 3222.13 | H4: =H5-H13 -> 3707.58 | I4: =I5-I13 -> 17231.67 | J4: =J5-J13 -> -17542.93 | K4: =K5-K13 -> 0 | ... O4: =O5-O13 -> 0
B5: Receita | C5: - | D5: =SUM(D6:D11) -> 49292.99 | E5: =SUM(E6:E11) -> 22658.55 | F5: =SUM(F6:F11) -> 25745.35 | G5: =SUM(G6:G11) -> 38989.99 | H5: =SUM(H6:H11) -> 22836.63 | I5: =SUM(I6:I11) -> 46977.33 | J5: =SUM(J6:J11) -> 35715 | K5: =SUM(K6:K11) -> 0 | ... O5: =SUM(O6:O11) -> 0
B6: Operacional Tesouraria | C6: =13572.08+SUM(D6:O6)-SUM(D14:O14)-SUM(D16:O16)-SUM(D17:O17) -> 36082.68 | D6: =('JAN-Receitas'!$F$6-'JAN-Receitas'!$P$6-'JAN-Receitas'!$Q$6-'JAN-Receitas'!$R$6-'JAN-Receitas'!$S$6-'JAN-Receitas'!$T$6)+'JAN-Receitas'!$F$127+'JAN-Receitas'!$F$148+'JAN-Receitas'!$F$168+'JAN-Receitas'!$F$172-('JAN-Receitas'!$F$166+'JAN-Receitas'!$F$167+'JAN-Receitas'!F169) -> 41929.63 | E6: =('FEV-Receitas'!$F$6-'FEV-Receitas'!$P$6-'FEV-Receitas'!$Q$6-'FEV-Receitas'!$R$6-'FEV-Receitas'!$S$6-'FEV-Receitas'!$T$6)+'FEV-Receitas'!$F$127+'FEV-Receitas'!$F$147+'FEV-Receitas'!$F$169+'FEV-Receitas'!$F$173 -> 21053.29 | F6: =('MAR-Receitas'!$F$6-'MAR-Receitas'!$P$6-'MAR-Receitas'!$Q$6-'MAR-Receitas'!$R$6-'MAR-Receitas'!$S$6-'MAR-Receitas'!$T$6)+'MAR-Receitas'!$F$127+'MAR-Receitas'!$F$151+'MAR-Receitas'!$F$175+'MAR-Receitas'!$F$179-('MAR-Receitas'!F140) -> 23479.41 | G6: =('ABR-Receitas'!$F$6-'ABR-Receitas'!$P$6-'ABR-Receitas'!$Q$6-'ABR-Receitas'!$R$6-'ABR-Receitas'!$S$6-'ABR-Receitas'!$T$6)+'ABR-Receitas'!$F$126+'ABR-Receitas'!$F$150+'ABR-Receitas'!$F$180+'ABR-Receitas'!$F$184-('ABR-Receitas'!$F126) -> 22380.86 | H6: =('MAI-Receitas'!$F$6-'MAI-Receitas'!$P$6-'MAI-Receitas'!$Q$6-'MAI-Receitas'!$R$6-'MAI-Receitas'!$S$6-'MAI-Receitas'!$T$6)+'MAI-Receitas'!$F$124+'MAI-Receitas'!$F$149+'MAI-Receitas'!$F$179+'MAI-Receitas'!$F$183 -> 21585.89 | I6: =('JUN-Receitas'!$F$6-'JUN-Receitas'!$P$6-'JUN-Receitas'!$Q$6-'JUN-Receitas'!$R$6-'JUN-Receitas'!$S$6-'JUN-Receitas'!$T$6)+'JUN-Receitas'!$F$126+'JUN-Receitas'!$F$152+'JUN-Receitas'!$F$182+'JUN-Receitas'!$F$186-('JUN-Receitas'!$F126) -> 18361.6 | J6: =('JUL-Receitas'!$F$6-'JUL-Receitas'!$P$6-'JUL-Receitas'!$Q$6-'JUL-Receitas'!$R$6-'JUL-Receitas'!$S$6-'JUL-Receitas'!$T$6)+'JUL-Receitas'!$F$7+'JUL-Receitas'!$F$16+'JUL-Receitas'!$F$25+'JUL-Receitas'!$F$29-('JUL-Receitas'!$F12)-'JUL-Receitas'!F27 -> 20599.94 | K6: =('AGO-Receitas'!$F$6-'AGO-Receitas'!$P$6-'AGO-Receitas'!$Q$6-'AGO-Receitas'!$R$6-'AGO-Receitas'!$S$6-'AGO-Receitas'!$T$6)+'AGO-Receitas'!$F$126+'AGO-Receitas'!$F$154+'AGO-Receitas'!$F$184+'AGO-Receitas'!$F$188-('AGO-Receitas'!$F$170+'AGO-Receitas'!$F171+'AGO-Receitas'!$F$172+'AGO-Receitas'!$F139+'AGO-Receitas'!$F146) -> 0 | L6: =('SET-Receitas'!$F$6-'SET-Receitas'!$P$6-'SET-Receitas'!$Q$6-'SET-Receitas'!$R$6-'SET-Receitas'!$S$6-'SET-Receitas'!$T$6)+'SET-Receitas'!$F$126+'SET-Receitas'!$F$154+'SET-Receitas'!$F$184+'SET-Receitas'!$F$188-('SET-Receitas'!$F171+'SET-Receitas'!$F$172+'SET-Receitas'!$F139+'SET-Receitas'!$F146)-'SET-Receitas'!$F184 -> 0 | M6: =('OUT-Receitas'!$F$6-'OUT-Receitas'!$P$6-'OUT-Receitas'!$Q$6-'OUT-Receitas'!$R$6-'OUT-Receitas'!$S$6-'OUT-Receitas'!$T$6)+'OUT-Receitas'!$F$126+'OUT-Receitas'!$F$154+'OUT-Receitas'!$F$184+'OUT-Receitas'!$F$188-('OUT-Receitas'!$F171+'OUT-Receitas'!$F$172+'OUT-Receitas'!$F139+'OUT-Receitas'!$F146)-'OUT-Receitas'!$F184-'OUT-Receitas'!$F170 -> 0 | N6: =('NOV-Receitas'!$F$6-'NOV-Receitas'!$P$6-'NOV-Receitas'!$Q$6-'NOV-Receitas'!$R$6-'NOV-Receitas'!$S$6-'NOV-Receitas'!$T$6)+'NOV-Receitas'!$F$125+'NOV-Receitas'!$F$153+'NOV-Receitas'!$F$183+'NOV-Receitas'!$F$187-('NOV-Receitas'!$F170+'NOV-Receitas'!$F$171+'NOV-Receitas'!$F138+'NOV-Receitas'!$F145)-'NOV-Receitas'!$F183-'NOV-Receitas'!F169 -> 0 | O6: =('DEZ-Receitas'!$F$6-'DEZ-Receitas'!$P$6-'DEZ-Receitas'!$Q$6-'DEZ-Receitas'!$R$6-'DEZ-Receitas'!$S$6-'DEZ-Receitas'!$T$6)+'DEZ-Receitas'!$F$125+'DEZ-Receitas'!$F$154+'DEZ-Receitas'!$F$184+'DEZ-Receitas'!$F$188-('DEZ-Receitas'!$F170+'DEZ-Receitas'!$F171+'DEZ-Receitas'!$F$172+'DEZ-Receitas'!$F173+'DEZ-Receitas'!$F139+'DEZ-Receitas'!$F146+'DEZ-Receitas'!$F184+'DEZ-Receitas'!$F129) -> 0
B7: Beneficência NLT | C7: =834.599999999999+SUM(D7:O7)-SUM(D18:O18) -> 1020.91 | D7: ='JAN-Receitas'!$P$6 -> 152.36 | E7: ='FEV-Receitas'!$P$6 -> 223.26 | F7: ='MAR-Receitas'!$P$6 -> 178.94 | G7: ='ABR-Receitas'!$P$6 -> 191.76 | H7: ='MAI-Receitas'!$P$6 -> 178.74 | I7: ='JUN-Receitas'!$P$6 -> 212.32 | J7: ='JUL-Receitas'!$P$6 -> 179.06 | K7: ='AGO-Receitas'!$P$6 -> 0 | L7: ='SET-Receitas'!$P$6+('SET-Receitas'!$F$171+'SET-Receitas'!$F$172) -> 0 | M7: ='OUT-Receitas'!$P$6+('OUT-Receitas'!$F$171+'OUT-Receitas'!$F$172)+'OUT-Receitas'!$F170 -> 0 | N7: ='NOV-Receitas'!$P$6+('NOV-Receitas'!$F$170+'NOV-Receitas'!$F$171) -> 0 | O7: ='DEZ-Receitas'!$P$6+('DEZ-Receitas'!$F$171+'DEZ-Receitas'!$F$172) -> 0
B8: Novo Encanto NLT | C8: =903.41+SUM(D8:O8)-SUM(D19:O19)-SUM(D15:O15) -> 1370.41 | D8: ='JAN-Receitas'!$Q$6 -> 155 | E8: ='FEV-Receitas'!$Q$6 -> 215 | F8: ='MAR-Receitas'!$Q$6 -> 170 | G8: ='ABR-Receitas'!$Q$6 -> 190 | H8: ='MAI-Receitas'!$Q$6 -> 150 | I8: ='JUN-Receitas'!$Q$6 -> 195 | J8: ='JUL-Receitas'!$Q$6 -> 160 | K8: ='AGO-Receitas'!$Q$6 -> 0 | L8: ='SET-Receitas'!$Q$6 -> 0 | M8: ='OUT-Receitas'!$Q$6 -> 0 | N8: ='NOV-Receitas'!$Q$6 -> 0 | O8: ='DEZ-Receitas'!$Q$6 -> 0
B9: Plantio NLT | C9: =2242.53+SUM(D9:O9)-SUM(D20:O20) -> 866.53 | D9: ='JAN-Receitas'!$R$6+('JAN-Receitas'!$F$166+'JAN-Receitas'!$F$167) -> 259 | E9: ='FEV-Receitas'!$R$6 -> 260 | F9: ='MAR-Receitas'!$R$6 -> 205 | G9: ='ABR-Receitas'!$R$6 -> 210 | H9: ='MAI-Receitas'!$R$6 -> 175 | I9: ='JUN-Receitas'!$R$6 -> 195 | J9: ='JUL-Receitas'!$R$6 -> 160 | K9: ='AGO-Receitas'!$R$6+('AGO-Receitas'!$F$170+'AGO-Receitas'!$F$171+'AGO-Receitas'!$F$172) -> 0 | L9: ='SET-Receitas'!$R$6 -> 0 | M9: ='OUT-Receitas'!$R$6 -> 0 | N9: ='NOV-Receitas'!$R$6 -> 0 | O9: ='DEZ-Receitas'!$R$6 -> 0
B10: Fundo de Reserva Bilhete Aéreo | C10: =1500.49+SUM(D10:O10)-SUM(D21:O21) -> 626.65 | D10: ='JAN-Receitas'!$S$6 -> 217 | E10: ='FEV-Receitas'!$S$6 -> 297 | F10: ='MAR-Receitas'!$S$6 -> 262 | G10: ='ABR-Receitas'!$S$6 -> 297 | H10: ='MAI-Receitas'!$S$6 -> 227 | I10: ='JUN-Receitas'!$S$6 -> 307 | J10: ='JUL-Receitas'!$S$6+'JUL-Receitas'!F27 -> 1072 | K10: ='AGO-Receitas'!$S$6 -> 0 | L10: ='SET-Receitas'!$S$6 -> 0 | M10: ='OUT-Receitas'!$S$6 -> 0 | N10: ='NOV-Receitas'!$S$6 -> 0 | O10: ='DEZ-Receitas'!$S$6 -> 0
B11: Fundo de Reserva Construção | C11: =-4382.56999999995+SUM(D11:O11)-SUM(D22:O22) -> -30456.54 | D11: ='JAN-Receitas'!$T$6+'JAN-Receitas'!F169 -> 6580 | E11: ='FEV-Receitas'!$T$6 -> 610 | F11: ='MAR-Receitas'!$T$6+'MAR-Receitas'!F140 -> 1450 | G11: ='ABR-Receitas'!$T$6+'ABR-Receitas'!$F126 -> 15720.37 | H11: ='MAI-Receitas'!$T$6 -> 520 | I11: ='JUN-Receitas'!$T$6+'JUN-Receitas'!$F126 -> 27706.41 | J11: ='JUL-Receitas'!$T$6+'JUL-Receitas'!$F12 -> 13544 | K11: ='AGO-Receitas'!$T$6+'AGO-Receitas'!$F139+'AGO-Receitas'!$F146 -> 0 | L11: ='SET-Receitas'!$T$6+'SET-Receitas'!$F139+'SET-Receitas'!$F146+'SET-Receitas'!$F184 -> 0 | M11: ='OUT-Receitas'!$T$6+'OUT-Receitas'!$F139+'OUT-Receitas'!$F146+'OUT-Receitas'!$F184 -> 0 | N11: ='NOV-Receitas'!$T$6+'NOV-Receitas'!$F138+'NOV-Receitas'!$F145+'NOV-Receitas'!$F183+'NOV-Receitas'!F169 -> 0 | O11: ='DEZ-Receitas'!$T$6+'DEZ-Receitas'!$F170+'DEZ-Receitas'!$F171+'DEZ-Receitas'!$F$172+'DEZ-Receitas'!$F173+'DEZ-Receitas'!$F139+'DEZ-Receitas'!$F146+'DEZ-Receitas'!$F184+'DEZ-Receitas'!$F129 -> 0
B13: Despesa | C13: - | D13: =SUM(D14:D22) -> 57344.6 | E13: =SUM(E14:E22) -> 23123.13 | F13: =SUM(F14:F22) -> 29007.51 | G13: =SUM(G14:G22) -> 35767.86 | H13: =SUM(H14:H22) -> 19129.05 | I13: =SUM(I14:I22) -> 29745.66 | J13: =SUM(J14:J22) -> 53257.93 | K13: =SUM(K14:K22) -> 0 | ... O13: =SUM(O14:O22) -> 0
B14: Operacional Tesouraria | C14: - | D14: ='JAN-Despesas'!$F$6+SUM('JAN-Despesas'!$F$17:$F$28)+'JAN-Despesas'!$F$34+'JAN-Despesas'!$F$38+'JAN-Despesas'!$F$63+'JAN-Despesas'!$F$93+'JAN-Despesas'!$F$108+'JAN-Despesas'!$F$160+'JAN-Despesas'!$F$166+'JAN-Despesas'!$F$182+'JAN-Despesas'!$F$192+'JAN-Despesas'!$F$222+'JAN-Despesas'!$F$271+'JAN-Despesas'!$F$32 -> 36029.6 | E14: ='FEV-Despesas'!$F$6+SUM('FEV-Despesas'!$F$17:$F$28)+'FEV-Despesas'!$F$34+'FEV-Despesas'!$F$38+'FEV-Despesas'!$F$63+'FEV-Despesas'!$F$93+'FEV-Despesas'!$F$119+'FEV-Despesas'!$F$174+'FEV-Despesas'!$F$180+'FEV-Despesas'!$F$196+'FEV-Despesas'!$F$206+'FEV-Despesas'!$F$236+'FEV-Despesas'!$F$277+'FEV-Despesas'!$F$32 -> 16504.07 | F14: ='MAR-Despesas'!$F$6+SUM('MAR-Despesas'!$F$17:$F$28)+'MAR-Despesas'!$F$34+'MAR-Despesas'!$F$38+'MAR-Despesas'!$F$63+'MAR-Despesas'!$F$93+'MAR-Despesas'!$F$119+'MAR-Despesas'!$F$173+'MAR-Despesas'!$F$179+'MAR-Despesas'!$F$195+'MAR-Despesas'!$F$205+'MAR-Despesas'!$F$235+'MAR-Despesas'!$F$276+'MAR-Despesas'!$F$32+'MAR-Despesas'!$F$33 -> 17840.75 | G14: ='ABR-Despesas'!$F$6+SUM('ABR-Despesas'!$F$17:$F$28)+'ABR-Despesas'!$F$34+'ABR-Despesas'!$F$38+'ABR-Despesas'!$F$63+'ABR-Despesas'!$F$85+'ABR-Despesas'!$F$111+'ABR-Despesas'!$F$169+'ABR-Despesas'!$F$175+'ABR-Despesas'!$F$214+'ABR-Despesas'!$F$224+'ABR-Despesas'!$F$254+'ABR-Despesas'!$F$305+'ABR-Despesas'!$F$32-'ABR-Despesas'!F285-'ABR-Despesas'!F175+'ABR-Despesas'!F33 -> 14473.15 | H14: ='MAI-Despesas'!$F$6+SUM('MAI-Despesas'!$F$17:$F$28)+'MAI-Despesas'!$F$34+'MAI-Despesas'!$F$38+'MAI-Despesas'!$F$63+'MAI-Despesas'!$F$87+'MAI-Despesas'!$F$113+'MAI-Despesas'!$F$183+'MAI-Despesas'!$F$189+'MAI-Despesas'!$F$228+'MAI-Despesas'!$F$238+'MAI-Despesas'!$F$268+'MAI-Despesas'!$F$319+'MAI-Despesas'!$F$32 -> 14836.44 | I14: ='JUN-Despesas'!$F$6+SUM('JUN-Despesas'!$F$17:$F$28)+'JUN-Despesas'!$F$33+'JUN-Despesas'!$F$34+'JUN-Despesas'!$F$38+'JUN-Despesas'!$F$63+'JUN-Despesas'!$F$87+'JUN-Despesas'!$F$113+'JUN-Despesas'!$F$174+'JUN-Despesas'!$F$180+'JUN-Despesas'!$F$219+'JUN-Despesas'!$F$229+'JUN-Despesas'!$F$259+'JUN-Despesas'!$F$310+'JUN-Despesas'!$F$32-'JUN-Despesas'!$F$259 -> 14405.45 | J14: ='JUL-Despesas'!$F$6+SUM('JUL-Despesas'!$F$13:$F$18)+'JUL-Despesas'!$F$22+'JUL-Despesas'!$F$24+'JUL-Despesas'!$F$32+'JUL-Despesas'!$F$52+'JUL-Despesas'!$F$70+'JUL-Despesas'!$F$87+'JUL-Despesas'!$F$93+'JUL-Despesas'!$F$21-'JUL-Despesas'!$F$92 -> 20703.1 | K14: ='AGO-Despesas'!$F$6+SUM('AGO-Despesas'!$F$17:$F$27)+'AGO-Despesas'!$F$33+'AGO-Despesas'!$F$37+'AGO-Despesas'!$F$62+'AGO-Despesas'!$F$89+'AGO-Despesas'!$F$115+'AGO-Despesas'!$F$176+'AGO-Despesas'!$F$182+'AGO-Despesas'!$F$221+'AGO-Despesas'!$F$231+'AGO-Despesas'!$F$261+'AGO-Despesas'!$F$324+'AGO-Despesas'!$F$31-'AGO-Despesas'!$F$292-'AGO-Despesas'!$F$315 -> 0 | L14: ='SET-Despesas'!$F$6+SUM('SET-Despesas'!$F$17:$F$27)+'SET-Despesas'!$F$33+'SET-Despesas'!$F$37+'SET-Despesas'!$F$62+'SET-Despesas'!$F$89+'SET-Despesas'!$F$115+'SET-Despesas'!$F$176+'SET-Despesas'!$F$182+'SET-Despesas'!$F$221+'SET-Despesas'!$F$231+'SET-Despesas'!$F$261+'SET-Despesas'!$F$324+'SET-Despesas'!$F$31-'SET-Despesas'!$F$292-'SET-Despesas'!$F$315 -> 0 | M14: ='OUT-Despesas'!$F$6+SUM('OUT-Despesas'!$F$17:$F$27)+'OUT-Despesas'!$F$33+'OUT-Despesas'!$F$37+'OUT-Despesas'!$F$62+'OUT-Despesas'!$F$89+'OUT-Despesas'!$F$115+'OUT-Despesas'!$F$176+'OUT-Despesas'!$F$182+'OUT-Despesas'!$F$221+'OUT-Despesas'!$F$231+'OUT-Despesas'!$F$261+'OUT-Despesas'!$F$324+'OUT-Despesas'!$F$31+'OUT-Despesas'!$F$32-'OUT-Despesas'!$F$292-'OUT-Despesas'!$F$315 -> 0 | N14: ='NOV-Despesas'!$F$6+SUM('NOV-Despesas'!$F$17:$F$28)+'NOV-Despesas'!$F$34+'NOV-Despesas'!$F$38+'NOV-Despesas'!$F$63+'NOV-Despesas'!$F$90+'NOV-Despesas'!$F$116+'NOV-Despesas'!$F$179+'NOV-Despesas'!$F$185+'NOV-Despesas'!$F$224+'NOV-Despesas'!$F$234+'NOV-Despesas'!$F$264+'NOV-Despesas'!$F$327+'NOV-Despesas'!$F$32+'NOV-Despesas'!$F$33-'NOV-Despesas'!$F$295-'NOV-Despesas'!$F$318-'NOV-Despesas'!F35 -> 0 | O14: ='DEZ-Despesas'!$F$6+SUM('DEZ-Despesas'!$F$17:$F$28)+'DEZ-Despesas'!$F$34+'DEZ-Despesas'!$F$38+'DEZ-Despesas'!$F$63+'DEZ-Despesas'!$F$90+'DEZ-Despesas'!$F$116+'DEZ-Despesas'!$F$179+'DEZ-Despesas'!$F$185+'DEZ-Despesas'!$F$224+'DEZ-Despesas'!$F$234+'DEZ-Despesas'!$F$327+'DEZ-Despesas'!$F$32+'DEZ-Despesas'!$F$33 -> 0
B15: Repasse Novo encanto | D15: ='JAN-Despesas'!$F$29 -> 117 | E15: ='FEV-Despesas'!$F$29 -> 84 | F15: ='MAR-Despesas'!$F$29 -> 117 | G15: ='ABR-Despesas'!$F$29 -> 117 | H15: ='MAI-Despesas'!$F$29 -> 108 | I15: ='JUN-Despesas'!$F$29 -> 108 | J15: ='JUL-Despesas'!$F$19 -> 117 | K15: ='AGO-Despesas'!$F$28 -> 0 | L15: ='SET-Despesas'!$F$28 -> 0 | M15: ='OUT-Despesas'!$F$28 -> 0 | N15: ='NOV-Despesas'!$F$29 -> 0 | O15: ='DEZ-Despesas'!$F$29 -> 0
B16: Repasse Flor Divina | D16: ='JAN-Despesas'!$F$30 -> 2263.27 | E16: ='FEV-Despesas'!$F$30 -> 0 | F16: ='MAR-Despesas'!$F$30 -> 2048 | G16: ='ABR-Despesas'!$F$30 -> 2095.3 | H16: ='MAI-Despesas'!$F$30 -> 2289.32 | I16: ='JUN-Despesas'!$F$30 -> 0 | J16: ='JUL-Despesas'!$F$20 -> 1469.75 | K16: ='AGO-Despesas'!$F$29 -> 0 | L16: ='SET-Despesas'!$F$29 -> 0 | M16: ='OUT-Despesas'!$F$29 -> 0 | N16: ='NOV-Despesas'!$F$30 -> 0 | O16: ='DEZ-Despesas'!$F$30 -> 0
B17: Repasse Memorial José Gabriel da Costa | D17: ='JAN-Despesas'!$F$31 -> 0 | E17: ='FEV-Despesas'!$F$31 -> 0 | F17: ='MAR-Despesas'!$F$31 -> 1921.82 | G17: ='ABR-Despesas'!$F$31 -> 0 | H17: ='MAI-Despesas'!$F$31 -> 0 | I17: ='JUN-Despesas'!$F$31 -> 0 | J17: 0 | K17: ='AGO-Despesas'!$F$30 -> 0 | L17: ='SET-Despesas'!$F$30 -> 0 | M17: ='OUT-Despesas'!$F$30 -> 0 | N17: ='NOV-Despesas'!$F$31 -> 0 | O17: ='DEZ-Despesas'!$F$31 -> 0
B18: Beneficência NLT | D18: ='JAN-Despesas'!$F$172 -> 0 | E18: ='FEV-Despesas'!$F$186 -> 100 | F18: ='MAR-Despesas'!$F$185 -> 100 | G18: ='ABR-Despesas'!$F$204 -> 100 | H18: ='MAI-Despesas'!$F$218 -> 100 | I18: ='JUN-Despesas'!$F$209 -> 630.13 | J18: ='JUL-Despesas'!$F$82 -> 100 | K18: ='AGO-Despesas'!$F$211 -> 0 | L18: ='SET-Despesas'!$F$211 -> 0 | M18: ='OUT-Despesas'!$F$211 -> 0 | N18: ='NOV-Despesas'!$F$214 -> 0 | O18: ='DEZ-Despesas'!$F$214 -> 0
B19: Novo Encanto NLT | D19: ='JAN-Despesas'!$F$213 -> 0 | E19: ='FEV-Despesas'!$F$227 -> 0 | F19: ='MAR-Despesas'!$F$226 -> 0 | G19: ='ABR-Despesas'!$F$245 -> 0 | H19: ='MAI-Despesas'!$F$258 -> 0 | I19: ='JUN-Despesas'!$F$250 -> 0 | J19: 0 | K19: ='AGO-Despesas'!$F$251 -> 0 | L19: ='SET-Despesas'!$F$251 -> 0 | M19: ='OUT-Despesas'!$F$251 -> 0 | N19: ='NOV-Despesas'!$F$254 -> 0 | O19: ='DEZ-Despesas'!$F$254 -> 0
B20: Plantio NLT | D20: ='JAN-Despesas'!$F$202 -> 160 | E20: ='FEV-Despesas'!$F$216 -> 0 | F20: ='MAR-Despesas'!$F$215 -> 800 | G20: ='ABR-Despesas'!$F$234 -> 1240 | H20: ='MAI-Despesas'!$F$248 -> 80 | I20: ='JUN-Despesas'!$F$239 -> 400 | J20: ='JUL-Despesas'!$F$84 -> 160 | K20: ='AGO-Despesas'!$F$241 -> 0 | L20: ='SET-Despesas'!$F$241 -> 0 | M20: ='OUT-Despesas'!$F$241 -> 0 | N20: ='NOV-Despesas'!$F$244 -> 0 | O20: ='DEZ-Despesas'!$F$244 -> 0
B21: Fundo de Reserva Bilhete Aéreo | D21: ='JAN-Despesas'!$F$125 -> 0 | E21: ='FEV-Despesas'!$F$137 -> 513.21 | F21: ='MAR-Despesas'!$F$136 -> 513.21 | G21: ='ABR-Despesas'!$F$134 -> 513.21 | H21: ='MAI-Despesas'!$F$148 -> 513.21 | I21: ='JUN-Despesas'!$F$139 -> 0 | J21: ='JUL-Despesas'!$F$61 -> 1500 | K21: ='AGO-Despesas'!$F$141 -> 0 | L21: ='SET-Despesas'!$F$141 -> 0 | M21: ='OUT-Despesas'!$F$141 -> 0 | N21: ='NOV-Despesas'!$F$144 -> 0 | O21: ='DEZ-Despesas'!$F$144 -> 0
B22: Fundo de Reserva Construção | D22: ='JAN-Despesas'!$F$135 -> 18774.73 | E22: ='FEV-Despesas'!$F$147 -> 5921.85 | F22: ='MAR-Despesas'!$F$146 -> 5666.73 | G22: ='ABR-Despesas'!$F$144+'ABR-Despesas'!F285+'ABR-Despesas'!F175 -> 17229.2 | H22: ='MAI-Despesas'!$F$158 -> 1202.08 | I22: ='JUN-Despesas'!$F$149+'JUN-Despesas'!$F$259 -> 14202.08 | J22: ='JUL-Despesas'!$F$64+'JUL-Despesas'!$F$92 -> 29208.08 | K22: ='AGO-Despesas'!$F$151+'AGO-Despesas'!$F$292+'AGO-Despesas'!$F$315 -> 0 | L22: ='SET-Despesas'!$F$151+'SET-Despesas'!$F$292+'SET-Despesas'!$F$315 -> 0 | M22: ='OUT-Despesas'!$F$151+'OUT-Despesas'!$F$292+'OUT-Despesas'!$F$315 -> 0 | N22: ='NOV-Despesas'!$F$154+'NOV-Despesas'!$F$295+'NOV-Despesas'!$F$318+'NOV-Despesas'!$F$35 -> 0 | O22: ='DEZ-Despesas'!$F$154+'DEZ-Despesas'!$F$264 -> 0
B24: Observação:

Sheet Dinheiro
B2: MOV. EM DINHEIRO | C2: SALDO ATUAL | D2: 2025
D3: JAN | E3: FEV | F3: MAR | G3: ABR | H3: MAI | I3: JUN | J3: JUL | K3: AGO | L3: SET | M3: OUT | N3: NOV | O3: DEZ
B4: SALDO | C4: =2724.62+SUM(D4:O4) -> 614.2 | D4: =D5-D16 -> 2809.58 | E4: =E5-E16 -> -3850 | F4: =F5-F16 -> -957 | G4: =G5-G16 -> -305 | H4: =H5-H16 -> 112 | I4: =I5-I16 -> 80 | J4: =J5-J16 -> 0 | K4: =K5-K16 -> 0 | ... O4: =O5-O16 -> 0
B5: Receita | C5: - | D5: =SUM(D6:D14) -> 6477.08 | E5: =SUM(E6:E14) -> 150 | F5: =SUM(F6:F14) -> 43 | G5: =SUM(G6:G14) -> 3032 | H5: =SUM(H6:H14) -> 112 | I5: =SUM(I6:I14) -> 80 | J5: =SUM(J6:J14) -> 0 | K5: =SUM(K6:K14) -> 0 | ... O5: =SUM(O6:O14) -> 0
B6: Recebimento Mensalidade | D6: 0 | E6: 0 | F6: 0 | G6: 0 | H6: 0 | I6: 0 | J6: 0 | K6: 0 | L6: 0 | M6: 0 | N6: 0 | O6: 0
B7: 1a Escala - Caixa jantar | D7: ='JAN-Receitas'!F156 -> 20 | E7: ='FEV-Receitas'!F155 -> 40 | F7: 0 | G7: ='MAI-Receitas'!F157 -> 0 | H7: 0 | I7: 10 | J7: 0 | K7: 0 | L7: 0 | M7: 0 | N7: 0 | O7: 0
B8: 2a Escala - Caixa jantar | D8: ='JAN-Receitas'!$F158 -> 20 | E8: ='FEV-Receitas'!F157 -> 20 | F8: ='MAR-Receitas'!F161 -> 10 | G8: 0 | H8: ='MAI-Receitas'!F159 -> 10 | I8: 30 | J8: 0 | K8: 0 | L8: 0 | M8: 0 | N8: 0 | O8: 0
B9: 1a Escala - Caixa da boa vontade | D9: ='JAN-Receitas'!F151 -> 114 | E9: ='FEV-Receitas'!F150 -> 0 | F9: ='MAR-Receitas'!F154 -> 5 | G9: ='MAI-Receitas'!F152 -> 0 | H9: 0 | I9: 40 | J9: 0 | K9: 0 | L9: 0 | M9: 0 | N9: 0 | O9: 0
B10: 2a Escala - Caixa da boa vontade | D10: ='JAN-Receitas'!F153 -> 35 | E10: ='FEV-Receitas'!F152 -> 90 | F10: ='MAR-Receitas'!F156 -> 27 | G10: 0 | H10: ='MAI-Receitas'!F154 -> 102 | I10: 0 | J10: 0 | K10: 0 | L10: 0 | M10: 0 | N10: 0 | O10: 0
B11: Outras receitas | D11: 0 | E11: 0 | F11: ='MAR-Receitas'!F164 -> 1 | G11: 400 | H11: 0 | I11: 0 | J11: 0 | K11: 0 | L11: 0 | M11: 0 | N11: 0 | O11: 0
B12: Outras receitas | D12: 0 | E12: 0 | F12: 0 | G12: 0 | H12: 0 | I12: 0 | J12: 0 | K12: 0 | L12: 0 | M12: 0 | N12: 0 | O12: 0
B13: Promoção | D13: ='JAN-Receitas'!F138 -> 5423.14 | E13: 0 | F13: 0 | G13: ='ABR-Receitas'!F144 -> 2632 | H13: 0 | I13: 0 | J13: 0 | K13: 0 | L13: 0 | M13: 0 | N13: 0 | O13: 0
B14: Doação | D14: ='JAN-Receitas'!F170 -> 864.94 | E14: 0 | F14: 0 | G14: 0 | H14: 0 | I14: 0 | J14: 0 | K14: 0 | L14: 0 | M14: 0 | N14: 0 | O14: 0
B16: Despesa | C16: - | D16: =SUM(D17:D24) -> 3667.5 | E16: =SUM(E17:E24) -> 4000 | F16: =SUM(F17:F24) -> 1000 | G16: =SUM(G17:G24) -> 3337 | H16: =SUM(H17:H24) -> 0 | I16: =SUM(I17:I24) -> 0 | J16: =SUM(J17:J24) -> 0 | K16: =SUM(K17:K24) -> 0 | ... O16: =SUM(O17:O24) -> 0
B17: Cantina SANA | D17: ='JAN-Despesas'!F245 -> 1650 | E17: 0 | F17: 0 | G17: 0 | H17: 0 | I17: 0 | J17: 0 | K17: 0 | L17: 0 | M17: 0 | N17: 0 | O17: 0
B18: Cantina SANA | D18: ='JAN-Despesas'!F246 -> 1237.5 | E18: 0 | F18: 0 | G18: 0 | H18: 0 | I18: 0 | J18: 0 | K18: 0 | L18: 0 | M18: 0 | N18: 0 | O18: 0
B19: Cantina SANA | D19: ='JAN-Despesas'!F260 -> 780 | E19: 0 | F19: 0 | G19: 0 | H19: 0 | I19: 0 | J19: 0 | K19: 0 | L19: 0 | M19: 0 | N19: 0 | O19: 0
B20: Outras despesas | D20: 0 | E20: 0 | F20: 0 | G20: 0 | H20: 0 | I20: 0 | J20: 0 | K20: 0 | L20: 0 | M20: 0 | N20: 0 | O20: 0
B21: Outras despesas | D21: 0 | E21: 0 | F21: 0 | G21: 0 | H21: 0 | I21: 0 | J21: 0 | K21: 0 | L21: 0 | M21: 0 | N21: 0 | O21: 0
B22: Outras despesas | D22: 0 | E22: 0 | F22: 0 | G22: 0 | H22: 0 | I22: 0 | J22: 0 | K22: 0 | L22: 0 | M22: 0 | N22: 0 | O22: 0
B23: Outras despesas | D23: 0 | E23: 0 | F23: 0 | G23: 0 | H23: 0 | I23: 0 | J23: 0 | K23: 0 | L23: 0 | M23: 0 | N23: 0 | O23: 0
B24: Depósito | D24: 0 | E24: 4000 | F24: 1000 | G24: =1337+2000 -> 3337 | H24: 0 | I24: 0 | J24: 0 | K24: 0 | L24: 0 | M24: 0 | N24: 0 | O24: 0
B26: Observações do mês:

Sheet Mov. entre Contas
B2: MOVIM. ENTRE CONTAS | C2: 2025
C3: JAN | D3: FEV | E3: MAR | F3: ABR | G3: MAI | H3: JUN | I3: JUL | J3: AGO | K3: SET | L3: OUT | M3: NOV | N3: DEZ
B4: SALDO | C4: =C5-C10 -> 0 | D4: =D5-D10 -> 4000 | E4: =E5-E10 -> 1000 | F4: =F5-F10 -> 3337 | G4: =G5-G10 -> 0 | H4: =H5-H10 -> 0 | I4: =I5-I10 -> 0 | J4: =J5-J10 -> 0 | ... N4: =N5-N10 -> 0
B5: Entrada | C5: =SUM(C6:C8) -> 7034.94 | D5: =SUM(D6:D8) -> 6956.56 | E5: =SUM(E6:E8) -> 4518.74 | F5: =SUM(F6:F8) -> 16237 | G5: =SUM(G6:G8) -> 1779.61 | H5: =SUM(H6:H8) -> 996.67 | I5: =SUM(I6:I8) -> 4549.8 | J5: =SUM(J6:J8) -> 0 | ... N5: =SUM(N6:N8) -> 0
B6: Banco - Cora | C6: =391.94+1788+4500 -> 6679.94 | D6: =4000+701+2255.56 -> 6956.56 | E6: =1000+2500+906.74 -> 4406.74 | F6: =900+12000+1337+2000 -> 16237 | G6: =1779.61 -> 1779.61 | H6: =160+452.14+354.28 -> 966.42 | I6: =354.88+759.76 -> 1114.64 | J6: 0 | K6: 0 | L6: 0 | M6: 0 | N6: 0
B7: Banco - Pagbank | C7: 355 | D7: 0 | E7: 112 | F7: 0 | G7: 0 | H7: 0 | I7: 3435.16 | J7: 0 | K7: 0 | L7: 0 | M7: 0 | N7: 0
B8: Banco - Stone | C8: 0 | D8: 0 | E8: 0 | F8: 0 | G8: 0 | H8: =18.75+11.5 -> 30.25 | I8: 0 | J8: 0 | K8: 0 | L8: 0 | M8: 0 | N8: 0
B10: Saída | C10: =SUM(C11:C13) -> 7034.94 | D10: =SUM(D11:D13) -> 2956.56 | E10: =SUM(E11:E13) -> 3518.74 | F10: =SUM(F11:F13) -> 12900 | G10: =SUM(G11:G13) -> 1779.61 | H10: =SUM(H11:H13) -> 996.67 | I10: =SUM(I11:I13) -> 4549.8 | J10: =SUM(J11:J13) -> 0 | ... N10: =SUM(N11:N13) -> 0
B11: Banco - Cora | C11: 0 | D11: 0 | E11: 0 | F11: 0 | G11: 0 | H11: 0 | I11: 0 | J11: 0 | K11: 0 | L11: 0 | M11: 0 | N11: 0
B12: Banco - Pagbank | C12: =391.94+4500 -> 4891.94 | D12: =2255.56 -> 2255.56 | E12: =906.74 -> 906.74 | F12: =12000 -> 12000 | G12: =1779.61 -> 1779.61 | H12: =160+452.14+18.75+11.5+354.28 -> 996.67 | I12: 0 | J12: 0 | K12: 0 | L12: 0 | M12: 0 | N12: 0
B13: Banco - Stone | C13: =355+1788 -> 2143 | D13: 701 | E13: =2500+112 -> 2612 | F13: 900 | G13: 0 | H13: 0 | I13: =354.88+759.76+3435.16 -> 4549.8 | J13: 0 | K13: 0 | L13: 0 | M13: 0 | N13: 0
B15: Observações do mês:

Sheet 2023-DEZ-RECEITAS
B2: RECEITAS
B4: TOTAL | E4: =SUM(E6,E127,E147,E166,E170) -> 13054.13 | F4: =SUM(F6,F127,F147,F166,F170) -> 16583.84 | H4: CAIXA | I4: PLANO DE CONTAS DG
C5: Data | D5: Efetivado | E5: Valor Previsto | F5: Valor Recebido | G5: Observação | J5: Inadimp. (qtd) | K5: Inadimp. (R$) | L5: Núcleo | M5: Repasse DG | N5: Repasse 11a R | O5: Benef. NLT | P5: NE NLT | Q5: Plantio NLT | R5: FR Bilhete Aéreo | S5: FR Construção | T5: Taxa Extra | U5: Detalhamento Taxa Extra | W5: A receber:
B6: Mensalidade | C6: 10 | D6: - | E6: =SUM(E7:E126) -> 13054.13 | F6: =SUM(F7:F126) -> 13681.15 | G6: - | J6: =(COUNTIF(D7:D126,"Pendente")+COUNTIF(D7:D126,"Parcial"))/COUNTA(B7:B126) -> 0.13131313 | K6: =IFERROR(-(W6/E6),"Pendente info") -> 0.099068264 | L6: =SUMIF($D$7:$D$126,"OK",L7:L126)+SUMIF($D$7:$D$126,"Parcial",L7:L126) -> 8523.3 | M6: =SUMIF($D$7:$D$126,"OK",M7:M126)+SUMIF($D$7:$D$126,"Parcial",M7:M126) -> 2186.73 | N6: =SUMIF($D$7:$D$126,"OK",N7:N126)+SUMIF($D$7:$D$126,"Parcial",N7:N126) -> 1157 | O6: =SUMIF($D$7:$D$126,"OK",O7:O126)+SUMIF($D$7:$D$126,"Parcial",O7:O126) -> 224.12 | P6: =SUMIF($D$7:$D$126,"OK",P7:P126)+SUMIF($D$7:$D$126,"Parcial",P7:P126) -> 150 | Q6: =SUMIF($D$7:$D$126,"OK",Q7:Q126)+SUMIF($D$7:$D$126,"Parcial",Q7:Q126) -> 295 | R6: =SUMIF($D$7:$D$126,"OK",R7:R126)+SUMIF($D$7:$D$126,"Parcial",R7:R126) -> 390 | S6: =SUMIF($D$7:$D$126,"OK",S7:S126)+SUMIF($D$7:$D$126,"Parcial",S7:S126) -> 705 | T6: =SUMIF($D$7:$D$126,"OK",T7:T126)+SUMIF($D$7:$D$126,"Parcial",T7:T126) -> 50 | U6: - | V6: =IF(F6=SUM(L6:T6),"OK","Diferente") -> OK | W6: =SUM(W7:W126) -> -1293.25
B7: Elpídio Gomes de Moura Neto | C7: 12 | D7: OK | E7: 140.44 | F7: =E7 -> 140.44 | G7: Pagamento único de R$ 445,81 | H7: Banco - Cora | L7: 76.43 | M7: 24.57 | N7: 13 | O7: 1.44 | P7: 5 | Q7: 5 | R7: 15 | V7: =IF(F7=SUM(L7:T7),"OK","Diferente") -> OK | W7: =IF(V7="Diferente",F7-SUM(L7:T7),"")
B8: Juliana Collyer Arruda de Moura | C8: 12 | D8: OK | E8: 101.29 | F8: =E8 -> 101.29 | H8: Banco - Cora | L8: 52.28 | M8: 24.57 | N8: 13 | O8: 1.44 | P8: 5 | Q8: 5 | V8: =IF(F8=SUM(L8:T8),"OK","Diferente") -> OK | W8: =IF(V8="Diferente",F8-SUM(L8:T8),"")
B9: Silvéria Lopes Vasconcelos Arruda | C9: 12 | D9: OK | E9: 91.29 | F9: =E9 -> 91.29 | H9: Banco - Cora | L9: 52.28 | M9: 24.57 | N9: 13 | O9: 1.44 | V9: =IF(F9=SUM(L9:T9),"OK","Diferente") -> OK | W9: =IF(V9="Diferente",F9-SUM(L9:T9),"")
B10: Francisco de Assis Vasconcelos Arruda | C10: 12 | D10: OK | E10: 112.79 | F10: =E10 -> 112.79 | H10: Banco - Cora | L10: 63.78 | M10: 24.57 | N10: 13 | O10: 1.44 | P10: 5 | Q10: 5 | V10: =IF(F10=SUM(L10:T10),"OK","Diferente") -> OK | W10: =IF(V10="Diferente",F10-SUM(L10:T10),"")
B11: Antônio Gonçalves de Lima Filho | C11: 11 | D11: OK | E11: 166.17 | F11: =E11 -> 166.17 | G11: Pagamento único de R$ 312,34 | H11: Banco - Cora | L11: 107.16 | M11: 24.57 | N11: 13 | O11: 1.44 | Q11: 10 | R11: 10 | V11: =IF(F11=SUM(L11:T11),"OK","Diferente") -> OK | W11: =IF(V11="Diferente",F11-SUM(L11:T11),"")
B12: Sandra Borges Gonçalves de Lima | C12: 11 | D12: OK | E12: 146.17 | F12: =E12 -> 146.17 | H12: Banco - Cora | L12: 107.16 | M12: 24.57 | N12: 13 | O12: 1.44 | V12: =IF(F12=SUM(L12:T12),"OK","Diferente") -> OK | W12: =IF(V12="Diferente",F12-SUM(L12:T12),"")
B13: Marcelo de Castro Brasil | D13: Pendente | E13: 296.49 | F13: 0 | L13: 127.48 | M13: 24.57 | N13: 13 | O13: 1.44 | P13: 10 | Q13: 20 | R13: 50 | S13: 50 | V13: =IF(F13=SUM(L13:T13),"OK","Diferente") -> Diferente | W13: =IF(V13="Diferente",F13-SUM(L13:T13),"") -> -296.49
B14: Flora Borges Gonçalves Lima Brasil | D14: Pendente | E14: 189.29 | F14: 0 | L14: 95.28 | M14: 24.57 | N14: 13 | O14: 1.44 | P14: 5 | S14: 50 | V14: =IF(F14=SUM(L14:T14),"OK","Diferente") -> Diferente | W14: =IF(V14="Diferente",F14-SUM(L14:T14),"") -> -189.29
B15: Cássio Pereira Costa Sousa | C15: 19 | D15: OK | E15: 186.14 | F15: =E15*2 -> 372.28 | G15: Pagamento único de R$ 564,26 descontado da despesa de alimentação paga pela C. Mônica referente à confraternização. Desta forma, não há essa entrada no extrato do banco. | H15: Banco - Cora | L15: =117.13+186.14 -> 303.27 | M15: 24.57 | N15: 13 | O15: 1.44 | P15: 5 | Q15: 5 | R15: 20 | V15: =IF(F15=SUM(L15:T15),"OK","Diferente") -> OK | W15: =IF(V15="Diferente",F15-SUM(L15:T15),"")
B16: Mônica de Araújo Campos Costa Sousa | C16: 19 | D16: OK | E16: 95.99 | F16: =E16*2 -> 191.98 | H16: Banco - Cora | L16: =46.98+95.99 -> 142.97 | M16: 24.57 | N16: 13 | O16: 1.44 | P16: 5 | Q16: 5 | V16: =IF(F16=SUM(L16:T16),"OK","Diferente") -> OK | W16: =IF(V16="Diferente",F16-SUM(L16:T16),"")
B17: José Maurício Guimarães Gomes | C17: 8 | D17: OK | E17: 192.19 | F17: =E17 -> 192.19 | G17: Pagamento único de R$ 324,18 | H17: Banco - Cora | L17: 148.18 | M17: 24.57 | N17: 13 | O17: 1.44 | P17: 5 | V17: =IF(F17=SUM(L17:T17),"OK","Diferente") -> OK | W17: =IF(V17="Diferente",F17-SUM(L17:T17),"")
B18: Ticiane Aragão da Silveira Gomes | C18: 8 | D18: OK | E18: 131.99 | F18: =E18 -> 131.99 | H18: Banco - Cora | L18: 92.98 | M18: 24.57 | N18: 13 | O18: 1.44 | V18: =IF(F18=SUM(L18:T18),"OK","Diferente") -> OK | W18: =IF(V18="Diferente",F18-SUM(L18:T18),"")
B19: Sérvulo Sidney Gladius Paiva Pimentel | C19: 1 | D19: OK | E19: 434.29 | F19: =E19 -> 434.29 | G19: Pagamento único de R$ 858,58 | H19: Banco - Cora | L19: 325.28 | M19: 24.57 | N19: 13 | O19: 11.44 | Q19: 10 | S19: 50 | V19: =IF(F19=SUM(L19:T19),"OK","Diferente") -> OK | W19: =IF(V19="Diferente",F19-SUM(L19:T19),"")
B20: Maria Danielly Rios da Silva Paiva | C20: 1 | D20: OK | E20: 424.29 | F20: =E20 -> 424.29 | H20: Banco - Cora | L20: 325.28 | M20: 24.57 | N20: 13 | O20: 1.44 | Q20: 10 | S20: 50 | V20: =IF(F20=SUM(L20:T20),"OK","Diferente") -> OK | W20: =IF(V20="Diferente",F20-SUM(L20:T20),"")
B21: Régis Bezerra Gomes | C21: 1 | D21: OK | E21: 171.99 | F21: =E21 -> 171.99 | G21: Pagamento único de R$ 315,58 | H21: Banco - Cora | L21: 92.98 | M21: 24.57 | N21: 13 | O21: 1.44 | P21: 5 | Q21: 5 | S21: 30 | V21: =IF(F21=SUM(L21:T21),"OK","Diferente") -> OK | W21: =IF(V21="Diferente",F21-SUM(L21:T21),"")
B22: Ana Carolina de Oliveira Martins Gomes | C22: 1 | D22: OK | E22: 143.59 | F22: =E22 -> 143.59 | H22: Banco - Cora | L22: 74.58 | M22: 24.57 | N22: 13 | O22: 1.44 | S22: 30 | V22: =IF(F22=SUM(L22:T22),"OK","Diferente") -> OK | W22: =IF(V22="Diferente",F22-SUM(L22:T22),"")
B23: Lindayana de Souza Florêncio | C23: 21 | D23: OK | E23: 83.34 | F23: =E23*2+50 -> 216.68 | G23: Não consta a entrada destes valores no banco pois foram utilizados para compensar a despesa do auto de natal no valor de R$ 445,56. Esta despesa compensa a mensalidade de dezembro/23 e janeiro/24. | H23: Banco - Cora | L23: =34.33*2 -> 68.66 | M23: =24.57*2 -> 49.14 | N23: 26 | O23: 2.88 | P23: 10 | Q23: 10 | T23: 50 | U23: Confraternização dezembro/23 (antecipado de janeiro). | V23: =IF(F23=SUM(L23:T23),"OK","Diferente") -> OK | W23: =IF(V23="Diferente",F23-SUM(L23:T23),"")
B24: Davi Florêncio de Sousa | C24: 21 | D24: OK | E24: 114.44 | F24: =E24*2 -> 228.88 | H24: Banco - Cora | L24: =50.43*2 -> 100.86 | M24: =24.57*2 -> 49.14 | N24: 26 | O24: 2.88 | P24: 10 | Q24: 10 | S24: 30 | V24: =IF(F24=SUM(L24:T24),"OK","Diferente") -> OK | W24: =IF(V24="Diferente",F24-SUM(L24:T24),"")
B25: Joaquim Garcez de Lima Rocha | D25: Pendente | E25: 160.4 | F25: 0 | L25: 106.39 | M25: 24.57 | N25: 13 | O25: 6.44 | Q25: 10 | V25: =IF(F25=SUM(L25:T25),"OK","Diferente") -> Diferente | W25: =IF(V25="Diferente",F25-SUM(L25:T25),"") -> -160.4
B26: Emília Mesquita Salgueiro Garcez | D26: Pendente | E26: 118.35 | F26: 0 | L26: 79.34 | M26: 24.57 | N26: 13 | O26: 1.44 | V26: =IF(F26=SUM(L26:T26),"OK","Diferente") -> Diferente | W26: =IF(V26="Diferente",F26-SUM(L26:T26),"") -> -118.35
B27: Francisco Saulo Studart Albuquerque | C27: 4 | D27: OK | E27: 150 | F27: 645 | G27: R$ 645 referente a agosto, setembro, outubro e novembro | H27: Banco - Cora | L27: =110.43+(645-150) -> 605.43 | M27: 24.57 | N27: 13 | O27: 2 | V27: =IF(F27=SUM(L27:T27),"OK","Diferente") -> OK | W27: =IF(V27="Diferente",F27-SUM(L27:T27),"")
B28: Franco Costa e Silva | C28: 18 | D28: OK | E28: 205.79 | F28: =E28 -> 205.79 | G28: Pagamento único de R$ 264,58. O valor foi a menor que o padrão da mensalidade pois no mês anterior foi realizado um pagamento a maior, gerando crédito para a mensalidade de dezembro. | H28: Banco - Cora | L28: =106.78-37 -> 69.78 | M28: 24.57 | N28: 13 | O28: 11.44 | P28: 5 | Q28: 5 | R28: 10 | S28: 30 | V28: =IF(F28=SUM(L28:T28),"OK","Diferente") -> Diferente | W28: =IF(V28="Diferente",F28-SUM(L28:T28),"") -> 37
B29: Juliana Soares Monteiro | C29: 18 | D29: Parcial | E29: 195.79 | F29: =264.58-F28 -> 58.79 | H29: Banco - Cora | L29: =106.78-100 -> 6.78 | M29: 24.57 | N29: 13 | O29: 1.44 | P29: 5 | Q29: 5 | R29: 10 | S29: 30 | V29: =IF(F29=SUM(L29:T29),"OK","Diferente") -> Diferente | W29: =IF(V29="Diferente",F29-SUM(L29:T29),"") -> -37
B30: Hugo Uchôa Passos Alencar | C30: 5 | D30: OK | E30: 207.69 | F30: =E30 -> 207.69 | G30: Pagamento único de R$ 364,38 | H30: Banco - Cora | L30: 113.68 | M30: 24.57 | N30: 13 | O30: 1.44 | P30: 5 | Q30: 10 | R30: 10 | S30: 30 | V30: =IF(F30=SUM(L30:T30),"OK","Diferente") -> OK | W30: =IF(V30="Diferente",F30-SUM(L30:T30),"")
B31: Mairi Alencar de Lacerda Ferraz Uchôa | C31: 5 | D31: OK | E31: 156.69 | F31: =E31 -> 156.69 | H31: Banco - Cora | L31: 67.68 | M31: 24.57 | N31: 13 | O31: 1.44 | Q31: 10 | R31: 10 | S31: 30 | V31: =IF(F31=SUM(L31:T31),"OK","Diferente") -> OK | W31: =IF(V31="Diferente",F31-SUM(L31:T31),"")
B32: João Carlos Studart Antero | D32: Pendente | E32: 123.99 | F32: 0 | L32: 69.98 | M32: 24.57 | N32: 13 | O32: 1.44 | P32: 5 | R32: 10 | V32: =IF(F32=SUM(L32:T32),"OK","Diferente") -> Diferente | W32: =IF(V32="Diferente",F32-SUM(L32:T32),"") -> -123.99
B33: Janaina Silva Leitão Studart Antero | D33: Pendente | E33: 118.99 | F33: 0 | L33: 69.98 | M33: 24.57 | N33: 13 | O33: 1.44 | R33: 10 | V33: =IF(F33=SUM(L33:T33),"OK","Diferente") -> Diferente | W33: =IF(V33="Diferente",F33-SUM(L33:T33),"") -> -118.99
B34: Janaina de Pádua Carneiro Vasconcelos Giffoni | C34: 12 | D34: OK | E34: 172.79 | F34: =E34 -> 172.79 | G34: Pagamento único de R$ 403,53 | H34: Banco - Cora | L34: 83.78 | M34: 24.57 | N34: 13 | O34: 1.44 | S34: 50 | V34: =IF(F34=SUM(L34:T34),"OK","Diferente") -> OK | W34: =IF(V34="Diferente",F34-SUM(L34:T34),"")
B35: Vicente Alves Giffoni | C35: 12 | D35: OK | E35: 230.74 | F35: =E35 -> 230.74 | H35: Banco - Cora | L35: 121.73 | M35: 24.57 | N35: 13 | O35: 11.44 | Q35: 10 | S35: 50 | V35: =IF(F35=SUM(L35:T35),"OK","Diferente") -> OK | W35: =IF(V35="Diferente",F35-SUM(L35:T35),"")
B36: Raphael Bruno Dantas Moreira | C36: 15 | D36: OK | E36: 196.2 | F36: =E36 -> 196.2 | H36: Banco - Cora | L36: 128.63 | M36: 24.57 | N36: 13 | O36: 10 | P36: 5 | Q36: 15 | V36: =IF(F36=SUM(L36:T36),"OK","Diferente") -> OK | W36: =IF(V36="Diferente",F36-SUM(L36:T36),"")
B37: Davi Silvino Moraes | C37: 2 | D37: OK | E37: 176.76 | F37: =E37 -> 176.76 | H37: Banco - Cora | L37: 79.19 | M37: 24.57 | N37: 13 | O37: 5 | P37: 5 | Q37: 10 | R37: 10 | S37: 30 | V37: =IF(F37=SUM(L37:T37),"OK","Diferente") -> OK | W37: =IF(V37="Diferente",F37-SUM(L37:T37),"")
B38: Dimaranje José Moraes | C38: 15 | D38: OK | E38: 110.81 | F38: =(271/2)+E38 -> 246.31 | G38: Pagamento único de R$ 271,00 referente a novembro. Pagamento único de R$ 221,62 referente a dezembro. | H38: Banco - Cora | L38: =71.74+135.5 -> 207.24 | M38: 24.57 | N38: 13 | O38: 1.5 | V38: =IF(F38=SUM(L38:T38),"OK","Diferente") -> OK | W38: =IF(V38="Diferente",F38-SUM(L38:T38),"")
B39: Silvane da Silva Gonçalves | C39: 15 | D39: OK | E39: 110.81 | F39: =(271/2)+E39 -> 246.31 | H39: Banco - Cora | L39: =71.74+135.5 -> 207.24 | M39: 24.57 | N39: 13 | O39: 1.5 | V39: =IF(F39=SUM(L39:T39),"OK","Diferente") -> OK | W39: =IF(V39="Diferente",F39-SUM(L39:T39),"")
B40: Vicente de Paula Giffoni Filho | C40: 1 | D40: OK | E40: 118.59 | F40: =E40 -> 118.59 | G40: Pagamento único de R$ 428,36 | H40: Banco - Cora | L40: 74.58 | M40: 24.57 | N40: 13 | O40: 1.44 | Q40: 5 | V40: =IF(F40=SUM(L40:T40),"OK","Diferente") -> OK | W40: =IF(V40="Diferente",F40-SUM(L40:T40),"")
B41: Francinete Alves de Oliveira Giffoni | C41: 1 | D41: OK | E41: 123.59 | F41: =E41 -> 123.59 | H41: Banco - Cora | L41: 74.58 | M41: 24.57 | N41: 13 | O41: 1.44 | P41: 5 | Q41: 5 | V41: =IF(F41=SUM(L41:T41),"OK","Diferente") -> OK | W41: =IF(V41="Diferente",F41-SUM(L41:T41),"")
B42: Emanuel Alves Giffoni | C42: 1 | D42: OK | E42: 118.59 | F42: =E42 -> 118.59 | H42: Banco - Cora | L42: 74.58 | M42: 24.57 | N42: 13 | O42: 1.44 | Q42: 5 | V42: =IF(F42=SUM(L42:T42),"OK","Diferente") -> OK | W42: =IF(V42="Diferente",F42-SUM(L42:T42),"")
B43: Flora Alves Giffoni | C43: 1 | D43: OK | E43: 67.59 | F43: =E43 -> 67.59 | H43: Banco - Cora | L43: 28.58 | M43: 24.57 | N43: 13 | O43: 1.44 | V43: =IF(F43=SUM(L43:T43),"OK","Diferente") -> OK | W43: =IF(V43="Diferente",F43-SUM(L43:T43),"")
B44: Jonatas Cavalcante Brauna | C44: 1 | D44: OK | E44: 100 | F44: =E44 -> 100 | H44: Banco - Cora | L44: 50.99 | M44: 24.57 | N44: 13 | O44: 1.44 | Q44: 5 | R44: 5 | V44: =IF(F44=SUM(L44:T44),"OK","Diferente") -> OK | W44: =IF(V44="Diferente",F44-SUM(L44:T44),"")
B45: Lia Barroso Simonetti Gomes | C45: 15 | D45: OK | E45: 378.44 | F45: =E45 -> 378.44 | G45: Pagamento único de R$ 510,44 | H45: Banco - Cora | L45: 234.43 | M45: 24.57 | N45: 13 | O45: 1.44 | P45: 5 | R45: 50 | S45: 50 | V45: =IF(F45=SUM(L45:T45),"OK","Diferente") -> OK | W45: =IF(V45="Diferente",F45-SUM(L45:T45),"")
B46: Henrique Silva Nicolau | C46: 15 | D46: OK | E46: 132 | F46: =E46 -> 132 | H46: Banco - Cora | L46: 87.43 | M46: 24.57 | N46: 13 | O46: 2 | R46: 5 | V46: =IF(F46=SUM(L46:T46),"OK","Diferente") -> OK | W46: =IF(V46="Diferente",F46-SUM(L46:T46),"")
B47: Lucas Maia Dantas | C47: 5 | D47: OK | E47: 291.89 | F47: =E47 -> 291.89 | G47: Pagamento único de R$ 447,33 | H47: Banco - Cora | L47: 122.88 | M47: 24.57 | N47: 13 | O47: 1.44 | Q47: 10 | R47: 20 | S47: 100 | V47: =IF(F47=SUM(L47:T47),"OK","Diferente") -> OK | W47: =IF(V47="Diferente",F47-SUM(L47:T47),"")
B48: Emanuela Cristine Pereira Félix | C48: 5 | D48: OK | E48: 155.44 | F48: =E48 -> 155.44 | H48: Banco - Cora | L48: 96.43 | M48: 24.57 | N48: 13 | O48: 1.44 | R48: 20 | V48: =IF(F48=SUM(L48:T48),"OK","Diferente") -> OK | W48: =IF(V48="Diferente",F48-SUM(L48:T48),"")
B49: Lucas Caldas Oliveira | C49: - | D49: OK | E49: 125 | F49: 0 | G49: Pago em novembro/23. | H49: Banco - Cora | L49: 0 | M49: 0 | N49: 0 | O49: 0 | Q49: 0 | R49: 0 | V49: =IF(F49=SUM(L49:T49),"OK","Diferente") -> OK | W49: =IF(V49="Diferente",F49-SUM(L49:T49),"")
B50: Gabriela Araújo Holanda Pinto | C50: - | D50: OK | E50: 65 | F50: 0 | H50: Banco - Cora | L50: 0 | M50: 0 | N50: 0 | O50: 0 | R50: 0 | V50: =IF(F50=SUM(L50:T50),"OK","Diferente") -> OK | W50: =IF(V50="Diferente",F50-SUM(L50:T50),"")
B51: Valterlir Pereira de Lima | C51: 15 | D51: OK | E51: 179.99 | F51: =331.73+E51 -> 511.72 | G51: Pagamento único de R$ 331,73 referente a novembro Pagamento único de R$ 271,73 referente a dezembro | H51: Banco - Cora | L51: =115.98+331.73 -> 447.71 | M51: 24.57 | N51: 13 | O51: 11.44 | P51: 5 | Q51: 10 | V51: =IF(F51=SUM(L51:T51),"OK","Diferente") -> OK | W51: =IF(V51="Diferente",F51-SUM(L51:T51),"")
B52: Maria Lúcia Ferreira da Silva Lima | C52: 15 | D52: OK | E52: 91.74 | F52: =E52 -> 91.74 | H52: Banco - Cora | L52: 52.73 | M52: 24.57 | N52: 13 | O52: 1.44 | V52: =IF(F52=SUM(L52:T52),"OK","Diferente") -> OK | W52: =IF(V52="Diferente",F52-SUM(L52:T52),"")
B53: Salomão José Marques Maciel | C53: 1 | D53: OK | E53: 139.2 | F53: =E53 -> 139.2 | G53: Pagamento único de R$ 214,09 | H53: Banco - Cora | L53: 55.19 | M53: 24.57 | N53: 13 | O53: 1.44 | P53: 5 | Q53: 10 | R53: 30 | V53: =IF(F53=SUM(L53:T53),"OK","Diferente") -> OK | W53: =IF(V53="Diferente",F53-SUM(L53:T53),"")
B54: Ana Clara Simonetti Gomes Maciel | C54: 1 | D54: OK | E54: 74.89 | F54: =E54 -> 74.89 | H54: Banco - Cora | L54: 30.88 | M54: 24.57 | N54: 13 | O54: 1.44 | Q54: 5 | V54: =IF(F54=SUM(L54:T54),"OK","Diferente") -> OK | W54: =IF(V54="Diferente",F54-SUM(L54:T54),"")
B55: Rafael Luna Honório | C55: 11 | D55: OK | E55: 39.51 | F55: =39.51*2 -> 79.02 | G55: Pagamento único de R$ 79,02 referente a novembro (11/12). Pagamento único de R$ 79,02 referente a dezembro (11/12). | H55: Banco - Cora | L55: =0.44+39.51 -> 39.95 | M55: 24.57 | N55: 13 | O55: 1.5 | V55: =IF(F55=SUM(L55:T55),"OK","Diferente") -> OK | W55: =IF(V55="Diferente",F55-SUM(L55:T55),"")
B56: Júlia Rogério Fiore Cheuen | C56: 11 | D56: OK | E56: 39.51 | F56: =39.51*2 -> 79.02 | H56: Banco - Cora | L56: =0.44+39.51 -> 39.95 | M56: 24.57 | N56: 13 | O56: 1.5 | V56: =IF(F56=SUM(L56:T56),"OK","Diferente") -> OK | W56: =IF(V56="Diferente",F56-SUM(L56:T56),"")
B57: Isabela Clareana Pereira Félix | C57: 7 | D57: Parcial | E57: 135.44 | F57: 67.06 | G57: Msg do Lucas Caldas: A da clareana a C Maria José comprou uma mangueira e ficou assim: Desp mangueiras 539,70 Mensalidade setembro 177,94 Mensalidade outubro 157,94 Mensalidade novembro 135,44 Parte da mensalidade de dezembro 68,38 | H57: Banco - Cora | L57: =96.43-68.38 -> 28.05 | M57: 24.57 | N57: 13 | O57: 1.44 | V57: =IF(F57=SUM(L57:T57),"OK","Diferente") -> OK | W57: =IF(V57="Diferente",F57-SUM(L57:T57),"")
B58: Pedro Klecius Farias Cardoso | C58: 4 | D58: OK | E58: 244.29 | F58: =E58 -> 244.29 | G58: Pagamento único de R$ 388,58 | H58: Banco - Cora | L58: 95.28 | M58: 24.57 | N58: 13 | O58: 1.44 | Q58: 10 | S58: 100 | V58: =IF(F58=SUM(L58:T58),"OK","Diferente") -> OK | W58: =IF(V58="Diferente",F58-SUM(L58:T58),"")
B59: Genilda da Silva Cardoso | C59: 4 | D59: OK | E59: 144.29 | F59: =E59 -> 144.29 | H59: Banco - Cora | L59: 95.28 | M59: 24.57 | N59: 13 | O59: 1.44 | Q59: 10 | V59: =IF(F59=SUM(L59:T59),"OK","Diferente") -> OK | W59: =IF(V59="Diferente",F59-SUM(L59:T59),"")
B60: Manoel Messias do Nascimento Neto | D60: Pendente | E60: 65.74 | F60: 0 | L60: 26.67 | M60: 24.57 | N60: 13 | O60: 1.5 | V60: =IF(F60=SUM(L60:T60),"OK","Diferente") -> Diferente | W60: =IF(V60="Diferente",F60-SUM(L60:T60),"") -> -65.74
B61: Branda de Pádua Carneiro Vasconcelos Lessa | C61: 5 | D61: OK | E61: 87.14 | F61: =E61 -> 87.14 | G61: Pagamento único de R$ 211,23 | H61: Banco - Cora | L61: 48.13 | M61: 24.57 | N61: 13 | O61: 1.44 | V61: =IF(F61=SUM(L61:T61),"OK","Diferente") -> OK | W61: =IF(V61="Diferente",F61-SUM(L61:T61),"")
B62: Mateus Chaves Lessa de Castro | C62: 5 | D62: OK | E62: 124.09 | F62: =E62 -> 124.09 | H62: Banco - Cora | L62: 40.08 | M62: 24.57 | N62: 13 | O62: 1.44 | Q62: 15 | R62: 15 | S62: 15 | V62: =IF(F62=SUM(L62:T62),"OK","Diferente") -> OK | W62: =IF(V62="Diferente",F62-SUM(L62:T62),"")
B63: Rossyane Maria Oliveira da Costa | C63: 1 | D63: OK | E63: 42.92 | F63: 50 | H63: Banco - Cora | L63: =3.85+7.08 -> 10.93 | M63: 24.57 | N63: 13 | O63: 1.5 | V63: =IF(F63=SUM(L63:T63),"OK","Diferente") -> OK | W63: =IF(V63="Diferente",F63-SUM(L63:T63),"")
B64: Aline Miranda de Oliveira Germano | C64: 18 | D64: OK | E64: 55.37 | F64: =E64+55.37 -> 110.74 | G64: Pagamento único de R$ 55,37 referente a novembro (18/12). O valor de R$ 55,37 referente a dezembro foi descontado do valor de R$ 220,00 referente a despesa do bolo para a confraternização. Com isso, não há entrada do valor de R$ 55,37 no banco referente a mensalidade de dezembro/23. | H64: Banco - Cora | L64: =16.36+55.37 -> 71.73 | M64: 24.57 | N64: 13 | O64: 1.44 | V64: =IF(F64=SUM(L64:T64),"OK","Diferente") -> OK | W64: =IF(V64="Diferente",F64-SUM(L64:T64),"")
B65: Antônio Ramon da Silva Maia | C65: 8 | D65: OK | E65: 65.75 | F65: =E65 -> 65.75 | H65: Banco - Cora | L65: 26.74 | M65: 24.57 | N65: 13 | O65: 1.44 | V65: =IF(F65=SUM(L65:T65),"OK","Diferente") -> OK | W65: =IF(V65="Diferente",F65-SUM(L65:T65),"")
B66: Rafaely Maia Sombra Cordeiro | C66: 8 | D66: OK | E66: 66 | F66: =E66 -> 66 | H66: Banco - Cora | L66: 26.93 | M66: 24.57 | N66: 13 | O66: 1.5 | V66: =IF(F66=SUM(L66:T66),"OK","Diferente") -> OK | W66: =IF(V66="Diferente",F66-SUM(L66:T66),"")
B67: Francisco Hilton dos Santos Junior | C67: 19 | D67: OK | E67: 75.64 | F67: =E67 -> 75.64 | H67: Banco - Cora | L67: 36.63 | M67: 24.57 | N67: 13 | O67: 1.44 | V67: =IF(F67=SUM(L67:T67),"OK","Diferente") -> OK | W67: =IF(V67="Diferente",F67-SUM(L67:T67),"")
B68: Manoel Edini de Aguiar | C68: 28 | D68: OK | E68: 60 | F68: 110 | G68: Mensalidade de janeiro e fevereiro/24. Dezembro já havia sido pago em novembro. | H68: Banco - Cora | L68: =20.93+10.93 -> 31.86 | M68: =24.57*2 -> 49.14 | N68: =13*2 -> 26 | O68: =1.5*2 -> 3 | V68: =IF(F68=SUM(L68:T68),"OK","Diferente") -> OK | W68: =IF(V68="Diferente",F68-SUM(L68:T68),"")
B69: Cecilia Maria Cunha | C69: 16 | D69: OK | E69: 160 | F69: 190 | H69: Banco - Cora | L69: =90.99+30 -> 120.99 | M69: 24.57 | N69: 13 | O69: 11.44 | P69: 10 | R69: 10 | V69: =IF(F69=SUM(L69:T69),"OK","Diferente") -> OK | W69: =IF(V69="Diferente",F69-SUM(L69:T69),"")
B70: Ianna Darc Gomes Martins | C70: 1 | D70: OK | E70: 65.74 | F70: =E70 -> 65.74 | H70: Banco - Cora | L70: 26.67 | M70: 24.57 | N70: 13 | O70: 1.5 | V70: =IF(F70=SUM(L70:T70),"OK","Diferente") -> OK | W70: =IF(V70="Diferente",F70-SUM(L70:T70),"")
B71: Márcio Wallace Evangelista Teixeira | C71: 11 | D71: OK | E71: 186.82 | F71: =E71 -> 186.82 | G71: Pagamento único de R$ 373,64. | H71: Banco - Cora | L71: 109.25 | M71: 24.57 | N71: 13 | O71: 10 | Q71: 15 | R71: 15 | V71: =IF(F71=SUM(L71:T71),"OK","Diferente") -> OK | W71: =IF(V71="Diferente",F71-SUM(L71:T71),"")
B72: Juliana Dias Perdigão Teixeira | C72: 11 | D72: OK | E72: 186.82 | F72: =E72 -> 186.82 | H72: Banco - Cora | L72: 109.25 | M72: 24.57 | N72: 13 | O72: 10 | Q72: 15 | R72: 15 | V72: =IF(F72=SUM(L72:T72),"OK","Diferente") -> OK | W72: =IF(V72="Diferente",F72-SUM(L72:T72),"")
B73: Mateus de Miranda Dino | C73: 2 | D73: OK | E73: 141.54 | F73: =E73+166.54 -> 308.08 | G73: R$ 166,54 referente a novembro. R$ 141,54 referente a dezembro. | H73: Banco - Cora | L73: =77.53+166.54 -> 244.07 | M73: 24.57 | N73: 13 | O73: 1.44 | Q73: 20 | R73: 5 | V73: =IF(F73=SUM(L73:T73),"OK","Diferente") -> OK | W73: =IF(V73="Diferente",F73-SUM(L73:T73),"")
B74: Vitor Santos de Oliveira | C74: 12 | D74: OK | E74: 63.67 | F74: =E74 -> 63.67 | H74: Banco - Cora | L74: 24.66 | M74: 24.57 | N74: 13 | O74: 1.44 | V74: =IF(F74=SUM(L74:T74),"OK","Diferente") -> OK | W74: =IF(V74="Diferente",F74-SUM(L74:T74),"")
B75: Carmem Silvia de Carvalho Rego | C75: 12 | D75: OK | E75: 94.02 | F75: =E75 -> 94.02 | H75: Banco - Cora | L75: 54.95 | M75: 24.57 | N75: 13 | O75: 1.5 | V75: =IF(F75=SUM(L75:T75),"OK","Diferente") -> OK | W75: =IF(V75="Diferente",F75-SUM(L75:T75),"")
B76: Antonio Gilardo Xavier de Oliveira | C76: 31 | D76: Parcial | E76: 50 | F76: 200 | G76: Pagamento único de R$ 400,00 referente a mensalidades de agosto a novembro. | H76: Dinheiro em espécie | L76: =10.93+150 -> 160.93 | M76: 24.57 | N76: 13 | O76: 1.5 | V76: =IF(F76=SUM(L76:T76),"OK","Diferente") -> OK | W76: =IF(V76="Diferente",F76-SUM(L76:T76),"")
B77: Maria Euzanira Barbosa Oliveira | C77: 31 | D77: Parcial | E77: 50 | F77: 200 | H77: Dinheiro em espécie | L77: =10.93+150 -> 160.93 | M77: 24.57 | N77: 13 | O77: 1.5 | V77: =IF(F77=SUM(L77:T77),"OK","Diferente") -> OK | W77: =IF(V77="Diferente",F77-SUM(L77:T77),"")
B78: Thamires Caldas Oliveira | C78: 3 | D78: OK | E78: 40 | F78: =E78 -> 40 | H78: Banco - Cora | L78: 0.93 | M78: 24.57 | N78: 13 | O78: 1.5 | V78: =IF(F78=SUM(L78:T78),"OK","Diferente") -> OK | W78: =IF(V78="Diferente",F78-SUM(L78:T78),"")
B79: Maria Josilene Bezerra | C79: 8 | D79: OK | E79: 149.01 | F79: =E79 -> 149.01 | H79: Banco - Cora | L79: 96.44 | M79: 24.57 | N79: 13 | O79: 5 | P79: 10 | V79: =IF(F79=SUM(L79:T79),"OK","Diferente") -> OK | W79: =IF(V79="Diferente",F79-SUM(L79:T79),"")
B80: Wllysses José Marques Maciel | C80: 1 | D80: OK | E80: 55.39 | F80: =E80 -> 55.39 | H80: Banco - Cora | L80: 16.32 | M80: 24.57 | N80: 13 | O80: 1.5 | V80: =IF(F80=SUM(L80:T80),"OK","Diferente") -> OK | W80: =IF(V80="Diferente",F80-SUM(L80:T80),"")
B81: Dailane de Souza Florêncio | C81: 7 | D81: OK | E81: 65.74 | F81: =E81 -> 65.74 | H81: Banco - Cora | L81: 26.67 | M81: 24.57 | N81: 13 | O81: 1.5 | V81: =IF(F81=SUM(L81:T81),"OK","Diferente") -> OK | W81: =IF(V81="Diferente",F81-SUM(L81:T81),"")
B82: Samuel Dantas Moreira | C82: 19 | D82: OK | E82: 54.57 | F82: =E82 -> 54.57 | G82: Pagamento único de R$ 114,14 | H82: Banco - Cora | L82: 10 | M82: 24.57 | N82: 13 | O82: 2 | R82: 5 | V82: =IF(F82=SUM(L82:T82),"OK","Diferente") -> OK | W82: =IF(V82="Diferente",F82-SUM(L82:T82),"")
B83: Lorena Rodrigues Sales Dantas | C83: 19 | D83: OK | E83: 59.57 | F83: =E83 -> 59.57 | H83: Banco - Cora | L83: 15 | M83: 24.57 | N83: 13 | O83: 2 | R83: 5 | V83: =IF(F83=SUM(L83:T83),"OK","Diferente") -> OK | W83: =IF(V83="Diferente",F83-SUM(L83:T83),"")
B84: David Nascimento Alexandrino | C84: 2 | D84: OK | E84: 77.24 | F84: =E84 -> 77.24 | G84: Pagamento único de R$ 189,00 | H84: Banco - Cora | L84: 38.17 | M84: 24.57 | N84: 13 | O84: 1.5 | V84: =IF(F84=SUM(L84:T84),"OK","Diferente") -> OK | W84: =IF(V84="Diferente",F84-SUM(L84:T84),"")
B85: Maryna Rios Paiva | C85: 2 | D85: OK | E85: 111.76 | F85: =E85 -> 111.76 | H85: Banco - Cora | L85: 72.75 | M85: 24.57 | N85: 13 | O85: 1.44 | V85: =IF(F85=SUM(L85:T85),"OK","Diferente") -> OK | W85: =IF(V85="Diferente",F85-SUM(L85:T85),"")
B86: Francilene Alves de Oliveira Braga | C86: 12 | D86: OK | E86: 127.54 | F86: =E86 -> 127.54 | G86: Pagamento único de R$ 382,62 | H86: Banco - Cora | L86: 82.97 | M86: 24.57 | N86: 13 | O86: 2 | R86: 5 | V86: =IF(F86=SUM(L86:T86),"OK","Diferente") -> OK | W86: =IF(V86="Diferente",F86-SUM(L86:T86),"")
B87: Ana Alves Braga | C87: 12 | D87: OK | E87: 127.54 | F87: =E87 -> 127.54 | H87: Banco - Cora | L87: 82.97 | M87: 24.57 | N87: 13 | O87: 2 | R87: 5 | V87: =IF(F87=SUM(L87:T87),"OK","Diferente") -> OK | W87: =IF(V87="Diferente",F87-SUM(L87:T87),"")
B88: Luiza Alves Braga | C88: 12 | D88: OK | E88: 127.54 | F88: =E88 -> 127.54 | H88: Banco - Cora | L88: 82.97 | M88: 24.57 | N88: 13 | O88: 2 | R88: 5 | V88: =IF(F88=SUM(L88:T88),"OK","Diferente") -> OK | W88: =IF(V88="Diferente",F88-SUM(L88:T88),"")
B89: Vitor Hugo Paiva de Sousa | C89: 16 | D89: OK | E89: 150 | F89: =E89 -> 150 | H89: Banco - Cora | L89: 100.93 | M89: 24.57 | N89: 13 | O89: 1.5 | R89: 10 | V89: =IF(F89=SUM(L89:T89),"OK","Diferente") -> OK | W89: =IF(V89="Diferente",F89-SUM(L89:T89),"")
B90: Rafael Barbosa de Souza | C90: 4 | D90: OK | E90: 150 | F90: =E90 -> 150 | G90: Pagamento único de R$ 300,00 | H90: Banco - Cora | L90: 95.43 | M90: 24.57 | N90: 13 | O90: 2 | Q90: 5 | R90: 10 | V90: =IF(F90=SUM(L90:T90),"OK","Diferente") -> OK | W90: =IF(V90="Diferente",F90-SUM(L90:T90),"")
B91: Sarah Gomes Pinheiro | C91: 4 | D91: OK | E91: 150 | F91: =E91 -> 150 | H91: Banco - Cora | L91: 95.43 | M91: 24.57 | N91: 13 | O91: 2 | Q91: 5 | R91: 10 | V91: =IF(F91=SUM(L91:T91),"OK","Diferente") -> OK | W91: =IF(V91="Diferente",F91-SUM(L91:T91),"")
B92: Valmir Pereira Júnior | C92: 6 | D92: OK | E92: 150 | F92: =E92 -> 150 | H92: Banco - Cora | L92: 95.43 | M92: 24.57 | N92: 13 | O92: 2 | P92: 5 | R92: 10 | V92: =IF(F92=SUM(L92:T92),"OK","Diferente") -> OK | W92: =IF(V92="Diferente",F92-SUM(L92:T92),"")
B93: Bruno Bezerra Gomes | C93: 2 | D93: OK | E93: 45 | F93: =E93 -> 45 | H93: Banco - Cora | L93: 0.93 | M93: 24.57 | N93: 13 | O93: 1.5 | P93: 5 | V93: =IF(F93=SUM(L93:T93),"OK","Diferente") -> OK | W93: =IF(V93="Diferente",F93-SUM(L93:T93),"")
B94: Yara Freitas de Carvalho de Aguiar | D94: Pendente | E94: 70 | F94: 0 | L94: 30.93 | M94: 24.57 | N94: 13 | O94: 1.5 | V94: =IF(F94=SUM(L94:T94),"OK","Diferente") -> Diferente | W94: =IF(V94="Diferente",F94-SUM(L94:T94),"") -> -70
B95: Pollyanna Aparecida Batista Viana | C95: 1 | D95: OK | E95: 132 | F95: =E95 -> 132 | G95: Pagamento único de R$ 264,00 | H95: Banco - Cora | L95: 87.43 | M95: 24.57 | N95: 13 | O95: 2 | R95: 5 | V95: =IF(F95=SUM(L95:T95),"OK","Diferente") -> OK | W95: =IF(V95="Diferente",F95-SUM(L95:T95),"")
B96: João Viana Filho | C96: 1 | D96: OK | E96: 132 | F96: =E96 -> 132 | H96: Banco - Cora | L96: 87.43 | M96: 24.57 | N96: 13 | O96: 2 | R96: 5 | V96: =IF(F96=SUM(L96:T96),"OK","Diferente") -> OK | W96: =IF(V96="Diferente",F96-SUM(L96:T96),"")
B97: Francisca Sonia Costa | D97: Pendente | E97: 150 | F97: 0 | L97: 105.43 | M97: 24.57 | N97: 13 | O97: 2 | R97: 5 | V97: =IF(F97=SUM(L97:T97),"OK","Diferente") -> Diferente | W97: =IF(V97="Diferente",F97-SUM(L97:T97),"") -> -150
B98: Raquel da Silva Maia | C98: 1 | D98: OK | E98: 65 | F98: =E98 -> 65 | G98: Pagamento único de R$ 130,00 | H98: Banco - Cora | L98: 25.93 | M98: 24.57 | N98: 13 | O98: 1.5 | V98: =IF(F98=SUM(L98:T98),"OK","Diferente") -> OK | W98: =IF(V98="Diferente",F98-SUM(L98:T98),"")
B99: Francisco Eleilton Mendonça do Nascimento | C99: 1 | D99: OK | E99: 65 | F99: =E99 -> 65 | H99: Banco - Cora | L99: 25.93 | M99: 24.57 | N99: 13 | O99: 1.5 | V99: =IF(F99=SUM(L99:T99),"OK","Diferente") -> OK | W99: =IF(V99="Diferente",F99-SUM(L99:T99),"")
B100: Lucas Pinto Assunção | C100: 4 | D100: OK | E100: 70 | F100: =E100 -> 70 | H100: Banco - Cora | L100: 30.93 | M100: 24.57 | N100: 13 | O100: 1.5 | V100: =IF(F100=SUM(L100:T100),"OK","Diferente") -> OK | W100: =IF(V100="Diferente",F100-SUM(L100:T100),"")
B101: Maria Rosinele Felix do Nascimento | C101: 6 | D101: OK | E101: 140 | F101: =E101 -> 140 | H101: Banco - Cora | L101: 90.93 | M101: 24.57 | N101: 13 | O101: 1.5 | R101: 10 | V101: =IF(F101=SUM(L101:T101),"OK","Diferente") -> OK | W101: =IF(V101="Diferente",F101-SUM(L101:T101),"")
B102: Geane Batista Chaves | C102: 9 | D102: OK | E102: 160 | F102: 160 | H102: Banco - Cora | L102: 102.43 | M102: 24.57 | N102: 13 | O102: 5 | P102: 5 | R102: 10 | V102: =IF(F102=SUM(L102:T102),"OK","Diferente") -> OK | W102: =IF(V102="Diferente",F102-SUM(L102:T102),"")
...

Sheet 2023-DEZ-DESPESAS
B2: DESPESAS
B4: TOTAL | C4: - | D4: - | E4: =SUBTOTAL(9,E12,E37,E24,E105,E130,E136,E43,E6,E20,E192,E233,E142,E152,E162,E172,E182,E58) -> 0 | F4: =SUBTOTAL(9,F12,F37,F24,F95,F105,F130,F136,F43,F6,F20,F192,F233,F142,F152,F162,F172,F182,F58) -> 20359.32 | G4: - | H4: CAIXA | I4: COMPROVANTE | J4: PLANO DE CONTAS DG
C5: Data | D5: Efetivado | E5: Valor Previsto | F5: Valor Pago | G5: Observação
B6: NCL - Funcionários | C6: - | D6: - | E6: =SUM(E7:E11) -> 0 | F6: =SUM(F7:F11) -> 2464.52
B7: Salário | C7: 1 29 | D7: OK | E7: 0 | F7: =669.38+669.38 -> 1338.76 | G7: 01/12: Competência novembro, pago em dezembro. 29/12: Competência dezembro, pago em dezembro. | H7: Banco - Cora | I7: https://drive.google.com/file/d/1hy0gmUuDzO0Y1v2o5JeNrihBy4VZhOXk/view?usp=drive_link https://drive.google.com/file/d/1lH1HF_Pjg1fP995oUndkHiEUbdCEk4Lt/view?usp=drive_link
B8: 13° salário | C8: 20 | D8: OK | E8: 0 | F8: 325.99 | G8: 2a parcela 13° salário | H8: Banco - Cora | I8: https://drive.google.com/file/d/1HxfPZMes6T4DpkfQ9SN_bQakL0wH2ONT/view?usp=drive_link
B9: Férias | E9: 0 | F9: 0
B10: Encargos sociais | C10: 6 6 6 6 11 | D10: OK | E10: 0 | F10: =263.06+40.12+92.04+11.51+263.06 -> 669.79 | G10: 06/12: Darf previdenciário (R$ 263,06) 06/12: Darf previdenciário complementar (R$ 40,12) 06/12: FGTS (R$ 92,04) 06/12: PIS (R$ 11,51) 11/12: Darf previdenciário 13° salário (R$ 263,06) | H10: Banco - Cora | I10: https://drive.google.com/file/d/1K6wk-3aiUDrSIcQpIg07SrxvPGrFP-DY/view?usp=drive_link
B11: Outras despesas | C11: 22 | D11: OK | E11: 0 | F11: 129.98 | G11: 22/12: Duas cestas básicas para o Wesley. Dezembro/23 e janeiro/24. | H11: Banco - Cora | I11: https://drive.google.com/file/d/1armK0m59uAYu4CUS54qTVAiGc4D58WRv/view?usp=drive_link
B12: NCL - Repasses | C12: - | D12: - | E12: =SUM(E13:E19) -> 0 | F12: =SUM(F13:F19) -> 5194.16
B13: Diretoria Geral | C13: 20 | D13: OK | E13: 0 | F13: 2432.43 | H13: Banco - Prosperar Bank | I13: https://drive.google.com/file/d/1cArE6avLBdLZ_P5rT3rm_SHq9NEZyHHr/view?usp=drive_link
B14: 11a Região | C14: 14 | D14: OK | E14: 0 | F14: 1597 | H14: Banco - Prosperar Bank | I14: https://drive.google.com/file/d/16meczPDHPc1QEuGSscL4d7D707LYwmfm/view?usp=drive_link
B15: Novo Encanto | C15: 1 | D15: OK | E15: 0 | F15: 75 | H15: Banco - Cora | I15: https://drive.google.com/file/d/1cHkb8Yo3pPerc3nasiot9hJr4l1NKzRr/view?usp=drive_link
B16: Flor Divina | C16: 29 | D16: OK | E16: 0 | F16: =1089.73 -> 1089.73 | G16: Realizada uma transferência única de R$ 1.134,87, tendo R$ 1.089,73 saído do caixa da tesouraria e R$ 45,14 saído do caixa do Plantio (este valor está registrado nas despesas do plantio). | H16: Banco - Cora | I16: https://drive.google.com/file/d/1Ze8pvPmSyC-jJebtaDGmWRAVg1EjtwxZ/view?usp=drive_link
B17: Outro repasse (1) | E17: 0 | F17: 0
B18: Outro repasse (2) | E18: 0 | F18: 0
B19: Outro repasse (3) | E19: 0 | F19: 0
B20: NCL - Tarifas bancárias | C20: - | D20: - | E20: =SUM(E21:E23) -> 0 | F20: =SUM(F21:F23) -> 185.83
B21: Tarifa Itaú | C21: 4 | D21: OK | E21: 0 | F21: 118 | H21: Banco - Itaú | I21: https://drive.google.com/file/d/1Lrvz77hCs-9Ap-_hYtGDYxki1G3ANRlg/view?usp=drive_link
B22: IR do rendimento bruto do Pagbank | C22: 3 a 23 | D22: OK | E22: 0 | F22: 67.83 | H22: Banco - Pagbank | I22: https://drive.google.com/file/d/11LttsR061P4v40YjP52xj6kuSFCfOTYi/view?usp=drive_link
B23: Tarifa 3 | E23: 0 | F23: 0
B24: NCL - Despesas gerais | C24: - | D24: - | E24: =SUM(E25:E36) -> 0 | F24: =SUM(F25:F36) -> 4146.94
B25: Energia Elétrica | C25: 20 | D25: OK | E25: 0 | F25: 990.95 | H25: Banco - Prosperar Bank | I25: https://drive.google.com/file/d/19M0xZrZjCQjoBB2X8KbSUNgdb2ElEME8/view?usp=sharing
B26: Vigilância - Banco | C26: 17 | D26: OK | E26: 0 | F26: =590 -> 590 | G26: 17/12: R$ 590 referente a 2a escala. | H26: Banco - Cora | I26: https://drive.google.com/file/d/1-wYPjr9-RuWpx8mwPbBKgbEW_-ao1nJ2/view?usp=drive_link
B27: Contabilidade | C27: 4 | D27: OK | E27: 0 | F27: 396 | H27: Banco - Cora | I27: https://drive.google.com/file/d/1upTOtwJrjO-9QEwX0pEf6Xu4dDw0VTRX/view?usp=drive_link
B28: Internet | C28: 1 | D28: OK | E28: 0 | F28: 79.99 | H28: Banco - Cora | I28: https://drive.google.com/file/d/154fyTE2hE2-eF-mYvbl4PsFrIA4CvEBh/view?usp=drive_link
B29: Som | E29: 0 | F29: 0
B30: Jardim | E30: 0 | F30: 0
B31: Aluguel cadeiras 2a escala e sessão extra M. Herculano | C31: 18 | D31: OK | E31: 0 | F31: 200 | H31: Banco - Cora | I31: https://drive.google.com/file/d/1XNnx8OvJv3e9g5t7kDyG_22UT3Gy9hE9/view?usp=drive_link
B32: Compra de calças brancas e amarelas M. Herculano | C32: 19 | D32: OK | E32: 0 | F32: 800 | H32: Banco - Cora | I32: https://drive.google.com/file/d/1I6z53UUGdn_2WHC0Wbf8Uboov-m0h4Gh/view?usp=drive_link
B33: Homenagem M. Herculano | C33: 21 | D33: OK | E33: 0 | F33: 290 | H33: Banco - Cora | I33: https://drive.google.com/file/d/1jqskAC3ezP8yULTHgRoYQmbM6N641kMA/view?usp=drive_link
B34: Vigilância - Espécie | C34: 31 | D34: OK | E34: 0 | F34: 800 | G34: 31/12: R$ 800 referente a sessão de ano novo. | H34: Dinheiro em espécie | I34: https://drive.google.com/file/d/1P-zr1Ezy8pcmrVnt_qoETRI434kGz9Bv/view?usp=drive_link
B35: Despesa 5 | E35: 0 | F35: 0
B36: Despesa 6 | E36: 0 | F36: 0
B37: NCL - Organ | C37: - | D37: - | E37: =SUM(E38:E42) -> 0 | F37: =SUM(F38:F42) -> 2855.32
B38: Mercado | C38: 2 15 17 17 17 22 | D38: OK | E38: 0 | F38: =194.36+323.77+99+51.76+195.87+60 -> 924.76 | G38: 02/12: Despesa lanche compras realizadas pela C. Ticiane (R$ 194,36) 15/12: Despesa lanche compras realizadas pela C. Mônica (R$ 323,77) 17/12: Despesa sucos realizadas pela C. Mônica (R$ 99,00) 17/12: Despesa pães realizadas pela C. Mônica (R$ 51,76) 17/12: Despesa lanche pós sessão realizadas pela C. Mônica (R$ 195,87) 22/12: Despesa milhos realizada pela Genilda (R$ 60,00). Valor compensado em gasolina. | H38: Banco - Cora | I38: https://drive.google.com/file/d/1qohA5ZqkXdAGAMBL9jPLCmu8490VWIKK/view?usp=drive_link https://drive.google.com/file/d/1FimwTgXc5cQaAAXqpNbxTZQ5KHiZTdnC/view?usp=drive_link https://drive.google.com/file/d/1UxUwTwLslc6eMcGDWQDeEAC7cY_apPPj/view?usp=drive_link https://drive.google.com/file/d/1FVP9SX6TRCPgAC27SHwM1qTxya69rkaN/view?usp=drive_link https://drive.google.com/file/d/1vbz-0wRkX3s6zyqn-g6Mu60pchC2vKN3/view?usp=drive_link https://drive.google.com/file/d/1NpttEIh0DeYQy-fFYDCiY2BOfVJw1uMu/view?usp=drive_link
B39: Água mineral | C39: 6 | D39: OK | E39: 0 | F39: =176 -> 176 | G39: 06/12: Compra de água mineral realizada pela C. Mônica (R$ 176,00) | H39: Banco - Prosperar Bank | I39: https://drive.google.com/file/d/1_jNZMYCrAGGWzhMBq9-LhIw9GpW9Czv-/view?usp=drive_link
B40: Jantar | C40: 1 2 15 | D40: OK | E40: 0 | F40: =344.38+54.52+471.89+35.94 -> 906.73 | G40: 01/12: Despesa jantar compras realizadas pela Janaina (R$ 344,38) 02/12: Despesa jantar compras realizadas pela Janaina (R$ 54,52) 15/12: Despesa jantar compras realizadas pela C. Mônica (R$ 471,89) 18/12: Despesa jantar compras realizadas pela C. Mônica (R$ 35,94) | H40: Banco - Cora | I40: https://drive.google.com/file/d/1nPgegJSuqnwuk-iYFRhXYHo8wTC8aEz9/view?usp=drive_link https://drive.google.com/file/d/1sRWeeKtrGlKQTITRH-yqV0m_hkcXNgii/view?usp=drive_link https://drive.google.com/file/d/1x9MFphbftZkHDMhlobbkfb6HuGUDHzNt/view?usp=drive_link https://drive.google.com/file/d/1zRm9goP6Ggpm_QObPvcdrIUpZEEYidEP/view?usp=drive_link
B41: Material de limpeza | C41: 3 5 15 30 | D41: OK | E41: 0 | F41: =40+345.8+173.44+243.6+9.99 -> 812.83 | G41: 03/12: Material de limpeza compras realizadas pelo Didi (R$ 40,00) 05/12: Material de limpeza compras realizadas pela C. Mônica (R$ 345,80) 15/12: Material de limpeza compras realizadas pela C. Mônica (R$ 173,44) 30/12: Material de limpeza compras realizadas pela C. Mônica (R$ 243,60 + R$ 9,99) | H41: Banco - Cora | I41: https://drive.google.com/file/d/1xJLqU67vj9QoDtu5M4sDg3TwvPlUd5Sp/view?usp=drive_link https://drive.google.com/file/d/12kj-Bqazy502velNLugU1ASuF7W7G2mr/view?usp=drive_link https://drive.google.com/file/d/1puaDbpAwNB8jJhxFDy9XPv-19RGucxbz/view?usp=drive_link https://drive.google.com/file/d/1XJXpsoBSrRqg7Yb5ZjlIUeaILjYtuxrx/view?usp=drive_link
B42: Outra despesa (3) | C42: 31 | D42: OK | E42: 0 | F42: 35 | G42: 31/12: Despesa castanhas pós sessão realizada pela C. Mônica (R$ 35,00) | H42: Dinheiro em espécie | I42: https://drive.google.com/file/d/1-8_zDpcbXg1Q9ElAhbCwiAwIGBZzl8r3/view?usp=drive_link
B43: NCL - Preparo | C43: - | D43: - | E43: =SUM(E44,E50,E54) -> 0 | F43: =SUM(F44,F50,F54) -> 0
B44: Organ | E44: =SUM(E45:E49) -> 0 | F44: =SUM(F45:F49) -> 0
B45: Mercado | E45: 0 | F45: 0
B46: Água mineral | E46: 0 | F46: 0
B47: Outra despesa (1) | E47: 0 | F47: 0
B48: Outra despesa (2) | E48: 0 | F48: 0
B49: Outra despesa (3) | E49: 0 | F49: 0
B50: Materiais | E50: =SUM(E51:E53) -> 0 | F50: =SUM(F51:F53) -> 0
B51: Despesa 1 | E51: 0 | F51: 0
B52: Despesa 2 | E52: 0 | F52: 0
B53: Despesa 3 | E53: 0 | F53: 0
B54: Colheita | E54: =SUM(E55:E57) -> 0 | F54: =SUM(F55:F57) -> 0
B55: Despesa 1 | E55: 0 | F55: 0
B56: Despesa 2 | E56: 0 | F56: 0
B57: Despesa 3 | E57: 0 | F57: 0
B58: NCL - Festividades | C58: - | D58: - | E58: =SUM(E59,E65,E75,E85) -> 0 | F58: =SUM(F59,F65,F75,F85) -> 2025.22
B59: Sessão de casal | E59: =SUM(E60:E64) -> 0 | F59: =SUM(F60:F64) -> 0
B60: Jantar | E60: 0 | F60: 0
B61: Lembrancinhas | E61: 0 | F61: 0
B62: Disco de vinil | E62: 0 | F62: 0
B63: Despesa 2 | E63: 0 | F63: 0
B64: Despesa 3 | E64: 0 | F64: 0
B65: Confraternização final do ano | E65: =SUM(E66:E74) -> 0 | F65: =SUM(F66:F74) -> 1579.66
B66: Alimentação | C66: 15 19 | D66: OK | E66: 0 | F66: =142.22+163.53+1053.91 -> 1359.66 | G66: 15/12: Despesa R$ 142,22 15/12: Despesa R$ 163,53 19/12: Despesa R$ 1053,91. Deste valor foi descontado o valor de R$ 564,26 referente a mensalidade de dezembro do M. Cassio e C. Mônica. Assim, a saída que consta no extrato bancário é de R$ 489,65. | H66: Banco - Cora | I66: https://drive.google.com/file/d/1fJ5MoDApYbuZ0-i08Ve74EUfw5HxXMgj/view?usp=drive_link https://drive.google.com/file/d/19lDNPlUGVTADLU58r4994kd3o-tuJv-z/view?usp=drive_link
B67: Bolo | C67: 18 | D67: OK | E67: 0 | F67: 220 | G67: No extrato do banco constará apenas uma transferêncian no valor de R$ 164,63, pois do valor de R$ 220,00 foi descontada a mensalidade de dezembro no valor de R$ 55,37. Com isso, a saída que consta no extrato do banco é de R$ 164,63. | H67: Banco - Cora | I67: https://drive.google.com/file/d/1qLpnSY08jJAk3CFmmsoIEDw0Xywt6fEt/view?usp=drive_link
B68: Despesa 3 | E68: 0 | F68: 0
B69: Despesa 4 | E69: 0 | F69: 0
B70: Despesa 5 | E70: 0 | F70: 0
B71: Despesa 6 | E71: 0 | F71: 0
B72: Despesa 7 | E72: 0 | F72: 0
B73: Despesa 8 | E73: 0 | F73: 0
B74: Despesa 9 | E74: 0 | F74: 0
B75: Auto de Natal | E75: =SUM(E76:E84) -> 0 | F75: =SUM(F76:F84) -> 445.56
B76: Aluguel de roupas, decoração e outros | C76: 21 | D76: OK | E76: 0 | F76: 445.56 | G76: Não consta esta saída no extrato bancário pois este valor foi descontado da mensalidade do Davi Florência e Lindayana, referente às mensalidades de dezembro/23 e janeiro/24. | H76: Banco - Cora | I76: https://drive.google.com/file/d/1xc_buoMPmLg1YUP_RRXDtoeCLwFWHc__/view?usp=drive_link
B77: Despesa 2 | E77: 0 | F77: 0
B78: Despesa 3 | E78: 0 | F78: 0
B79: Despesa 4 | E79: 0 | F79: 0
B80: Despesa 5 | E80: 0 | F80: 0
B81: Despesa 6 | E81: 0 | F81: 0
B82: Despesa 7 | E82: 0 | F82: 0
B83: Despesa 8 | E83: 0 | F83: 0
B84: Despesa 9 | E84: 0 | F84: 0
B85: Evento 3 | E85: =SUM(E86:E94) -> 0 | F85: =SUM(F86:F94) -> 0
B86: Despesa 1 | E86: 0 | F86: 0
B87: Despesa 2 | E87: 0 | F87: 0
B88: Despesa 3 | E88: 0 | F88: 0
B89: Despesa 4 | E89: 0 | F89: 0
B90: Despesa 5 | E90: 0 | F90: 0
B91: Despesa 6 | E91: 0 | F91: 0
B92: Despesa 7 | E92: 0 | F92: 0
B93: Despesa 8 | E93: 0 | F93: 0
B94: Despesa 9 | E94: 0 | F94: 0
B95: FR Bilhete Aéreo | C95: - | D95: - | E95: =SUM(E96:E104) -> 0 | F95: =SUM(F96:F104) -> 0
B96: Bilhete Aéreo Gerusa | E96: 0 | F96: 0
B97: Bilhete Aéreo Gerusa | E97: 0 | F97: 0
B98: Despesa 3 | E98: 0 | F98: 0
B99: Despesa 4 | E99: 0 | F99: 0
B100: Despesa 5 | E100: 0 | F100: 0
B101: Despesa 6 | E101: 0 | F101: 0
B102: Despesa 7 | E102: 0 | F102: 0
...

Sheet JAN-Receitas
B2: RECEITAS
B4: TOTAL | E4: =SUM(E6,E127,E148,E168,E172) -> 17447.43 | F4: =SUM(F6,F127,F148,F168,F172) -> 49292.99 | H4: CAIXA | I4: PLANO DE CONTAS DG
C5: Data | D5: Efetivado | E5: Valor Previsto | F5: Valor Recebido | G5: Observação | J5: Inadimp. (qtd) | K5: Inadimp. (R$) | L5: % Atraso | M5: Núcleo | N5: Repasse DG | O5: Repasse 11a R | P5: Benef. NLT | Q5: NE NLT | R5: Plantio NLT | S5: FR Bilhete Aéreo | T5: FR Construção | U5: Taxa Extra | V5: Detalhamento Taxa Extra | X5: A receber:
B6: Mensalidade | C6: 10 | D6: - | E6: =SUM(E7:E126) -> 17447.43 | F6: =SUMIF(D7:D126,"OK",F7:F126)+SUMIF(D7:D126,"Parcial",F7:F126) -> 13383.98 | G6: - | J6: =(COUNTIF(D7:D126,"Pendente")+COUNTIF(D7:D126,"Parcial"))/COUNTA(B7:B126) -> 0.31632653 | K6: =IFERROR(-(X6/E6),"Pendente info") -> 0.25623029 | L6: =SUM(L7:L105)/COUNTA(B7:B105) -> 0.19387755 | M6: =SUMIF($D$7:$D$126,"OK",M7:M126)+SUMIF($D$7:$D$126,"Parcial",M7:M126) -> 7065 | N6: =SUMIF($D$7:$D$126,"OK",N7:N126)+SUMIF($D$7:$D$126,"Parcial",N7:N126) -> 1621.62 | O6: =SUMIF($D$7:$D$126,"OK",O7:O126)+SUMIF($D$7:$D$126,"Parcial",O7:O126) -> 792 | P6: =SUMIF($D$7:$D$126,"OK",P7:P126)+SUMIF($D$7:$D$126,"Parcial",P7:P126) -> 152.36 | Q6: =SUMIF($D$7:$D$126,"OK",Q7:Q126)+SUMIF($D$7:$D$126,"Parcial",Q7:Q126) -> 155 | R6: =SUMIF($D$7:$D$126,"OK",R7:R126)+SUMIF($D$7:$D$126,"Parcial",R7:R126) -> 185 | S6: =SUMIF($D$7:$D$126,"OK",S7:S126)+SUMIF($D$7:$D$126,"Parcial",S7:S126) -> 217 | T6: =SUMIF($D$7:$D$126,"OK",T7:T126)+SUMIF($D$7:$D$126,"Parcial",T7:T126) -> 580 | U6: =SUMIF($D$7:$D$126,"OK",U7:U126)+SUMIF($D$7:$D$126,"Parcial",U7:U126) -> 2616 | V6: - | W6: =IF(F6=SUM(M6:U6),"OK","Diferente") -> OK | X6: =SUM(X7:X126) -> -4470.56
B7: ELPÍDIO GOMES DE MOURA NETO | D7: OK | E7: =SUM(M7:U7) -> 0 | L7: =IF(C7>=13,1,"") | V7: TAXA CONFRATERNIZAÇÃO 2024 R$ 5,00; TAXA DE PREPARO 1/2 R$ 13,00 | W7: =IF(F7=SUM(M7:U7),"OK","Diferente") -> OK | X7: =IF(W7="Diferente",F7-SUM(M7:U7),"")
B8: JULIANA COLLYER ARRUDA DE MOURA | D8: OK | E8: =SUM(M8:U8) -> 0 | L8: =IF(C8>=13,1,"") | V8: TAXA CONFRATERNIZAÇÃO 2024 R$ 5,00; TAXA DE PREPARO 1/2 R$ 13,00 | W8: =IF(F8=SUM(M8:U8),"OK","Diferente") -> OK | X8: =IF(W8="Diferente",F8-SUM(M8:U8),"")
B9: SILVERIA LOPES VASCONCELOS ARRUDA | D9: OK | E9: =SUM(M9:U9) -> 0 | L9: =IF(C9>=13,1,"") | V9: TAXA CONFRATERNIZAÇÃO 2024 R$ 5,00; TAXA DE PREPARO 1/2 R$ 13,00 | W9: =IF(F9=SUM(M9:U9),"OK","Diferente") -> OK | X9: =IF(W9="Diferente",F9-SUM(M9:U9),"")
B10: FRANCISCO DE ASSIS VASCONCELOS ARRUDA | D10: OK | E10: =SUM(M10:U10) -> 0 | L10: =IF(C10>=13,1,"") | V10: TAXA CONFRATERNIZAÇÃO 2024 R$ 5,00; TAXA DE PREPARO 1/2 R$ 13,00 | W10: =IF(F10=SUM(M10:U10),"OK","Diferente") -> OK | X10: =IF(W10="Diferente",F10-SUM(M10:U10),"")
B11: ANTÔNIO GONÇALVES DE LIMA FILHO | C11: 10 | D11: OK | E11: =SUM(M11:U11) -> 193.43 | F11: =E11 -> 193.43 | H11: Banco - Cora | L11: =IF(C11>=13,1,"") | M11: 130 | N11: 24.57 | O11: 12 | P11: 3.86 | Q11: 5 | U11: 18 | V11: TAXA CONFRATERNIZAÇÃO 2024 R$ 5,00; TAXA DE PREPARO 1/2 R$ 13,00 | W11: =IF(F11=SUM(M11:U11),"OK","Diferente") -> OK | X11: =IF(W11="Diferente",F11-SUM(M11:U11),"")
B12: SANDRA BORGES GONÇALVES DE LIMA | C12: 10 | D12: OK | E12: =SUM(M12:U12) -> 186.57 | F12: =E12 -> 186.57 | H12: Banco - Cora | L12: =IF(C12>=13,1,"") | M12: 130 | N12: 24.57 | O12: 12 | P12: 2 | U12: 18 | V12: TAXA CONFRATERNIZAÇÃO 2024 R$ 5,00; TAXA DE PREPARO 1/2 R$ 13,00 | W12: =IF(F12=SUM(M12:U12),"OK","Diferente") -> OK | X12: =IF(W12="Diferente",F12-SUM(M12:U12),"")
B13: MARCELO DE CASTRO BRASIL | D13: Pendente | E13: =SUM(M13:U13) -> 366.49 | L13: =IF(C13>=13,1,"") | M13: 130.48 | N13: 24.57 | O13: 12 | P13: 1.44 | Q13: 10 | R13: 20 | S13: 50 | T13: 50 | U13: 68 | V13: COMPRA DE ARCONDICIONADO 7/10 R$ 50,00; TAXA CONFRATERNIZAÇÃO 2024 R$ 5,00; TAXA DE PREPARO 1/2 R$ 13,00 | W13: =IF(F13=SUM(M13:U13),"OK","Diferente") -> Diferente | X13: =IF(W13="Diferente",F13-SUM(M13:U13),"") -> -366.49
B14: FLORA BORGES GONÇALVES LIMA BRASIL | D14: Pendente | E14: =SUM(M14:U14) -> 209.29 | L14: =IF(C14>=13,1,"") | M14: 98.28 | N14: 24.57 | O14: 12 | P14: 1.44 | Q14: 5 | T14: 50 | U14: 18 | V14: TAXA CONFRATERNIZAÇÃO 2024 R$ 5,00; TAXA DE PREPARO 1/2 R$ 13,00 | W14: =IF(F14=SUM(M14:U14),"OK","Diferente") -> Diferente | X14: =IF(W14="Diferente",F14-SUM(M14:U14),"") -> -209.29
B15: CÁSSIO PEREIRA COSTA SOUSA | D15: Pendente | E15: =SUM(M15:U15) -> 316.14 | L15: =IF(C15>=13,1,"") | M15: 180.13 | N15: 24.57 | O15: 12 | P15: 1.44 | Q15: 5 | R15: 5 | S15: 20 | U15: 68 | V15: COMPRA DE ARCONDICIONADO 7/10 R$ 50,00; TAXA CONFRATERNIZAÇÃO 2024 R$ 5,00; TAXA DE PREPARO 1/2 R$ 13,00 | W15: =IF(F15=SUM(M15:U15),"OK","Diferente") -> Diferente | X15: =IF(W15="Diferente",F15-SUM(M15:U15),"") -> -316.14
B16: MÔNICA DE ARAUJO CAMPOS COSTA SOUSA | D16: Pendente | E16: =SUM(M16:U16) -> 155.99 | L16: =IF(C16>=13,1,"") | M16: 89.98 | N16: 24.57 | O16: 12 | P16: 1.44 | Q16: 5 | R16: 5 | U16: 18 | V16: TAXA CONFRATERNIZAÇÃO 2024 R$ 5,00; TAXA DE PREPARO 1/2 R$ 13,00 | W16: =IF(F16=SUM(M16:U16),"OK","Diferente") -> Diferente | X16: =IF(W16="Diferente",F16-SUM(M16:U16),"") -> -155.99
B17: JOSÉ MAURÍCIO GUIMARÃES GOMES | C17: 10 | D17: OK | E17: =SUM(M17:U17) -> 252.19 | F17: =E17 -> 252.19 | H17: Banco - Cora | L17: =IF(C17>=13,1,"") | M17: 191.18 | N17: 24.57 | O17: 12 | P17: 1.44 | Q17: 5 | U17: 18 | V17: TAXA CONFRATERNIZAÇÃO 2024 R$ 5,00; TAXA DE PREPARO 1/2 R$ 13,00 | W17: =IF(F17=SUM(M17:U17),"OK","Diferente") -> OK | X17: =IF(W17="Diferente",F17-SUM(M17:U17),"")
B18: TICIANE ARAGAO DA SILVEIRA GOMES | C18: 10 | D18: OK | E18: =SUM(M18:U18) -> 191.99 | F18: =E18 -> 191.99 | H18: Banco - Cora | L18: =IF(C18>=13,1,"") | M18: 135.98 | N18: 24.57 | O18: 12 | P18: 1.44 | U18: 18 | V18: TAXA CONFRATERNIZAÇÃO 2024 R$ 5,00; TAXA DE PREPARO 1/2 R$ 13,00 | W18: =IF(F18=SUM(M18:U18),"OK","Diferente") -> OK | X18: =IF(W18="Diferente",F18-SUM(M18:U18),"")
B19: SERVULO SIDNEY GLADIUS PAIVA PIMENTEL | C19: 9 | D19: OK | E19: =SUM(M19:U19) -> 459.29 | F19: =E19 -> 459.29 | H19: Banco - Cora | L19: =IF(C19>=13,1,"") | M19: 328.28 | N19: 24.57 | O19: 12 | P19: 11.44 | Q19: 5 | R19: 10 | T19: 50 | U19: 18 | V19: TAXA CONFRATERNIZAÇÃO 2024 R$ 5,00; TAXA DE PREPARO 1/2 R$ 13,00 | W19: =IF(F19=SUM(M19:U19),"OK","Diferente") -> OK | X19: =IF(W19="Diferente",F19-SUM(M19:U19),"")
B20: MARIA DANIELLY RIOS DA SILVA PAIVA | C20: 9 | D20: OK | E20: =SUM(M20:U20) -> 449.29 | F20: =E20 -> 449.29 | H20: Banco - Cora | L20: =IF(C20>=13,1,"") | M20: 328.28 | N20: 24.57 | O20: 12 | P20: 1.44 | Q20: 5 | R20: 10 | T20: 50 | U20: 18 | V20: TAXA CONFRATERNIZAÇÃO 2024 R$ 5,00; TAXA DE PREPARO 1/2 R$ 13,00 | W20: =IF(F20=SUM(M20:U20),"OK","Diferente") -> OK | X20: =IF(W20="Diferente",F20-SUM(M20:U20),"")
B21: RÉGIS BEZERRA GOMES | C21: 11 | D21: OK | E21: =SUM(M21:U21) -> 266.99 | F21: =E21 -> 266.99 | H21: Banco - Cora | L21: =IF(C21>=13,1,"") | M21: 120.98 | N21: 24.57 | O21: 12 | P21: 1.44 | Q21: 5 | R21: 5 | T21: 30 | U21: 68 | V21: COMPRA DE ARCONDICIONADO 7/10 R$ 50,00; TAXA CONFRATERNIZAÇÃO 2024 R$ 5,00; TAXA DE PREPARO 1/2 R$ 13,00 | W21: =IF(F21=SUM(M21:U21),"OK","Diferente") -> OK | X21: =IF(W21="Diferente",F21-SUM(M21:U21),"")
B22: ANA CAROLINA DE OLIVEIRA MARTINS GOMES | C22: 11 | D22: OK | E22: =SUM(M22:U22) -> 193.59 | F22: =E22 -> 193.59 | H22: Banco - Cora | L22: =IF(C22>=13,1,"") | M22: 102.58 | N22: 24.57 | O22: 12 | P22: 1.44 | Q22: 5 | T22: 30 | U22: 18 | V22: TAXA CONFRATERNIZAÇÃO 2024 R$ 5,00; TAXA DE PREPARO 1/2 R$ 13,00 | W22: =IF(F22=SUM(M22:U22),"OK","Diferente") -> OK | X22: =IF(W22="Diferente",F22-SUM(M22:U22),"")
B23: LINDAYANA DE SOUZA FLORÊNCIO | D23: Pendente | E23: =SUM(M23:U23) -> 153.34 | L23: =IF(C23>=13,1,"") | M23: 37.33 | N23: 24.57 | O23: 12 | P23: 1.44 | Q23: 5 | R23: 5 | U23: 68 | V23: COMPRA DE ARCONDICIONADO 7/10 R$ 50,00; TAXA CONFRATERNIZAÇÃO 2024 R$ 5,00; TAXA DE PREPARO 1/2 R$ 13,00 | W23: =IF(F23=SUM(M23:U23),"OK","Diferente") -> Diferente | X23: =IF(W23="Diferente",F23-SUM(M23:U23),"") -> -153.34
B24: DAVI FLORENCIO DE SOUSA | D24: Pendente | E24: =SUM(M24:U24) -> 134.44 | L24: =IF(C24>=13,1,"") | M24: 53.43 | N24: 24.57 | O24: 12 | P24: 1.44 | Q24: 5 | R24: 5 | T24: 15 | U24: 18 | V24: TAXA CONFRATERNIZAÇÃO 2024 R$ 5,00; TAXA DE PREPARO 1/2 R$ 13,00 | W24: =IF(F24=SUM(M24:U24),"OK","Diferente") -> Diferente | X24: =IF(W24="Diferente",F24-SUM(M24:U24),"") -> -134.44
B25: JOAQUIM GARCEZ DE LIMA ROCHA | D25: Pendente | E25: =SUM(M25:U25) -> 203 | L25: =IF(C25>=13,1,"") | M25: 131.99 | N25: 24.57 | O25: 12 | P25: 6.44 | R25: 10 | U25: 18 | V25: TAXA CONFRATERNIZAÇÃO 2024 R$ 5,00; TAXA DE PREPARO 1/2 R$ 13,00 | W25: =IF(F25=SUM(M25:U25),"OK","Diferente") -> Diferente | X25: =IF(W25="Diferente",F25-SUM(M25:U25),"") -> -203
B26: FRANCISCO SAULO STUDART ALBUQUERQUE | D26: Pendente | E26: =SUM(M26:U26) -> 128 | L26: =IF(C26>=13,1,"") | M26: 71.43 | N26: 24.57 | O26: 12 | P26: 2 | U26: 18 | V26: TAXA CONFRATERNIZAÇÃO 2024 R$ 5,00; TAXA DE PREPARO 1/2 R$ 13,00 | W26: =IF(F26=SUM(M26:U26),"OK","Diferente") -> Diferente | X26: =IF(W26="Diferente",F26-SUM(M26:U26),"") -> -128
B27: FRANCO COSTA E SILVA | C27: 8 | D27: OK | E27: =SUM(M27:U27) -> 598 | F27: =E27 -> 598 | H27: Banco - Cora | L27: =IF(C27>=13,1,"") | M27: 131.99 | N27: 24.57 | O27: 12 | P27: 11.44 | Q27: 5 | R27: 5 | S27: 10 | T27: 30 | U27: 368 | V27: COMPRA DE ARCONDICIONADO 7/10 R$ 50,00; TAXA AÇÃO ENTRE AMIGOS 2/2 R$ 300,00; TAXA CONFRATERNIZAÇÃO 2024 R$ 5,00; TAXA DE PREPARO 1/2 R$ 13,00 | W27: =IF(F27=SUM(M27:U27),"OK","Diferente") -> OK | X27: =IF(W27="Diferente",F27-SUM(M27:U27),"")
B28: JULIANA SOARES MONTEIRO | C28: 8 | D28: OK | E28: =SUM(M28:U28) -> 238 | F28: =E28 -> 238 | H28: Banco - Cora | L28: =IF(C28>=13,1,"") | M28: 131.99 | N28: 24.57 | O28: 12 | P28: 1.44 | Q28: 5 | R28: 5 | S28: 10 | T28: 30 | U28: 18 | V28: TAXA CONFRATERNIZAÇÃO 2024 R$ 5,00; TAXA DE PREPARO 1/2 R$ 13,00 | W28: =IF(F28=SUM(M28:U28),"OK","Diferente") -> OK | X28: =IF(W28="Diferente",F28-SUM(M28:U28),"")
B29: HUGO UCHOA PASSOS ALENCAR | C29: 13 | D29: OK | E29: =SUM(M29:U29) -> 277.69 | F29: =E29 -> 277.69 | H29: Banco - Cora | L29: =IF(C29>=13,1,"") -> 1 | M29: 116.68 | N29: 24.57 | O29: 12 | P29: 1.44 | Q29: 5 | R29: 10 | S29: 10 | T29: 30 | U29: 68 | V29: COMPRA DE ARCONDICIONADO 7/10 R$ 50,00; TAXA CONFRATERNIZAÇÃO 2024 R$ 5,00; TAXA DE PREPARO 1/2 R$ 13,00 | W29: =IF(F29=SUM(M29:U29),"OK","Diferente") -> OK | X29: =IF(W29="Diferente",F29-SUM(M29:U29),"")
B30: MAIRI ALENCAR DE LACERDA FERRAZ UCHÔA | C30: 13 | D30: OK | E30: =SUM(M30:U30) -> 176.69 | F30: =E30 -> 176.69 | H30: Banco - Cora | L30: =IF(C30>=13,1,"") -> 1 | M30: 70.68 | N30: 24.57 | O30: 12 | P30: 1.44 | R30: 10 | S30: 10 | T30: 30 | U30: 18 | V30: TAXA CONFRATERNIZAÇÃO 2024 R$ 5,00; TAXA DE PREPARO 1/2 R$ 13,00 | W30: =IF(F30=SUM(M30:U30),"OK","Diferente") -> OK | X30: =IF(W30="Diferente",F30-SUM(M30:U30),"")
B31: JOÃO CARLOS STUDART ANTERO | D31: Pendente | E31: =SUM(M31:U31) -> 185.44 | L31: =IF(C31>=13,1,"") | M31: 104.43 | N31: 24.57 | O31: 12 | P31: 1.44 | Q31: 5 | S31: 10 | T31: 10 | U31: 18 | V31: TAXA CONFRATERNIZAÇÃO 2024 R$ 5,00; TAXA DE PREPARO 1/2 R$ 13,00 | W31: =IF(F31=SUM(M31:U31),"OK","Diferente") -> Diferente | X31: =IF(W31="Diferente",F31-SUM(M31:U31),"") -> -185.44
B32: JANAÍNA SILVA LEITÃO STUDART ANTERO | D32: Pendente | E32: =SUM(M32:U32) -> 185.44 | L32: =IF(C32>=13,1,"") | M32: 104.43 | N32: 24.57 | O32: 12 | P32: 1.44 | Q32: 5 | S32: 10 | T32: 10 | U32: 18 | V32: TAXA CONFRATERNIZAÇÃO 2024 R$ 5,00; TAXA DE PREPARO 1/2 R$ 13,00 | W32: =IF(F32=SUM(M32:U32),"OK","Diferente") -> Diferente | X32: =IF(W32="Diferente",F32-SUM(M32:U32),"") -> -185.44
B33: JANAINA DE PÁDUA CARNEIRO VASCONCELOS GIFFONI | C33: 10 | D33: OK | E33: =SUM(M33:U33) -> 217.01 | F33: =E33 -> 217.01 | H33: Banco - Cora | L33: =IF(C33>=13,1,"") | M33: 156 | N33: 24.57 | O33: 12 | P33: 1.44 | Q33: 5 | U33: 18 | V33: TAXA CONFRATERNIZAÇÃO 2024 R$ 5,00; TAXA DE PREPARO 1/2 R$ 13,00 | W33: =IF(F33=SUM(M33:U33),"OK","Diferente") -> OK | X33: =IF(W33="Diferente",F33-SUM(M33:U33),"")
B34: VICENTE ALVES GIFFONI | C34: 10 | D34: OK | E34: =SUM(M34:U34) -> 287.01 | F34: =E34 -> 287.01 | H34: Banco - Cora | L34: =IF(C34>=13,1,"") | M34: 156 | N34: 24.57 | O34: 12 | P34: 11.44 | Q34: 5 | R34: 10 | U34: 68 | V34: COMPRA DE ARCONDICIONADO 7/10 R$ 50,00; TAXA CONFRATERNIZAÇÃO 2024 R$ 5,00; TAXA DE PREPARO 1/2 R$ 13,00 | W34: =IF(F34=SUM(M34:U34),"OK","Diferente") -> OK | X34: =IF(W34="Diferente",F34-SUM(M34:U34),"")
B35: RAPHAEL BRUNO DANTAS MOREIRA | D35: Pendente | E35: =SUM(M35:U35) -> 198.2 | L35: =IF(C35>=13,1,"") | M35: 131.63 | N35: 24.57 | O35: 12 | P35: 10 | Q35: 5 | R35: 15 | V35: TAXA CONFRATERNIZAÇÃO 2024 R$ 5,00; TAXA DE PREPARO 1/2 R$ 13,00 | W35: =IF(F35=SUM(M35:U35),"OK","Diferente") -> Diferente | X35: =IF(W35="Diferente",F35-SUM(M35:U35),"") -> -198.2
B36: DAVI SILVINO MORAES | C36: 9 | D36: OK | E36: =SUM(M36:U36) -> 246.76 | F36: =E36 -> 246.76 | H36: Banco - Cora | L36: =IF(C36>=13,1,"") | M36: 132.19 | N36: 24.57 | O36: 12 | P36: 5 | Q36: 5 | R36: 10 | S36: 10 | T36: 30 | U36: 18 | V36: TAXA CONFRATERNIZAÇÃO 2024 R$ 5,00; TAXA DE PREPARO 1/2 R$ 13,00 | W36: =IF(F36=SUM(M36:U36),"OK","Diferente") -> OK | X36: =IF(W36="Diferente",F36-SUM(M36:U36),"")
B37: DIMARANJE JOSÉ MORAES | D37: Pendente | E37: =SUM(M37:U37) -> 130.81 | L37: =IF(C37>=13,1,"") | M37: 74.74 | N37: 24.57 | O37: 12 | P37: 1.5 | U37: 18 | V37: TAXA CONFRATERNIZAÇÃO 2024 R$ 5,00; TAXA DE PREPARO 1/2 R$ 13,00 | W37: =IF(F37=SUM(M37:U37),"OK","Diferente") -> Diferente | X37: =IF(W37="Diferente",F37-SUM(M37:U37),"") -> -130.81
B38: SILVANE DA SILVA GONÇALVES | D38: Pendente | E38: =SUM(M38:U38) -> 130.81 | L38: =IF(C38>=13,1,"") | M38: 74.74 | N38: 24.57 | O38: 12 | P38: 1.5 | U38: 18 | V38: TAXA CONFRATERNIZAÇÃO 2024 R$ 5,00; TAXA DE PREPARO 1/2 R$ 13,00 | W38: =IF(F38=SUM(M38:U38),"OK","Diferente") -> Diferente | X38: =IF(W38="Diferente",F38-SUM(M38:U38),"") -> -130.81
B39: VICENTE DE PAULA GIFFONI FILHO | C39: 9 | D39: OK | E39: =SUM(M39:U39) -> 164.44 | F39: =E39 -> 164.44 | H39: Banco - Cora | L39: =IF(C39>=13,1,"") | M39: 103.43 | N39: 24.57 | O39: 12 | P39: 1.44 | R39: 5 | U39: 18 | V39: TAXA CONFRATERNIZAÇÃO 2024 R$ 5,00; TAXA DE PREPARO 1/2 R$ 13,00 | W39: =IF(F39=SUM(M39:U39),"OK","Diferente") -> OK | X39: =IF(W39="Diferente",F39-SUM(M39:U39),"")
B40: FRANCINETE ALVES DE OLIVEIRA GIFFONI | C40: 9 | D40: OK | E40: =SUM(M40:U40) -> 169.44 | F40: =E40 -> 169.44 | H40: Banco - Cora | L40: =IF(C40>=13,1,"") | M40: 103.43 | N40: 24.57 | O40: 12 | P40: 1.44 | Q40: 5 | R40: 5 | U40: 18 | V40: TAXA CONFRATERNIZAÇÃO 2024 R$ 5,00; TAXA DE PREPARO 1/2 R$ 13,00 | W40: =IF(F40=SUM(M40:U40),"OK","Diferente") -> OK | X40: =IF(W40="Diferente",F40-SUM(M40:U40),"")
B41: EMANUEL ALVES GIFFONI | C41: 9 | D41: OK | E41: =SUM(M41:U41) -> 169.44 | F41: =E41 -> 169.44 | H41: Banco - Cora | L41: =IF(C41>=13,1,"") | M41: 103.43 | N41: 24.57 | O41: 12 | P41: 1.44 | Q41: 5 | R41: 5 | U41: 18 | V41: TAXA CONFRATERNIZAÇÃO 2024 R$ 5,00; TAXA DE PREPARO 1/2 R$ 13,00 | W41: =IF(F41=SUM(M41:U41),"OK","Diferente") -> OK | X41: =IF(W41="Diferente",F41-SUM(M41:U41),"")
B42: FLORA ALVES GIFFONI | C42: 9 | D42: OK | E42: =SUM(M42:U42) -> 87.59 | F42: =E42 -> 87.59 | H42: Banco - Cora | L42: =IF(C42>=13,1,"") | M42: 31.58 | N42: 24.57 | O42: 12 | P42: 1.44 | U42: 18 | V42: TAXA CONFRATERNIZAÇÃO 2024 R$ 5,00; TAXA DE PREPARO 1/2 R$ 13,00 | W42: =IF(F42=SUM(M42:U42),"OK","Diferente") -> OK | X42: =IF(W42="Diferente",F42-SUM(M42:U42),"")
B43: JÔNATAS CAVALCANTE BRAÚNA | D43: Pendente | E43: =SUM(M43:U43) -> 218 | L43: =IF(C43>=13,1,"") | M43: 151.99 | N43: 24.57 | O43: 12 | P43: 1.44 | R43: 5 | S43: 5 | U43: 18 | V43: TAXA CONFRATERNIZAÇÃO 2024 R$ 5,00; TAXA DE PREPARO 1/2 R$ 13,00 | W43: =IF(F43=SUM(M43:U43),"OK","Diferente") -> Diferente | X43: =IF(W43="Diferente",F43-SUM(M43:U43),"") -> -218
B44: LUCAS MAIA DANTAS | C44: 13 | D44: OK | E44: =SUM(M44:U44) -> 316.89 | F44: =E44 -> 316.89 | H44: Banco - Cora | L44: =IF(C44>=13,1,"") -> 1 | M44: 125.88 | N44: 24.57 | O44: 12 | P44: 1.44 | Q44: 5 | R44: 10 | S44: 20 | T44: 100 | U44: 18 | V44: TAXA CONFRATERNIZAÇÃO 2024 R$ 5,00; TAXA DE PREPARO 1/2 R$ 13,00 | W44: =IF(F44=SUM(M44:U44),"OK","Diferente") -> OK | X44: =IF(W44="Diferente",F44-SUM(M44:U44),"")
B45: EMANUELA CRISTINE PEREIRA FELIX DANTAS | C45: 13 | D45: OK | E45: =SUM(M45:U45) -> 180.44 | F45: =E45 -> 180.44 | H45: Banco - Cora | L45: =IF(C45>=13,1,"") -> 1 | M45: 99.43 | N45: 24.57 | O45: 12 | P45: 1.44 | Q45: 5 | S45: 20 | U45: 18 | V45: TAXA CONFRATERNIZAÇÃO 2024 R$ 5,00; TAXA DE PREPARO 1/2 R$ 13,00 | W45: =IF(F45=SUM(M45:U45),"OK","Diferente") -> OK | X45: =IF(W45="Diferente",F45-SUM(M45:U45),"")
B46: LUCAS CALDAS OLIVEIRA | C46: 8 | D46: OK | E46: =SUM(M46:U46) -> 170 | F46: =E46 -> 170 | H46: Banco - Cora | L46: =IF(C46>=13,1,"") | M46: 93.43 | N46: 24.57 | O46: 12 | P46: 2 | Q46: 5 | R46: 5 | S46: 10 | U46: 18 | V46: TAXA CONFRATERNIZAÇÃO 2024 R$ 5,00; TAXA DE PREPARO 1/2 R$ 13,00 | W46: =IF(F46=SUM(M46:U46),"OK","Diferente") -> OK | X46: =IF(W46="Diferente",F46-SUM(M46:U46),"")
B47: GABRIELA ARAUJO HOLANDA PINTO | C47: 8 | D47: OK | E47: =SUM(M47:U47) -> 105 | F47: =E47 -> 105 | H47: Banco - Cora | L47: =IF(C47>=13,1,"") | M47: 43.93 | N47: 24.57 | O47: 12 | P47: 1.5 | S47: 5 | U47: 18 | V47: TAXA CONFRATERNIZAÇÃO 2024 R$ 5,00; TAXA DE PREPARO 1/2 R$ 13,00 | W47: =IF(F47=SUM(M47:U47),"OK","Diferente") -> OK | X47: =IF(W47="Diferente",F47-SUM(M47:U47),"")
B48: VALTERLIR PEREIRA DE LIMA | D48: Pendente | E48: =SUM(M48:U48) -> 249.99 | L48: =IF(C48>=13,1,"") | M48: 118.98 | N48: 24.57 | O48: 12 | P48: 11.44 | Q48: 5 | R48: 10 | U48: 68 | V48: COMPRA DE ARCONDICIONADO 7/10 R$ 50,00; TAXA CONFRATERNIZAÇÃO 2024 R$ 5,00; TAXA DE PREPARO 1/2 R$ 13,00 | W48: =IF(F48=SUM(M48:U48),"OK","Diferente") -> Diferente | X48: =IF(W48="Diferente",F48-SUM(M48:U48),"") -> -249.99
B49: MARIA LUCIA FERREIRA DA SILVA LIMA | D49: Pendente | E49: =SUM(M49:U49) -> 111.74 | L49: =IF(C49>=13,1,"") | M49: 55.73 | N49: 24.57 | O49: 12 | P49: 1.44 | U49: 18 | V49: TAXA CONFRATERNIZAÇÃO 2024 R$ 5,00; TAXA DE PREPARO 1/2 R$ 13,00 | W49: =IF(F49=SUM(M49:U49),"OK","Diferente") -> Diferente | X49: =IF(W49="Diferente",F49-SUM(M49:U49),"") -> -111.74
B50: SALOMÃO JOSÉ MARQUES MACIEL | C50: 8 | D50: OK | E50: =SUM(M50:U50) -> 112.76 | F50: =E50 -> 112.76 | H50: Banco - Cora | L50: =IF(C50>=13,1,"") | M50: 58.19 | N50: 24.57 | O50: 12 | P50: - | Q50: - | R50: - | S50: - | U50: 18 | V50: TAXA CONFRATERNIZAÇÃO 2024 R$ 5,00; TAXA DE PREPARO 1/2 R$ 13,00 | W50: =IF(F50=SUM(M50:U50),"OK","Diferente") -> OK | X50: =IF(W50="Diferente",F50-SUM(M50:U50),"")
B51: ANA CLARA SIMONETTI GOMES MACIEL | C51: 8 | D51: OK | E51: =SUM(M51:U51) -> 88.45 | F51: =E51 -> 88.45 | H51: Banco - Cora | L51: =IF(C51>=13,1,"") | M51: 33.88 | N51: 24.57 | O51: 12 | P51: - | R51: - | U51: 18 | V51: TAXA CONFRATERNIZAÇÃO 2024 R$ 5,00; TAXA DE PREPARO 1/2 R$ 13,00 | W51: =IF(F51=SUM(M51:U51),"OK","Diferente") -> OK | X51: =IF(W51="Diferente",F51-SUM(M51:U51),"")
B52: RAFAEL LUNA HONÓRIO | C52: 22 | D52: OK | E52: =SUM(M52:U52) -> 409.69 | F52: =E52 -> 409.69 | H52: Banco - Cora | L52: =IF(C52>=13,1,"") -> 1 | M52: 93.62 | N52: 24.57 | O52: 12 | P52: 1.5 | S52: 10 | U52: 268 | V52: COMPRA DE ARCONDICIONADO 7/10 R$ 50,00; TAXA AÇÃO ENTRE AMIGOS 2/2 R$ 200,00; TAXA CONFRATERNIZAÇÃO 2024 R$ 5,00; TAXA DE PREPARO 1/2 R$ 13,00 | W52: =IF(F52=SUM(M52:U52),"OK","Diferente") -> OK | X52: =IF(W52="Diferente",F52-SUM(M52:U52),"")
B53: JULIA ROGERIO FIORE CHEUEN | C53: 22 | D53: OK | E53: =SUM(M53:U53) -> 149.69 | F53: =E53 -> 149.69 | H53: Banco - Cora | L53: =IF(C53>=13,1,"") -> 1 | M53: 93.62 | N53: 24.57 | O53: 12 | P53: 1.5 | U53: 18 | V53: TAXA CONFRATERNIZAÇÃO 2024 R$ 5,00; TAXA DE PREPARO 1/2 R$ 13,00 | W53: =IF(F53=SUM(M53:U53),"OK","Diferente") -> OK | X53: =IF(W53="Diferente",F53-SUM(M53:U53),"")
B54: ISABELA CLAREANA PEREIRA FELIX | C54: 9 | D54: OK | E54: =SUM(M54:U54) -> 200.44 | F54: =E54 -> 200.44 | H54: Banco - Cora | L54: =IF(C54>=13,1,"") | M54: 139.43 | N54: 24.57 | O54: 12 | P54: 1.44 | Q54: 5 | U54: 18 | V54: TAXA CONFRATERNIZAÇÃO 2024 R$ 5,00; TAXA DE PREPARO 1/2 R$ 13,00 | W54: =IF(F54=SUM(M54:U54),"OK","Diferente") -> OK | X54: =IF(W54="Diferente",F54-SUM(M54:U54),"")
B55: PEDRO KLECIUS FARIAS CARDOSO | C55: 8 | D55: OK | E55: =SUM(M55:U55) -> 664.29 | F55: =E55 -> 664.29 | H55: Banco - Cora | L55: =IF(C55>=13,1,"") | M55: 98.28 | N55: 24.57 | O55: 12 | P55: 1.44 | R55: 10 | T55: 100 | U55: 418 | V55: DOAÇÃO COZINHA 4/4 R$ 400,00; TAXA CONFRATERNIZAÇÃO 2024 R$ 5,00; TAXA DE PREPARO 1/2 R$ 13,00 | W55: =IF(F55=SUM(M55:U55),"OK","Diferente") -> OK | X55: =IF(W55="Diferente",F55-SUM(M55:U55),"")
B56: GENILDA DA SILVA CARDOSO | C56: 8 | D56: OK | E56: =SUM(M56:U56) -> 164.29 | F56: =E56 -> 164.29 | H56: Banco - Cora | L56: =IF(C56>=13,1,"") | M56: 98.28 | N56: 24.57 | O56: 12 | P56: 1.44 | R56: 10 | U56: 18 | V56: TAXA CONFRATERNIZAÇÃO 2024 R$ 5,00; TAXA DE PREPARO 1/2 R$ 13,00 | W56: =IF(F56=SUM(M56:U56),"OK","Diferente") -> OK | X56: =IF(W56="Diferente",F56-SUM(M56:U56),"")
B57: MANOEL MESSIAS DO NASCIMENTO NETO | C57: 17 | D57: OK | E57: 75 | F57: =SUM(M57:U57) -> 175 | H57: Banco - Cora | L57: =IF(C57>=13,1,"") -> 1 | M57: =13.93+100 -> 113.93 | N57: 24.57 | O57: 12 | P57: 1.5 | Q57: 5 | U57: 18 | V57: TAXA CONFRATERNIZAÇÃO 2024 R$ 5,00; TAXA DE PREPARO 1/2 R$ 13,00 | W57: =IF(F57=SUM(M57:U57),"OK","Diferente") -> OK | X57: =IF(W57="Diferente",F57-SUM(M57:U57),"")
B58: BRANDA DE PÁDUA CARNEIRO VASCONCELOS LESSA | C58: 9 | D58: OK | E58: =SUM(M58:U58) -> 168.5 | F58: =E58 -> 168.5 | H58: Banco - Cora | L58: =IF(C58>=13,1,"") | M58: 93.43 | N58: 24.57 | O58: 12 | P58: 1.5 | R58: 10 | S58: 4 | T58: 5 | U58: 18 | V58: TAXA CONFRATERNIZAÇÃO 2024 R$ 5,00; TAXA DE PREPARO 1/2 R$ 13,00 | W58: =IF(F58=SUM(M58:U58),"OK","Diferente") -> OK | X58: =IF(W58="Diferente",F58-SUM(M58:U58),"")
B59: MATEUS CHAVES LESSA DE CASTRO | C59: 9 | D59: OK | E59: =SUM(M59:U59) -> 167.5 | F59: =E59 -> 167.5 | H59: Banco - Cora | L59: =IF(C59>=13,1,"") | M59: 93.43 | N59: 24.57 | O59: 12 | P59: 1.5 | R59: 10 | S59: 3 | T59: 5 | U59: 18 | V59: TAXA CONFRATERNIZAÇÃO 2024 R$ 5,00; TAXA DE PREPARO 1/2 R$ 13,00 | W59: =IF(F59=SUM(M59:U59),"OK","Diferente") -> OK | X59: =IF(W59="Diferente",F59-SUM(M59:U59),"")
B60: ROSSYANE MARIA OLIVEIRA DA COSTA | C60: 8 | D60: OK | E60: =SUM(M60:U60) -> 100 | F60: =E60 -> 100 | H60: Banco - Cora | L60: =IF(C60>=13,1,"") | M60: 61.93 | N60: 24.57 | O60: 12 | P60: 1.5 | W60: =IF(F60=SUM(M60:U60),"OK","Diferente") -> OK | X60: =IF(W60="Diferente",F60-SUM(M60:U60),"")
B61: ALINE MIRANDA DE OLIVEIRA | C61: 4 | D61: Parcial | E61: 80.37 | F61: =SUM(M61:U61) -> 363.48 | H61: Banco - Pagbank | L61: =IF(C61>=13,1,"") | M61: =19.36+283.11 -> 302.47 | N61: 24.57 | O61: 12 | P61: 1.44 | Q61: 5 | U61: 18 | V61: TAXA CONFRATERNIZAÇÃO 2024 R$ 5,00; TAXA DE PREPARO 1/2 R$ 13,00 | W61: =IF(F61=SUM(M61:U61),"OK","Diferente") -> OK | X61: =IF(W61="Diferente",F61-SUM(M61:U61),"")
B62: ANTÔNIO RAMON DA SILVA MAIA | D62: Pendente | E62: =SUM(M62:U62) -> 90.75 | L62: =IF(C62>=13,1,"") | M62: 29.74 | N62: 24.57 | O62: 12 | P62: 1.44 | Q62: 5 | U62: 18 | V62: TAXA CONFRATERNIZAÇÃO 2024 R$ 5,00; TAXA DE PREPARO 1/2 R$ 13,00 | W62: =IF(F62=SUM(M62:U62),"OK","Diferente") -> Diferente | X62: =IF(W62="Diferente",F62-SUM(M62:U62),"") -> -90.75
B63: RAFAELY MAIA SOMBRA CORDEIRO | D63: Pendente | E63: =SUM(M63:U63) -> 91 | L63: =IF(C63>=13,1,"") | M63: 29.93 | N63: 24.57 | O63: 12 | P63: 1.5 | Q63: 5 | U63: 18 | V63: TAXA CONFRATERNIZAÇÃO 2024 R$ 5,00; TAXA DE PREPARO 1/2 R$ 13,00 | W63: =IF(F63=SUM(M63:U63),"OK","Diferente") -> Diferente | X63: =IF(W63="Diferente",F63-SUM(M63:U63),"") -> -91
B64: FRANCISCO HILTON DOS SANTOS JÚNIOR | C64: 13 | D64: OK | E64: =SUM(M64:U64) -> 168 | F64: =E64 -> 168 | H64: Banco - Cora | L64: =IF(C64>=13,1,"") -> 1 | M64: 61.99 | N64: 24.57 | O64: 12 | P64: 1.44 | U64: 68 | V64: TAXA AÇÃO ENTRE AMIGOS 2/4 R$ 50,00; TAXA CONFRATERNIZAÇÃO 2024 R$ 5,00; TAXA DE PREPARO 1/2 R$ 13,00 | W64: =IF(F64=SUM(M64:U64),"OK","Diferente") -> OK | X64: =IF(W64="Diferente",F64-SUM(M64:U64),"")
B65: MANOEL EDINI DE AGUIAR | C65: 10 | D65: OK | E65: =SUM(M65:U65) -> 78 | F65: =E65 -> 78 | H65: Banco - Cora | L65: =IF(C65>=13,1,"") | M65: 21.93 | N65: 24.57 | O65: 12 | P65: 1.5 | U65: 18 | V65: TAXA CONFRATERNIZAÇÃO 2024 R$ 5,00; TAXA DE PREPARO 1/2 R$ 13,00 | W65: =IF(F65=SUM(M65:U65),"OK","Diferente") -> OK | X65: =IF(W65="Diferente",F65-SUM(M65:U65),"")
B66: FÁBIO DE FÁRIAS FEITOSA | C66: 13 | D66: OK | E66: =SUM(M66:U66) -> 185 | F66: =E66 -> 185 | H66: Banco - Cora | L66: =IF(C66>=13,1,"") -> 1 | M66: 102.43 | N66: 24.57 | O66: 12 | P66: 3 | Q66: 15 | S66: 10 | U66: 18 | V66: TAXA CONFRATERNIZAÇÃO 2024 R$ 5,00; TAXA DE PREPARO 1/2 R$ 13,00 | W66: =IF(F66=SUM(M66:U66),"OK","Diferente") -> OK | X66: =IF(W66="Diferente",F66-SUM(M66:U66),"")
B67: IANNA DARC GOMES MARTINS | D67: Pendente | E67: =SUM(M67:U67) -> 156.07 | L67: =IF(C67>=13,1,"") | M67: 100 | N67: 24.57 | O67: 12 | P67: 1.5 | U67: 18 | V67: TAXA CONFRATERNIZAÇÃO 2024 R$ 5,00; TAXA DE PREPARO 1/2 R$ 13,00 | W67: =IF(F67=SUM(M67:U67),"OK","Diferente") -> Diferente | X67: =IF(W67="Diferente",F67-SUM(M67:U67),"") -> -156.07
B68: MARCIO WALLACE EVANGELISTA TEIXEIRA | C68: 8 | D68: OK | E68: =SUM(M68:U68) -> 286.82 | F68: =E68 -> 286.82 | H68: Banco - Cora | L68: =IF(C68>=13,1,"") | M68: 122.25 | N68: 24.57 | O68: 12 | P68: 10 | Q68: 5 | R68: 5 | S68: 15 | T68: 25 | U68: 68 | V68: COMPRA DE ARCONDICIONADO 7/10 R$ 50,00; TAXA CONFRATERNIZAÇÃO 2024 R$ 5,00; TAXA DE PREPARO 1/2 R$ 13,00 | W68: =IF(F68=SUM(M68:U68),"OK","Diferente") -> OK | X68: =IF(W68="Diferente",F68-SUM(M68:U68),"")
B69: JULIANA DIAS PERDIGÃO TEIXEIRA | C69: 8 | D69: OK | E69: =SUM(M69:U69) -> 236.82 | F69: =E69 -> 236.82 | H69: Banco - Cora | L69: =IF(C69>=13,1,"") | M69: 122.25 | N69: 24.57 | O69: 12 | P69: 10 | Q69: 5 | R69: 5 | S69: 15 | T69: 25 | U69: 18 | V69: TAXA CONFRATERNIZAÇÃO 2024 R$ 5,00; TAXA DE PREPARO 1/2 R$ 13,00 | W69: =IF(F69=SUM(M69:U69),"OK","Diferente") -> OK | X69: =IF(W69="Diferente",F69-SUM(M69:U69),"")
B70: MATEUS DE MIRANDA DINO | C70: 27 | D70: OK | E70: =SUM(M70:U70) -> 199.44 | F70: =E70 -> 199.44 | H70: Banco - Cora | L70: =IF(C70>=13,1,"") -> 1 | M70: 113.43 | N70: 24.57 | O70: 12 | P70: 1.44 | Q70: 5 | R70: 20 | S70: 5 | U70: 18 | V70: TAXA CONFRATERNIZAÇÃO 2024 R$ 5,00; TAXA DE PREPARO 1/2 R$ 13,00 | W70: =IF(F70=SUM(M70:U70),"OK","Diferente") -> OK | X70: =IF(W70="Diferente",F70-SUM(M70:U70),"")
B71: VITOR SANTOS DE OLIVEIRA | C71: 13 | D71: OK | E71: =SUM(M71:U71) -> 83.67 | F71: =E71 -> 83.67 | H71: Banco - Cora | L71: =IF(C71>=13,1,"") -> 1 | M71: 27.66 | N71: 24.57 | O71: 12 | P71: 1.44 | U71: 18 | V71: TAXA CONFRATERNIZAÇÃO 2024 R$ 5,00; TAXA DE PREPARO 1/2 R$ 13,00 | W71: =IF(F71=SUM(M71:U71),"OK","Diferente") -> OK | X71: =IF(W71="Diferente",F71-SUM(M71:U71),"")
B72: CARMEM SILVIA DE CARVALHO RÊGO | C72: 13 | D72: OK | E72: =SUM(M72:U72) -> 138 | F72: =E72 -> 138 | H72: Banco - Cora | L72: =IF(C72>=13,1,"") -> 1 | M72: 81.93 | N72: 24.57 | O72: 12 | P72: 1.5 | U72: 18 | V72: TAXA CONFRATERNIZAÇÃO 2024 R$ 5,00; TAXA DE PREPARO 1/2 R$ 13,00 | W72: =IF(F72=SUM(M72:U72),"OK","Diferente") -> OK | X72: =IF(W72="Diferente",F72-SUM(M72:U72),"")
B73: ANTONIO GILARDO XAVIER DE OLIVEIRA | D73: Pendente | E73: =SUM(M73:U73) -> 70 | L73: =IF(C73>=13,1,"") | M73: 13.93 | N73: 24.57 | O73: 12 | P73: 1.5 | U73: 18 | V73: TAXA CONFRATERNIZAÇÃO 2024 R$ 5,00; TAXA DE PREPARO 1/2 R$ 13,00 | W73: =IF(F73=SUM(M73:U73),"OK","Diferente") -> Diferente | X73: =IF(W73="Diferente",F73-SUM(M73:U73),"") -> -70
B74: MARIA EUZANIRA BARBOSA OLIVEIRA | D74: Pendente | E74: =SUM(M74:U74) -> 70 | L74: =IF(C74>=13,1,"") | M74: 13.93 | N74: 24.57 | O74: 12 | P74: 1.5 | U74: 18 | V74: TAXA CONFRATERNIZAÇÃO 2024 R$ 5,00; TAXA DE PREPARO 1/2 R$ 13,00 | W74: =IF(F74=SUM(M74:U74),"OK","Diferente") -> Diferente | X74: =IF(W74="Diferente",F74-SUM(M74:U74),"") -> -70
B75: THAMIRES CALDAS OLIVEIRA | C75: 10 | D75: OK | E75: =SUM(M75:U75) -> 118 | F75: =E75 -> 118 | H75: Banco - Cora | L75: =IF(C75>=13,1,"") | M75: 56.93 | N75: 24.57 | O75: 12 | P75: 1.5 | Q75: 5 | U75: 18 | V75: TAXA CONFRATERNIZAÇÃO 2024 R$ 5,00; TAXA DE PREPARO 1/2 R$ 13,00 | W75: =IF(F75=SUM(M75:U75),"OK","Diferente") -> OK | X75: =IF(W75="Diferente",F75-SUM(M75:U75),"")
B76: MARIA JOSILENE BEZERRA | C76: 10 | D76: OK | E76: =SUM(M76:U76) -> 218 | F76: =E76 -> 218 | H76: Banco - Cora | L76: =IF(C76>=13,1,"") | M76: 148.43 | N76: 24.57 | O76: 12 | P76: 5 | Q76: 10 | U76: 18 | V76: TAXA CONFRATERNIZAÇÃO 2024 R$ 5,00; TAXA DE PREPARO 1/2 R$ 13,00 | W76: =IF(F76=SUM(M76:U76),"OK","Diferente") -> OK | X76: =IF(W76="Diferente",F76-SUM(M76:U76),"")
B77: WLLYSSES JOSE MARQUES MACIEL | D77: Pendente | E77: =SUM(M77:U77) -> 75.39 | L77: =IF(C77>=13,1,"") | M77: 19.32 | N77: 24.57 | O77: 12 | P77: 1.5 | U77: 18 | V77: TAXA CONFRATERNIZAÇÃO 2024 R$ 5,00; TAXA DE PREPARO 1/2 R$ 13,00 | W77: =IF(F77=SUM(M77:U77),"OK","Diferente") -> Diferente | X77: =IF(W77="Diferente",F77-SUM(M77:U77),"") -> -75.39
B78: DAILANE DE SOUZA FLORÊNCIO | C78: 13 | D78: OK | E78: =SUM(M78:U78) -> 85.74 | F78: =E78 -> 85.74 | H78: Banco - Cora | L78: =IF(C78>=13,1,"") -> 1 | M78: 29.67 | N78: 24.57 | O78: 12 | P78: 1.5 | U78: 18 | V78: TAXA CONFRATERNIZAÇÃO 2024 R$ 5,00; TAXA DE PREPARO 1/2 R$ 13,00 | W78: =IF(F78=SUM(M78:U78),"OK","Diferente") -> OK | X78: =IF(W78="Diferente",F78-SUM(M78:U78),"")
B79: SAMUEL DANTAS MOREIRA | D79: Pendente | E79: =SUM(M79:U79) -> 112.43 | L79: =IF(C79>=13,1,"") | M79: 50.86 | N79: 24.57 | O79: 12 | P79: 2 | Q79: 5 | U79: 18 | V79: TAXA CONFRATERNIZAÇÃO 2024 R$ 5,00; TAXA DE PREPARO 1/2 R$ 13,00 | W79: =IF(F79=SUM(M79:U79),"OK","Diferente") -> Diferente | X79: =IF(W79="Diferente",F79-SUM(M79:U79),"") -> -112.43
B80: LORENA RODRIGUES SALES DANTAS | D80: Pendente | E80: =SUM(M80:U80) -> 111.57 | L80: =IF(C80>=13,1,"") | M80: 50 | N80: 24.57 | O80: 12 | P80: 2 | Q80: 5 | U80: 18 | V80: TAXA CONFRATERNIZAÇÃO 2024 R$ 5,00; TAXA DE PREPARO 1/2 R$ 13,00 | W80: =IF(F80=SUM(M80:U80),"OK","Diferente") -> Diferente | X80: =IF(W80="Diferente",F80-SUM(M80:U80),"") -> -111.57
B81: DAVID NASCIMENTO ALEXANDRINO | C81: 8 | D81: OK | E81: =SUM(M81:U81) -> 149.69 | F81: =E81 -> 149.69 | H81: Banco - Cora | L81: =IF(C81>=13,1,"") | M81: 93.62 | N81: 24.57 | O81: 12 | P81: 1.5 | U81: 18 | V81: TAXA CONFRATERNIZAÇÃO 2024 R$ 5,00; TAXA DE PREPARO 1/2 R$ 13,00 | W81: =IF(F81=SUM(M81:U81),"OK","Diferente") -> OK | X81: =IF(W81="Diferente",F81-SUM(M81:U81),"")
B82: MARYNA RIOS PAIVA | C82: 8 | D82: OK | E82: =SUM(M82:U82) -> 149.69 | F82: =E82 -> 149.69 | H82: Banco - Cora | L82: =IF(C82>=13,1,"") | M82: 93.62 | N82: 24.57 | O82: 12 | P82: 1.5 | U82: 18 | V82: TAXA CONFRATERNIZAÇÃO 2024 R$ 5,00; TAXA DE PREPARO 1/2 R$ 13,00 | W82: =IF(F82=SUM(M82:U82),"OK","Diferente") -> OK | X82: =IF(W82="Diferente",F82-SUM(M82:U82),"")
B83: FRANCILENE ALVES DE OLIVEIRA BRAGA | C83: 15 | D83: OK | E83: =SUM(M83:U83) -> 311.57 | F83: =E83 -> 311.57 | H83: Banco - Cora | L83: =IF(C83>=13,1,"") -> 1 | M83: 100 | N83: 24.57 | O83: 12 | P83: 2 | S83: 5 | U83: 168 | V83: TAXA AÇÃO ENTRE AMIGOS 2/2 R$ 150,00; TAXA CONFRATERNIZAÇÃO 2024 R$ 5,00; TAXA DE PREPARO 1/2 R$ 13,00 | W83: =IF(F83=SUM(M83:U83),"OK","Diferente") -> OK | X83: =IF(W83="Diferente",F83-SUM(M83:U83),"")
B84: ANA ALVES BRAGA | C84: 15 | D84: OK | E84: =SUM(M84:U84) -> 161.57 | F84: =E84 -> 161.57 | H84: Banco - Cora | L84: =IF(C84>=13,1,"") -> 1 | M84: 100 | N84: 24.57 | O84: 12 | P84: 2 | S84: 5 | U84: 18 | V84: TAXA CONFRATERNIZAÇÃO 2024 R$ 5,00; TAXA DE PREPARO 1/2 R$ 13,00 | W84: =IF(F84=SUM(M84:U84),"OK","Diferente") -> OK | X84: =IF(W84="Diferente",F84-SUM(M84:U84),"")
B85: RAFAEL CASTELO BRANCO MOURAO DE ANDRADE | C85: 9 | D85: OK | E85: =SUM(M85:U85) -> 268 | F85: =E85 -> 268 | H85: Banco - Cora | L85: =IF(C85>=13,1,"") | M85: 196.43 | N85: 24.57 | O85: 12 | P85: 2 | S85: 5 | T85: 10 | U85: 18 | V85: TAXA CONFRATERNIZAÇÃO 2024 R$ 5,00; TAXA DE PREPARO 1/2 R$ 13,00 | W85: =IF(F85=SUM(M85:U85),"OK","Diferente") -> OK | X85: =IF(W85="Diferente",F85-SUM(M85:U85),"")
B86: RAFAEL BARBOSA DE SOUZA | C86: 20 | D86: OK | E86: =SUM(M86:U86) -> 265 | F86: =E86 -> 265 | H86: Banco - Cora | L86: =IF(C86>=13,1,"") -> 1 | M86: 138.43 | N86: 24.57 | O86: 12 | P86: 2 | Q86: 5 | R86: 5 | S86: 10 | U86: 68 | V86: COMPRA DE ARCONDICIONADO 7/10 R$ 50,00; TAXA CONFRATERNIZAÇÃO 2024 R$ 5,00; TAXA DE PREPARO 1/2 R$ 13,00 | W86: =IF(F86=SUM(M86:U86),"OK","Diferente") -> OK | X86: =IF(W86="Diferente",F86-SUM(M86:U86),"")
B87: SARAH GOMES PINHEIRO | C87: 20 | D87: OK | E87: =SUM(M87:U87) -> 215 | F87: =E87 -> 215 | H87: Banco - Cora | L87: =IF(C87>=13,1,"") -> 1 | M87: 138.43 | N87: 24.57 | O87: 12 | P87: 2 | Q87: 5 | R87: 5 | S87: 10 | U87: 18 | V87: TAXA CONFRATERNIZAÇÃO 2024 R$ 5,00; TAXA DE PREPARO 1/2 R$ 13,00 | W87: =IF(F87=SUM(M87:U87),"OK","Diferente") -> OK | X87: =IF(W87="Diferente",F87-SUM(M87:U87),"")
B88: YARA FREITAS DE CARVALHO DE AGUIAR | D88: Pendente | E88: =SUM(M88:U88) -> 130.23 | L88: =IF(C88>=13,1,"") | M88: 33.93 | N88: 24.57 | O88: 12 | P88: 1.5 | U88: 58.23 | V88: ACORDO MENSALIDADE 5/10 R$ 40,23; TAXA CONFRATERNIZAÇÃO 2024 R$ 5,00; TAXA DE PREPARO 1/2 R$ 13,00 | W88: =IF(F88=SUM(M88:U88),"OK","Diferente") -> Diferente | X88: =IF(W88="Diferente",F88-SUM(M88:U88),"") -> -130.23
B89: POLLYANNA APARECIDA BATISTA VIANA | C89: 8 | D89: OK | E89: =SUM(M89:U89) -> 181.57 | F89: =E89 -> 181.57 | H89: Banco - Cora | L89: =IF(C89>=13,1,"") | M89: 120 | N89: 24.57 | O89: 12 | P89: 2 | S89: 5 | U89: 18 | V89: TAXA CONFRATERNIZAÇÃO 2024 R$ 5,00; TAXA DE PREPARO 1/2 R$ 13,00 | W89: =IF(F89=SUM(M89:U89),"OK","Diferente") -> OK | X89: =IF(W89="Diferente",F89-SUM(M89:U89),"")
B90: JOÃO VIANA FILHO | C90: 8 | D90: OK | E90: =SUM(M90:U90) -> 181.57 | F90: =E90 -> 181.57 | H90: Banco - Cora | L90: =IF(C90>=13,1,"") | M90: 120 | N90: 24.57 | O90: 12 | P90: 2 | S90: 5 | U90: 18 | V90: TAXA CONFRATERNIZAÇÃO 2024 R$ 5,00; TAXA DE PREPARO 1/2 R$ 13,00 | W90: =IF(F90=SUM(M90:U90),"OK","Diferente") -> OK | X90: =IF(W90="Diferente",F90-SUM(M90:U90),"")
B91: FRANCISCA SONIA COSTA | C91: 10 | D91: OK | E91: =SUM(M91:U91) -> 170 | F91: =E91 -> 170 | H91: Banco - Cora | L91: =IF(C91>=13,1,"") | M91: 108.43 | N91: 24.57 | O91: 12 | P91: 2 | S91: 5 | U91: 18 | V91: TAXA CONFRATERNIZAÇÃO 2024 R$ 5,00; TAXA DE PREPARO 1/2 R$ 13,00 | W91: =IF(F91=SUM(M91:U91),"OK","Diferente") -> OK | X91: =IF(W91="Diferente",F91-SUM(M91:U91),"")
B92: RAQUEL DA SILVA MAIA | C92: 8 | D92: OK | E92: =SUM(M92:U92) -> 119.5 | F92: =E92 -> 119.5 | H92: Banco - Cora | L92: =IF(C92>=13,1,"") | M92: 63.43 | N92: 24.57 | O92: 12 | P92: 1.5 | U92: 18 | V92: TAXA CONFRATERNIZAÇÃO 2024 R$ 5,00; TAXA DE PREPARO 1/2 R$ 13,00 | W92: =IF(F92=SUM(M92:U92),"OK","Diferente") -> OK | X92: =IF(W92="Diferente",F92-SUM(M92:U92),"")
B93: FRANCISCO ELEILTON MENDONÇA DO NASCIMENTO | C93: 8 | D93: OK | E93: =SUM(M93:U93) -> 169.5 | F93: =E93 -> 169.5 | H93: Banco - Cora | L93: =IF(C93>=13,1,"") | M93: 63.43 | N93: 24.57 | O93: 12 | P93: 1.5 | U93: 68 | V93: COMPRA DE ARCONDICIONADO 7/10 R$ 50,00; TAXA CONFRATERNIZAÇÃO 2024 R$ 5,00; TAXA DE PREPARO 1/2 R$ 13,00 | W93: =IF(F93=SUM(M93:U93),"OK","Diferente") -> OK | X93: =IF(W93="Diferente",F93-SUM(M93:U93),"")
B94: MARIA ROSINELE FELIX DO NASCIMENTO | D94: Pendente | E94: =SUM(M94:U94) -> 165 | L94: =IF(C94>=13,1,"") | M94: 93.93 | N94: 24.57 | O94: 12 | P94: 1.5 | Q94: 5 | S94: 10 | U94: 18 | V94: TAXA CONFRATERNIZAÇÃO 2024 R$ 5,00; TAXA DE PREPARO 1/2 R$ 13,00 | W94: =IF(F94=SUM(M94:U94),"OK","Diferente") -> Diferente | X94: =IF(W94="Diferente",F94-SUM(M94:U94),"") -> -165
B95: RARISNEIDE DA SILVA MAIA | D95: Pendente | E95: =SUM(M95:U95) -> 170 | L95: =IF(C95>=13,1,"") | M95: 108.43 | N95: 24.57 | O95: 12 | P95: 2 | S95: 5 | U95: 18 | V95: TAXA CONFRATERNIZAÇÃO 2024 R$ 5,00; TAXA DE PREPARO 1/2 R$ 13,00 | W95: =IF(F95=SUM(M95:U95),"OK","Diferente") -> Diferente | X95: =IF(W95="Diferente",F95-SUM(M95:U95),"") -> -170
B96: VITOR BISPO BRAÚNA | C96: 8 | D96: OK | E96: =SUM(M96:U96) -> 168 | F96: =E96 -> 168 | H96: Banco - Cora | L96: =IF(C96>=13,1,"") | M96: 113.43 | N96: 24.57 | O96: 12 | U96: 18 | V96: TAXA CONFRATERNIZAÇÃO 2024 R$ 5,00; TAXA DE PREPARO 1/2 R$ 13,00 | W96: =IF(F96=SUM(M96:U96),"OK","Diferente") -> OK | X96: =IF(W96="Diferente",F96-SUM(M96:U96),"")
B97: WESLEY ALESSANDRO RIBEIRO SILVA | C97: 9 | D97: Parcial | E97: 24 | F97: =SUM(M97:U97) -> 48 | G97: Pendente R$ 24 de novembro e R$ 24 de janeiro. O valor de R$ 48 pago foi referente a outubro. | H97: Banco - Cora | L97: =IF(C97>=13,1,"") | M97: =-12.57*2 -> -25.14 | N97: =24.57*2 -> 49.14 | O97: =12*2 -> 24 | W97: =IF(F97=SUM(M97:U97),"OK","Diferente") -> OK | X97: =IF(W97="Diferente",F97-SUM(M97:U97),"")
B98: ANA GEORGINA OLIVEIRA PONTES COSTA | C98: 8 | D98: OK | E98: =SUM(M98:U98) -> 143 | F98: =E98 -> 143 | H98: Banco - Cora | L98: =IF(C98>=13,1,"") | M98: 88.43 | N98: 24.57 | O98: 12 | U98: 18 | V98: TAXA CONFRATERNIZAÇÃO 2024 R$ 5,00; TAXA DE PREPARO 1/2 R$ 13,00 | W98: =IF(F98=SUM(M98:U98),"OK","Diferente") -> OK | X98: =IF(W98="Diferente",F98-SUM(M98:U98),"")
B99: MARCOS FELIPE DA SILVA MAIA | D99: Pendente | E99: =SUM(M99:U99) -> 68 | L99: =IF(C99>=13,1,"") | M99: 13.43 | N99: 24.57 | O99: 12 | U99: 18 | V99: TAXA CONFRATERNIZAÇÃO 2024 R$ 5,00; TAXA DE PREPARO 1/2 R$ 13,00 | W99: =IF(F99=SUM(M99:U99),"OK","Diferente") -> Diferente | X99: =IF(W99="Diferente",F99-SUM(M99:U99),"") -> -68
B100: JALSEY PEREIRA DE NAZARENO | C100: 10 | D100: OK | E100: =SUM(M100:U100) -> 148 | F100: =E100 -> 148 | H100: Banco - Cora | L100: =IF(C100>=13,1,"") | M100: 91.93 | N100: 24.57 | O100: 12 | P100: 1.5 | U100: 18 | V100: TAXA CONFRATERNIZAÇÃO 2024 R$ 5,00; TAXA DE PREPARO 1/2 R$ 13,00 | W100: =IF(F100=SUM(M100:U100),"OK","Diferente") -> OK | X100: =IF(W100="Diferente",F100-SUM(M100:U100),"")
B101: SUZANA PAIVA BEZERRA DE NAZARENO | C101: 10 | D101: OK | E101: =SUM(M101:U101) -> 148 | F101: =E101 -> 148 | H101: Banco - Cora | L101: =IF(C101>=13,1,"") | M101: 91.93 | N101: 24.57 | O101: 12 | P101: 1.5 | U101: 18 | V101: TAXA CONFRATERNIZAÇÃO 2024 R$ 5,00; TAXA DE PREPARO 1/2 R$ 13,00 | W101: =IF(F101=SUM(M101:U101),"OK","Diferente") -> OK | X101: =IF(W101="Diferente",F101-SUM(M101:U101),"")
B102: PEDRO VICTOR MIRANDA DE OLIVEIRA SALVIANO | D102: Pendente | E102: =SUM(M102:U102) -> 83 | L102: =IF(C102>=13,1,"") | M102: 26.43 | N102: 24.57 | O102: 12 | P102: 2 | U102: 18 | V102: TAXA CONFRATERNIZAÇÃO 2024 R$ 5,00; TAXA DE PREPARO 1/2 R$ 13,00 | W102: =IF(F102=SUM(M102:U102),"OK","Diferente") -> Diferente | X102: =IF(W102="Diferente",F102-SUM(M102:U102),"") -> -83
...

Sheet JAN-Despesas
B2: DESPESAS
B4: TOTAL | C4: - | D4: - | E4: =SUBTOTAL(9,E16,E63,E38,E135,E160,E166,E93,E6,E34,E222,E271,E172,E182,E192,E202,E212,E108) -> 0 | F4: =SUBTOTAL(9,F16,F63,F38,F125,F135,F160,F166,F93,F6,F34,F222,F271,F172,F182,F192,F202,F212,F108) -> 57344.6 | G4: - | H4: CAIXA | I4: COMPROVANTE | J4: PLANO DE CONTAS DG
C5: Data | D5: Efetivado | E5: Valor Previsto | F5: Valor Pago | G5: Observação
B6: NCL - Funcionários | C6: - | D6: - | E6: =SUM(E7:E15) -> 0 | F6: =SUMIF(D7:D15,"OK",F7:F15) -> 2182.87
B7: Salário | C7: 1 | D7: OK | E7: 0 | F7: 709.82 | G7: Pagamento realizado em duplicidade considerando que já havia sido pago em 28/12/2024. Solicitada a devolução do pix ao Wesley que informou que já havia gasto o dinheiro. O valor de R$ 709,82 será descontado no pagamento dos salários de fevereiro e março. | H7: Banco - Cora | I7: https://drive.google.com/open?id=1mdcGvPCJ-b56kQcTTnv0NHR9lz6bhKaS&usp=drive_fs
B8: 13° salário | E8: 0 | F8: 0
B9: Férias | C9: 3 | D9: OK | E9: 0 | F9: 1026.95 | G9: 20 dias de férias + 10 dias comprados pelo núcleo. | H9: Banco - Cora | I9: https://drive.google.com/open?id=1yfj64PilsAhg2ps6P13cPj6FSWgIed3F&usp=drive_fs
B10: Encargos sociais | C10: 15 | D10: OK | E10: 0 | F10: 286.14 | H10: Banco - Cora | I10: https://drive.google.com/open?id=1gRnlDb8DmOVHUU_-CiM9efxoSRDOjTjU&usp=drive_fs
B11: Encargos sociais | C11: 15 | D11: OK | E11: 0 | F11: 40.12 | H11: Banco - Cora | I11: https://drive.google.com/open?id=1gVthgjd-xQLy4bzTITepW9-LSo7JZLV9&usp=drive_fs
B12: Encargos sociais | C12: 15 | D12: OK | E12: 0 | F12: 64.85 | H12: Banco - Cora | I12: https://drive.google.com/open?id=1gNhVwxUFoN7ZOYPVqARL9Bb276j9U7PY&usp=drive_fs
B13: Encargos sociais | E13: 0 | F13: 0
B14: Cesta básica | C14: 6 | D14: OK | E14: 0 | F14: 54.99 | H14: Banco - Cora | I14: https://drive.google.com/open?id=1IfoI9Iif_r_WmewDu7PzFevppvyzTPGY&usp=drive_fs
B15: Outras despesas | E15: 0 | F15: 0
B16: NCL - Repasses | C16: - | D16: - | E16: =SUM(E17:E33) -> 0 | F16: =SUMIF(D17:D33,"OK",F17:F33) -> 7731.61
B17: Diretoria Geral - FP | C17: 29 | D17: OK | E17: 0 | F17: 1409.24 | H17: Banco - Cora | I17: https://drive.google.com/open?id=1qyuapgNjKzGYut8sjI4isL4ao-Dil0W5&usp=drive_fs
B18: Diretoria Geral - FS | C18: 29 | D18: OK | E18: 0 | F18: 802.62 | H18: Banco - Cora
B19: Diretoria Geral - FA | C19: 29 | D19: OK | E19: 0 | F19: 98 | H19: Banco - Cora
B20: Diretoria Geral - FB | C20: 29 | D20: OK | E20: 0 | F20: 98 | H20: Banco - Cora
B21: Diretoria Geral - SUC | C21: 29 | D21: OK | E21: 0 | F21: 384 | H21: Banco - Cora
B22: 11a Região - Fundo Regional | C22: 20 | D22: OK | E22: 0 | F22: =(310.65/95)*98 -> 320.46 | G22: Pagamento único de R$ 1.176,00 | H22: Banco - Cora | I22: https://drive.google.com/open?id=1me6oMu0QuwSOf0672D1h16itpT7CXm8W&usp=drive_fs
B23: 11a Região - Plantio | C23: 20 | D23: OK | E23: 0 | F23: =(356.25/95)*98 -> 367.5 | H23: Banco - Cora
B24: 11a Região - Fundo de Beneficência | C24: 20 | D24: OK | E24: 0 | F24: =(441.75/95)*98 -> 455.7 | H24: Banco - Cora
B25: 11a Região - Fundo de Reserva | C25: 20 | D25: OK | E25: 0 | F25: =(31.35/95)*98 -> 32.34 | H25: Banco - Cora
B26: 11a Região - Servidor Vreal | E26: 0 | F26: 0
B27: 11a Região - Sala da Região | E27: 0 | F27: 0
B28: 11a Região - Extra | E28: 0 | F28: 0
B29: Novo Encanto | C29: 15 | D29: OK | E29: 0 | F29: 117 | H29: Banco - Cora | I29: https://drive.google.com/open?id=1fneKxS8fcSCEk6941q_y4bYQB-3y2aNp&usp=drive_fs
B30: Flor Divina | C30: 3 | D30: OK | E30: 0 | F30: =2343.27-80 -> 2263.27 | G30: Repasse de dezembro: R$ 2.343,27 realizada em 03/01, sendo R$ 80 referente a lanche do Plantio. | H30: Banco - Cora | I30: https://drive.google.com/open?id=1XlVADbZtcXWzEBTIqPWShhKUtzx-AXoK&usp=drive_fs
B31: Memorial José Gabriel da Costa | E31: 0 | F31: 0
B32: Flor Divina | C32: 31 | D32: OK | E32: 0 | F32: 1383.48 | G32: Repasse de janeiro: R$ 1.463,48, sendo R$ 1.383,48 pago pela tesouraria e R$ 80 pelo plantio. | H32: Banco - Cora | I32: https://drive.google.com/open?id=1yEGIa44JRzSyB9hsDq2v5wHpRZ_ExjoJ&usp=drive_fs
B33: Outro repasse | E33: 0 | F33: 0
B34: NCL - Tarifas bancárias | C34: - | D34: - | E34: =SUM(E35:E37) -> 0 | F34: =SUMIF(D35:D37,"OK",F35:F37) -> 1.89
B35: IR Rendimento Pagbank | C35: 2 | D35: OK | E35: 0 | F35: 1.89 | H35: Banco - Pagbank | I35: https://drive.google.com/open?id=1jHVfJCXu0-ZoBNffO1AqvlkvOq2K4JJP&usp=drive_fs
B36: Encerramento conta itaú | E36: 0 | F36: 0
B37: Tarifa 3 | E37: 0 | F37: 0
B38: NCL - Despesas gerais | C38: - | D38: - | E38: =SUM(E39:E62) -> 0 | F38: =SUMIF(D39:D62,"OK",F39:F62) -> 4886.5
B39: Energia Elétrica | C39: 31 | D39: OK | E39: 0 | F39: 795.7 | H39: Banco - Cora | I39: https://drive.google.com/open?id=1ma8w6Q6gU7pvYjO6f4zoUEVNUEMJ0uEg&usp=drive_fs
B40: Vigilância - 1a escala | C40: 5 | D40: OK | E40: 0 | F40: 650 | H40: Banco - Cora | I40: https://drive.google.com/open?id=1nYs5-oiWryI6gqMDbVz2yIXNsS9wlpfW&usp=drive_fs
B41: Vigilância - 2a escala | C41: 19 | D41: OK | E41: 0 | F41: 650 | H41: Banco - Cora | I41: https://drive.google.com/open?id=1TFH-yvYsU0O4H-HXjX5jxifCZ1CRuV5i&usp=drive_fs
B42: Contabilidade | E42: 0 | F42: 0
B43: Internet | C43: 14 | D43: OK | E43: 0 | F43: 84.9 | H43: Banco - Cora | I43: https://drive.google.com/open?id=1JiL4IMQV5qgjJVyaHpjfjyHxSF8AtRx5&usp=drive_fs
B44: Ar Condicionado Berçário | C44: 23 | D44: OK | E44: 0 | F44: 518 | G44: Parcela 7 de 10 | H44: Banco - Cora | I44: https://drive.google.com/open?id=1DPX6Bl60DmNnWtEFQvRXFl9BbLOJk8gP&usp=drive_fs
B45: Mesa de som | C45: 23 | D45: OK | E45: 0 | F45: 212.9 | G45: Parcela 6 de 10 | H45: Banco - Cora | I45: https://drive.google.com/open?id=1kTqwFs699bV9KwPZoXSmRktkBrO9pzuU&usp=drive_fs
B46: Inscrição Expedição Fazenda Bom Conselho | C46: 14 | D46: OK | E46: 0 | F46: 1625 | G46: 50% de 3 inscrições + 100% de 1 inscrição | H46: Banco - Cora | I46: https://drive.google.com/open?id=1mpUqEgxj0ZB73Y__9pdBZeufFcqznfb8&usp=drive_fs
B47: Compra de geladeira para cantina | C47: 15 | D47: OK | E47: 0 | F47: 350 | H47: Banco - Cora | I47: https://drive.google.com/open?id=1kDFmKoVNN0aixKjQHsg4n42tlMbm3_W3&usp=drive_fs
B48: Despesa | E48: 0 | F48: 0
B49: Despesa | E49: 0 | F49: 0
B50: Despesa | E50: 0 | F50: 0
B51: Despesa | E51: 0 | F51: 0
B52: Despesa | E52: 0 | F52: 0
B53: Despesa | E53: 0 | F53: 0
B54: Despesa | E54: 0 | F54: 0
B55: Despesa | E55: 0 | F55: 0
B56: Despesa | E56: 0 | F56: 0
B57: Despesa | E57: 0 | F57: 0
B58: Despesa | E58: 0 | F58: 0
B59: Despesa | E59: 0 | F59: 0
... B62: Despesa | E62: 0 | F62: 0
B63: NCL - Organ | C63: - | D63: - | E63: =SUM(E64:E92) -> 0 | F63: =SUMIF(D64:D92,"OK",F64:F92) -> 2783.74
B64: Lanche 1a escala | C64: 6 | D64: OK | E64: 0 | F64: 161.39 | H64: Banco - Cora | I64: https://drive.google.com/open?id=1hFSIHwRwuaQiYwWsWQxE8pSyVgKFTuLZ&usp=drive_fs
B65: Lanche 1a escala | C65: 6 | D65: OK | E65: 0 | F65: 31.8 | H65: Banco - Cora | I65: https://drive.google.com/open?id=1hJdc66d6kGI8Rp3MXD8dxoc-6x3uS3Vg&usp=drive_fs
B66: Lanche 1a escala | C66: 7 | D66: OK | E66: 0 | F66: 45 | G66: Água de coco | H66: Banco - Cora | I66: https://drive.google.com/open?id=1Y6W2yJNEpxHpXnLCX9sMGYNQ1oQjsRJR&usp=drive_fs
B67: Lanche 1a escala | C67: 7 | D67: OK | E67: 0 | F67: 86.71 | H67: Banco - Cora | I67: https://drive.google.com/open?id=1hfgQ-3NbxUZ47dvLGHUXcz6AdKYhXVs2&usp=drive_fs
B68: Lanche 1a escala | C68: 8 | D68: OK | E68: 0 | F68: 80.49 | H68: Banco - Cora | I68: https://drive.google.com/open?id=1nGrgfNljyrGW_1JiwA98QtZaCEVme198&usp=drive_fs
B69: Lanche 1a escala | C69: 8 | D69: OK | E69: 0 | F69: 67.96 | H69: Banco - Cora | I69: https://drive.google.com/open?id=1n5Sig2je9s_93XrjjUNd4tGcIoglHbTJ&usp=drive_fs
B70: Lanche 1a escala | C70: 8 | D70: OK | E70: 0 | F70: 279.75 | H70: Banco - Cora | I70: https://drive.google.com/open?id=1_YWVUPgvM0gwIOxfYsT1KfHs92QgjxHH&usp=drive_fs
B71: Lanche 1a escala | C71: 8 | D71: OK | E71: 0 | F71: 95 | H71: Banco - Cora | I71: https://drive.google.com/open?id=1nRM5lAsZ2shANLHnOZCz6YEiS8DusuX7&usp=drive_fs
B72: Lanche 2a escala | C72: 17 | D72: OK | E72: 0 | F72: 57 | G72: Sucos | H72: Banco - Cora | I72: https://drive.google.com/open?id=1mDGly3g1G-oIK4Z7r4AbKZKPss2un1JF&usp=drive_fs
B73: Lanche 2a escala | C73: 18 | D73: OK | E73: 0 | F73: 102 | H73: Banco - Cora | I73: https://drive.google.com/open?id=1lc-jV3MDu9Pt6VNBLSE32ETg1AvCE8zW&usp=drive_fs
B74: Lanche 2a escala | C74: 19 | D74: OK | E74: 0 | F74: 209.47 | G74: Pix único de R$ 867,42 para a C. Sandra. | H74: Banco - Cora | I74: https://drive.google.com/open?id=1m8TSvmL1_wmdN1UY5ImRRMfsPN415Beu&usp=drive_fs
B75: Lanche 2a escala | C75: 19 | D75: OK | E75: 0 | F75: 50 | G75: Pix único de R$ 867,42 para a C. Sandra. | H75: Banco - Cora | I75: https://drive.google.com/open?id=1lrtlxjHHABv_0lSzyuQdEv0MUg-DHK_B&usp=drive_fs
B76: Lanche 2a escala e Mercado | C76: 19 | D76: OK | E76: 0 | F76: 574.95 | G76: Pix único de R$ 867,42 para a C. Sandra. | H76: Banco - Cora | I76: https://drive.google.com/open?id=1loYwaTNByUvK_K_8wluh6PeqwuE-Aggz&usp=drive_fs
B77: Lanche 2a escala | C77: 19 | D77: OK | E77: 0 | F77: 45 | G77: Água de coco | H77: Banco - Cora | I77: https://drive.google.com/open?id=1Y6W2yJNEpxHpXnLCX9sMGYNQ1oQjsRJR&usp=drive_fs
B78: Lanche 2a escala | E78: 0 | F78: 0
B79: Lanche 2a escala | E79: 0 | F79: 0
B80: Mercado | C80: 6 | D80: OK | E80: 0 | F80: 29.97 | H80: Banco - Cora | I80: https://drive.google.com/open?id=1hFi3kqDg5CmQZr_L5FGbK_r2kstkObQd&usp=drive_fs
B81: Mercado | C81: 8 | D81: OK | E81: 0 | F81: 59.8 | H81: Banco - Cora | I81: https://drive.google.com/open?id=1n8ST-46Lp7fm5G579i1O8uVfNhkLs-cU&usp=drive_fs
B82: Mercado | C82: 18 | D82: OK | E82: 0 | F82: 34 | H82: Banco - Cora | I82: https://drive.google.com/open?id=1V_yMQKaE-8HrCzyTw6m1CUmmSMgk0Pvq&usp=drive_fs
B83: Mercado | C83: 18 | D83: OK | E83: 0 | F83: 44.5 | H83: Banco - Cora | I83: https://drive.google.com/open?id=1lkx6NraSyx_G_Yzr3sATDslJtVm8JaXD&usp=drive_fs
B84: Mercado | C84: 30 | D84: OK | E84: 0 | F84: 253.53 | H84: Banco - Cora | I84: https://drive.google.com/open?id=1twIVgKAhncKi0Zxz9x_9R7frN1L99vBe&usp=drive_fs
B85: Água mineral | C85: 15 | D85: OK | E85: 0 | F85: 176 | H85: Banco - Cora | I85: https://drive.google.com/open?id=1fmdjNaVxzj-GwXzVEc7xNRm7tR53xoyu&usp=drive_fs
B86: Água mineral | E86: 0 | F86: 0
B87: Jantar 1a escala | C87: 8 | D87: OK | E87: 0 | F87: 266.42 | H87: Banco - Cora | I87: https://drive.google.com/open?id=1nP-aw1axAorqtxZkqW0I4CQUtKTon4Am&usp=drive_fs
B88: Jantar 2a escala | C88: 19 | D88: OK | E88: 0 | F88: 33 | G88: Pix único de R$ 867,42 para a C. Sandra. | H88: Banco - Cora | I88: https://drive.google.com/open?id=1lqlQT10luc3ZSVa28ZmEQpVazP5bSNZr&usp=drive_fs
B89: Jantar 2a escala | E89: 0 | F89: 0
B90: Jantar 2a escala | E90: 0 | F90: 0
B91: Outra despesa | E91: 0 | F91: 0
B92: Outra despesa | E92: 0 | F92: 0
B93: NCL - Preparo | C93: - | D93: - | E93: =SUM(E94,E100,E104) -> 0 | F93: =SUM(F94,F100,F104) -> 0
B94: Organ | E94: =SUM(E95:E99) -> 0 | F94: =SUMIF(D95:D99,"OK",F95:F99) -> 0
B95: Mercado | E95: 0 | F95: 0
B96: Água mineral | E96: 0 | F96: 0
B97: Outra despesa (1) | E97: 0 | F97: 0
B98: Outra despesa (2) | E98: 0 | F98: 0
B99: Outra despesa (3) | E99: 0 | F99: 0
B100: Materiais | E100: =SUM(E101:E103) -> 0 | F100: =SUMIF(D101:D103,"OK",F101:F103) -> 0
B101: Despesa 1 | E101: 0 | F101: 0
B102: Despesa 2 | E102: 0 | F102: 0
B103: Despesa 3 | E103: 0 | F103: 0
B104: Colheita | E104: =SUM(E105:E107) -> 0 | F104: =SUMIF(D105:D107,"OK",F105:F107) -> 0
...

Sheet FEV-Receitas
B2: RECEITAS
B4: TOTAL | E4: =SUM(E6,E127,E147,E169,E173) -> 16476.43 | F4: =SUM(F6,F127,F147,F169,F173) -> 22658.55 | H4: CAIXA | I4: PLANO DE CONTAS DG
C5: Data | D5: Efetivado | E5: Valor Previsto | F5: Valor Recebido | G5: Observação | J5: Inadimp. (qtd) | K5: Inadimp. (R$) | L5: % Atraso | M5: Núcleo | N5: Repasse DG | O5: Repasse 11a R | P5: Benef. NLT | Q5: NE NLT | R5: Plantio NLT | S5: FR Bilhete Aéreo | T5: FR Construção | U5: Taxa Extra | V5: Detalhamento Taxa Extra | X5: A receber:
B6: Mensalidade | C6: 10 | D6: - | E6: =SUM(E7:E126) -> 16476.43 | F6: =SUMIF(D7:D126,"OK",F7:F126)+SUMIF(D7:D126,"Parcial",F7:F126) -> 15875.15 | G6: - | J6: =(COUNTIF(D7:D126,"Pendente")+COUNTIF(D7:D126,"Parcial"))/COUNTA(B7:B126) -> 0.0625 | K6: =IFERROR(-(X6/E6),"Pendente info") -> 0.14081813 | L6: =SUM(L7:L105)/COUNTA(B7:B105) -> 0.11458333 | M6: =SUMIF($D$7:$D$126,"OK",M7:M126)+SUMIF($D$7:$D$126,"Parcial",M7:M126) -> 8734.3 | N6: =SUMIF($D$7:$D$126,"OK",N7:N126)+SUMIF($D$7:$D$126,"Parcial",N7:N126) -> 2137.59 | O6: =SUMIF($D$7:$D$126,"OK",O7:O126)+SUMIF($D$7:$D$126,"Parcial",O7:O126) -> 1044 | P6: =SUMIF($D$7:$D$126,"OK",P7:P126)+SUMIF($D$7:$D$126,"Parcial",P7:P126) -> 223.26 | Q6: =SUMIF($D$7:$D$126,"OK",Q7:Q126)+SUMIF($D$7:$D$126,"Parcial",Q7:Q126) -> 215 | R6: =SUMIF($D$7:$D$126,"OK",R7:R126)+SUMIF($D$7:$D$126,"Parcial",R7:R126) -> 260 | S6: =SUMIF($D$7:$D$126,"OK",S7:S126)+SUMIF($D$7:$D$126,"Parcial",S7:S126) -> 297 | T6: =SUMIF($D$7:$D$126,"OK",T7:T126)+SUMIF($D$7:$D$126,"Parcial",T7:T126) -> 610 | U6: =SUMIF($D$7:$D$126,"OK",U7:U126)+SUMIF($D$7:$D$126,"Parcial",U7:U126) -> 2354 | V6: - | W6: =IF(F6=SUM(M6:U6),"OK","Diferente") -> OK | X6: =SUM(X7:X126) -> -2320.18
B7: ELPÍDIO GOMES DE MOURA NETO | D7: OK | E7: 0 | L7: =IF(C7>=13,1,"") | W7: =IF(F7=SUM(M7:U7),"OK","Diferente") -> OK | X7: =IF(W7="Diferente",F7-SUM(M7:U7),"")
B8: JULIANA COLLYER ARRUDA DE MOURA | D8: OK | E8: 0 | L8: =IF(C8>=13,1,"") | W8: =IF(F8=SUM(M8:U8),"OK","Diferente") -> OK | X8: =IF(W8="Diferente",F8-SUM(M8:U8),"")
B9: SILVERIA LOPES VASCONCELOS ARRUDA | D9: OK | E9: 0 | L9: =IF(C9>=13,1,"") | W9: =IF(F9=SUM(M9:U9),"OK","Diferente") -> OK | X9: =IF(W9="Diferente",F9-SUM(M9:U9),"")
B10: FRANCISCO DE ASSIS VASCONCELOS ARRUDA | D10: OK | E10: 0 | L10: =IF(C10>=13,1,"") | W10: =IF(F10=SUM(M10:U10),"OK","Diferente") -> OK | X10: =IF(W10="Diferente",F10-SUM(M10:U10),"")
B11: ANTÔNIO GONÇALVES DE LIMA FILHO | C11: 7 | D11: OK | E11: =SUM(M11:U11) -> 188.43 | F11: =E11 -> 188.43 | H11: Banco - Cora | L11: =IF(C11>=13,1,"") | M11: 130 | N11: 24.57 | O11: 12 | P11: 3.86 | Q11: 5 | U11: 13 | V11: TAXA DE PREPARO 2/2 R$ 13,00 | W11: =IF(F11=SUM(M11:U11),"OK","Diferente") -> OK | X11: =IF(W11="Diferente",F11-SUM(M11:U11),"")
B12: SANDRA BORGES GONÇALVES DE LIMA | C12: 7 | D12: OK | E12: =SUM(M12:U12) -> 181.57 | F12: =E12 -> 181.57 | H12: Banco - Cora | L12: =IF(C12>=13,1,"") | M12: 130 | N12: 24.57 | O12: 12 | P12: 2 | U12: 13 | V12: TAXA DE PREPARO 2/2 R$ 13,00 | W12: =IF(F12=SUM(M12:U12),"OK","Diferente") -> OK | X12: =IF(W12="Diferente",F12-SUM(M12:U12),"")
B13: MARCELO DE CASTRO BRASIL | E13: =SUM(M13:U13) -> 361.49 | L13: =IF(C13>=13,1,"") | M13: 130.48 | N13: 24.57 | O13: 12 | P13: 1.44 | Q13: 10 | R13: 20 | S13: 50 | T13: 50 | U13: 63 | V13: COMPRA DE ARCONDICIONADO 8/10 R$ 50,00; TAXA DE PREPARO 2/2 R$ 13,00 | W13: =IF(F13=SUM(M13:U13),"OK","Diferente") -> Diferente | X13: =IF(W13="Diferente",F13-SUM(M13:U13),"") -> -361.49
B14: FLORA BORGES GONÇALVES LIMA BRASIL | E14: =SUM(M14:U14) -> 204.29 | L14: =IF(C14>=13,1,"") | M14: 98.28 | N14: 24.57 | O14: 12 | P14: 1.44 | Q14: 5 | T14: 50 | U14: 13 | V14: TAXA DE PREPARO 2/2 R$ 13,00 | W14: =IF(F14=SUM(M14:U14),"OK","Diferente") -> Diferente | X14: =IF(W14="Diferente",F14-SUM(M14:U14),"") -> -204.29
B15: CÁSSIO PEREIRA COSTA SOUSA | C15: 1 | D15: Parcial | E15: 311.14 | F15: =SUM(M15:U15) -> 311.14 | G15: Este valor está lançado, porém não houve transação bancária. A C. Mônica solicitou que 4 compras da Organ realizadas por ela fossem abatidas do valor da mensalidade de janeiro. As 4 compras totalizam R$ 449,41, enquanto o valor da mensalidade é R$ 472,13. Dessa forma, foi lançado o valor de R$ 449,41 como receita de mensalidade para equiparar esta despesa. Resta ainda R$ 22,72 da mensalidade de janeiro e R$ 462,13 da mensalidade de fevereiro. | H15: Banco - Cora | L15: =IF(C15>=13,1,"") | M15: 180.13 | N15: 24.57 | O15: 12 | P15: 1.44 | Q15: 5 | R15: 5 | S15: 20 | U15: 63 | V15: COMPRA DE ARCONDICIONADO 8/10 R$ 50,00; TAXA DE PREPARO 2/2 R$ 13,00 | W15: =IF(F15=SUM(M15:U15),"OK","Diferente") -> OK | X15: =IF(W15="Diferente",F15-SUM(M15:U15),"")
B16: MÔNICA DE ARAUJO CAMPOS COSTA SOUSA | C16: 1 | D16: Parcial | E16: 150.99 | F16: =SUM(M16:U16) -> 138.27 | H16: Banco - Cora | L16: =IF(C16>=13,1,"") | M16: =89.98-22.72+10 -> 77.26 | N16: 24.57 | O16: 12 | P16: 1.44 | Q16: 5 | R16: 5 | U16: 13 | V16: TAXA DE PREPARO 2/2 R$ 13,00 | W16: =IF(F16=SUM(M16:U16),"OK","Diferente") -> OK | X16: =IF(W16="Diferente",F16-SUM(M16:U16),"")
B17: JOSÉ MAURÍCIO GUIMARÃES GOMES | C17: 4 | D17: OK | E17: =SUM(M17:U17) -> 247.19 | F17: =E17 -> 247.19 | H17: Banco - Cora | L17: =IF(C17>=13,1,"") | M17: 191.18 | N17: 24.57 | O17: 12 | P17: 1.44 | Q17: 5 | U17: 13 | V17: TAXA DE PREPARO 2/2 R$ 13,00 | W17: =IF(F17=SUM(M17:U17),"OK","Diferente") -> OK | X17: =IF(W17="Diferente",F17-SUM(M17:U17),"")
B18: TICIANE ARAGAO DA SILVEIRA GOMES | C18: 4 | D18: OK | E18: =SUM(M18:U18) -> 186.99 | F18: =E18 -> 186.99 | H18: Banco - Cora | L18: =IF(C18>=13,1,"") | M18: 135.98 | N18: 24.57 | O18: 12 | P18: 1.44 | U18: 13 | V18: TAXA DE PREPARO 2/2 R$ 13,00 | W18: =IF(F18=SUM(M18:U18),"OK","Diferente") -> OK | X18: =IF(W18="Diferente",F18-SUM(M18:U18),"")
B19: SERVULO SIDNEY GLADIUS PAIVA PIMENTEL | C19: 4 | D19: OK | E19: =SUM(M19:U19) -> 454.29 | F19: =E19 -> 454.29 | H19: Banco - Cora | L19: =IF(C19>=13,1,"") | M19: 328.28 | N19: 24.57 | O19: 12 | P19: 11.44 | Q19: 5 | R19: 10 | T19: 50 | U19: 13 | V19: TAXA DE PREPARO 2/2 R$ 13,00 | W19: =IF(F19=SUM(M19:U19),"OK","Diferente") -> OK | X19: =IF(W19="Diferente",F19-SUM(M19:U19),"")
B20: MARIA DANIELLY RIOS DA SILVA PAIVA | C20: 4 | D20: OK | E20: =SUM(M20:U20) -> 444.29 | F20: =E20 -> 444.29 | H20: Banco - Cora | L20: =IF(C20>=13,1,"") | M20: 328.28 | N20: 24.57 | O20: 12 | P20: 1.44 | Q20: 5 | R20: 10 | T20: 50 | U20: 13 | V20: TAXA DE PREPARO 2/2 R$ 13,00 | W20: =IF(F20=SUM(M20:U20),"OK","Diferente") -> OK | X20: =IF(W20="Diferente",F20-SUM(M20:U20),"")
B21: RÉGIS BEZERRA GOMES | C21: 14 | D21: OK | E21: =SUM(M21:U21) -> 261.99 | F21: =E21 -> 261.99 | H21: Banco - Cora | L21: =IF(C21>=13,1,"") -> 1 | M21: 120.98 | N21: 24.57 | O21: 12 | P21: 1.44 | Q21: 5 | R21: 5 | T21: 30 | U21: 63 | V21: COMPRA DE ARCONDICIONADO 8/10 R$ 50,00; TAXA DE PREPARO 2/2 R$ 13,00 | W21: =IF(F21=SUM(M21:U21),"OK","Diferente") -> OK | X21: =IF(W21="Diferente",F21-SUM(M21:U21),"")
B22: ANA CAROLINA DE OLIVEIRA MARTINS GOMES | C22: 14 | D22: OK | E22: =SUM(M22:U22) -> 188.59 | F22: =E22 -> 188.59 | H22: Banco - Cora | L22: =IF(C22>=13,1,"") -> 1 | M22: 102.58 | N22: 24.57 | O22: 12 | P22: 1.44 | Q22: 5 | T22: 30 | U22: 13 | V22: TAXA DE PREPARO 2/2 R$ 13,00 | W22: =IF(F22=SUM(M22:U22),"OK","Diferente") -> OK | X22: =IF(W22="Diferente",F22-SUM(M22:U22),"")
B23: LINDAYANA DE SOUZA FLORÊNCIO | E23: =SUM(M23:U23) -> 148.34 | L23: =IF(C23>=13,1,"") | M23: 37.33 | N23: 24.57 | O23: 12 | P23: 1.44 | Q23: 5 | R23: 5 | U23: 63 | V23: COMPRA DE ARCONDICIONADO 8/10 R$ 50,00; TAXA DE PREPARO 2/2 R$ 13,00 | W23: =IF(F23=SUM(M23:U23),"OK","Diferente") -> Diferente | X23: =IF(W23="Diferente",F23-SUM(M23:U23),"") -> -148.34
B24: DAVI FLORENCIO DE SOUSA | E24: =SUM(M24:U24) -> 129.44 | L24: =IF(C24>=13,1,"") | M24: 53.43 | N24: 24.57 | O24: 12 | P24: 1.44 | Q24: 5 | R24: 5 | T24: 15 | U24: 13 | V24: TAXA DE PREPARO 2/2 R$ 13,00 | W24: =IF(F24=SUM(M24:U24),"OK","Diferente") -> Diferente | X24: =IF(W24="Diferente",F24-SUM(M24:U24),"") -> -129.44
B25: JOAQUIM GARCEZ DE LIMA ROCHA | C25: 7 | D25: OK | E25: =SUM(M25:U25) -> 198 | F25: =E25 -> 198 | H25: Banco - Cora | L25: =IF(C25>=13,1,"") | M25: 131.99 | N25: 24.57 | O25: 12 | P25: 6.44 | R25: 10 | U25: 13 | V25: TAXA DE PREPARO 2/2 R$ 13,00 | W25: =IF(F25=SUM(M25:U25),"OK","Diferente") -> OK | X25: =IF(W25="Diferente",F25-SUM(M25:U25),"")
B26: FRANCISCO SAULO STUDART ALBUQUERQUE | E26: =SUM(M26:U26) -> 123 | L26: =IF(C26>=13,1,"") | M26: 71.43 | N26: 24.57 | O26: 12 | P26: 2 | U26: 13 | V26: TAXA DE PREPARO 2/2 R$ 13,00 | W26: =IF(F26=SUM(M26:U26),"OK","Diferente") -> Diferente | X26: =IF(W26="Diferente",F26-SUM(M26:U26),"") -> -123
B27: FRANCO COSTA E SILVA | C27: 11 | D27: OK | E27: =SUM(M27:U27) -> 393 | F27: =E27 -> 393 | H27: Banco - Cora | L27: =IF(C27>=13,1,"") | M27: 131.99 | N27: 24.57 | O27: 12 | P27: 11.44 | Q27: 5 | R27: 5 | S27: 10 | T27: 30 | U27: 163 | V27: COMPRA DE ARCONDICIONADO 8/10 R$ 50,00; TAXA DE PREPARO 2/2 R$ 13,00; DOAÇÃO CANTINA SANA R$ 100,00 | W27: =IF(F27=SUM(M27:U27),"OK","Diferente") -> OK | X27: =IF(W27="Diferente",F27-SUM(M27:U27),"")
B28: JULIANA SOARES MONTEIRO | C28: 11 | D28: OK | E28: =SUM(M28:U28) -> 233 | F28: =E28 -> 233 | H28: Banco - Cora | L28: =IF(C28>=13,1,"") | M28: 131.99 | N28: 24.57 | O28: 12 | P28: 1.44 | Q28: 5 | R28: 5 | S28: 10 | T28: 30 | U28: 13 | V28: TAXA DE PREPARO 2/2 R$ 13,00 | W28: =IF(F28=SUM(M28:U28),"OK","Diferente") -> OK | X28: =IF(W28="Diferente",F28-SUM(M28:U28),"")
B29: HUGO UCHOA PASSOS ALENCAR | C29: 11 | D29: OK | E29: =SUM(M29:U29) -> 272.69 | F29: =E29 -> 272.69 | H29: Banco - Cora | L29: =IF(C29>=13,1,"") | M29: 116.68 | N29: 24.57 | O29: 12 | P29: 1.44 | Q29: 5 | R29: 10 | S29: 10 | T29: 30 | U29: 63 | V29: COMPRA DE ARCONDICIONADO 8/10 R$ 50,00; TAXA DE PREPARO 2/2 R$ 13,00 | W29: =IF(F29=SUM(M29:U29),"OK","Diferente") -> OK | X29: =IF(W29="Diferente",F29-SUM(M29:U29),"")
B30: MAIRI ALENCAR DE LACERDA FERRAZ UCHÔA | C30: 11 | D30: OK | E30: =SUM(M30:U30) -> 171.69 | F30: =E30 -> 171.69 | H30: Banco - Cora | L30: =IF(C30>=13,1,"") | M30: 70.68 | N30: 24.57 | O30: 12 | P30: 1.44 | R30: 10 | S30: 10 | T30: 30 | U30: 13 | V30: TAXA DE PREPARO 2/2 R$ 13,00 | W30: =IF(F30=SUM(M30:U30),"OK","Diferente") -> OK | X30: =IF(W30="Diferente",F30-SUM(M30:U30),"")
B31: JOÃO CARLOS STUDART ANTERO | C31: 4 | D31: Parcial | E31: 180.44 | F31: =SUM(M31:U31) -> 350.88 | G31: Realizado o pagamento das mensalidades de dezembro e janeiro. Permane pendente fevereiro. | H31: Banco - Cora | L31: =IF(C31>=13,1,"") | M31: =104.43*2 -> 208.86 | N31: =24.57*2 -> 49.14 | O31: =12*2 -> 24 | P31: =1.44*2 -> 2.88 | Q31: =5*2 -> 10 | S31: =10*2 -> 20 | T31: =10*2 -> 20 | U31: 16 | V31: TAXA DE PREPARO 2/2 R$ 13,00 | W31: =IF(F31=SUM(M31:U31),"OK","Diferente") -> OK | X31: =IF(W31="Diferente",F31-SUM(M31:U31),"")
B32: JANAÍNA SILVA LEITÃO STUDART ANTERO | C32: 4 | D32: Parcial | E32: 180.44 | F32: =SUM(M32:U32) -> 334.88 | H32: Banco - Cora | L32: =IF(C32>=13,1,"") | M32: =104.43*2 -> 208.86 | N32: =24.57*2 -> 49.14 | O32: =12*2 -> 24 | P32: =1.44*2 -> 2.88 | Q32: =5*2 -> 10 | S32: =10*2 -> 20 | T32: =10*2 -> 20 | V32: TAXA DE PREPARO 2/2 R$ 13,00 | W32: =IF(F32=SUM(M32:U32),"OK","Diferente") -> OK | X32: =IF(W32="Diferente",F32-SUM(M32:U32),"")
B33: JANAINA DE PÁDUA CARNEIRO VASCONCELOS GIFFONI | C33: 10 | D33: OK | E33: =SUM(M33:U33) -> 212.01 | F33: =E33 -> 212.01 | H33: Banco - Cora | L33: =IF(C33>=13,1,"") | M33: 156 | N33: 24.57 | O33: 12 | P33: 1.44 | Q33: 5 | U33: 13 | V33: TAXA DE PREPARO 2/2 R$ 13,00 | W33: =IF(F33=SUM(M33:U33),"OK","Diferente") -> OK | X33: =IF(W33="Diferente",F33-SUM(M33:U33),"")
B34: VICENTE ALVES GIFFONI | C34: 10 | D34: OK | E34: =SUM(M34:U34) -> 282.01 | F34: =E34 -> 282.01 | H34: Banco - Cora | L34: =IF(C34>=13,1,"") | M34: 156 | N34: 24.57 | O34: 12 | P34: 11.44 | Q34: 5 | R34: 10 | U34: 63 | V34: COMPRA DE ARCONDICIONADO 8/10 R$ 50,00; TAXA DE PREPARO 2/2 R$ 13,00 | W34: =IF(F34=SUM(M34:U34),"OK","Diferente") -> OK | X34: =IF(W34="Diferente",F34-SUM(M34:U34),"")
B35: RAPHAEL BRUNO DANTAS MOREIRA | C35: 19 | D35: OK | E35: =211.2-13 -> 198.2 | F35: =SUM(M35:U35) -> 396.4 | H35: Banco - Cora | L35: =IF(C35>=13,1,"") -> 1 | M35: =131.63*2 -> 263.26 | N35: =24.57*2 -> 49.14 | O35: =12*2 -> 24 | P35: 20 | Q35: 10 | R35: 30 | V35: TAXA DE PREPARO 2/2 R$ 13,00 | W35: =IF(F35=SUM(M35:U35),"OK","Diferente") -> OK | X35: =IF(W35="Diferente",F35-SUM(M35:U35),"")
B36: DAVI SILVINO MORAES | C36: 5 | D36: OK | E36: =SUM(M36:U36) -> 241.76 | F36: =E36 -> 241.76 | H36: Banco - Cora | L36: =IF(C36>=13,1,"") | M36: 132.19 | N36: 24.57 | O36: 12 | P36: 5 | Q36: 5 | R36: 10 | S36: 10 | T36: 30 | U36: 13 | V36: TAXA DE PREPARO 2/2 R$ 13,00 | W36: =IF(F36=SUM(M36:U36),"OK","Diferente") -> OK | X36: =IF(W36="Diferente",F36-SUM(M36:U36),"")
B37: DIMARANJE JOSÉ MORAES | E37: =SUM(M37:U37) -> 125.81 | L37: =IF(C37>=13,1,"") | M37: 74.74 | N37: 24.57 | O37: 12 | P37: 1.5 | U37: 13 | V37: TAXA DE PREPARO 2/2 R$ 13,00 | W37: =IF(F37=SUM(M37:U37),"OK","Diferente") -> Diferente | X37: =IF(W37="Diferente",F37-SUM(M37:U37),"") -> -125.81
B38: SILVANE DA SILVA GONÇALVES | C38: 15 | D38: OK | E38: 125.81 | F38: =SUM(M38:U38) -> 256.62 | H38: Banco - Cora | L38: =IF(C38>=13,1,"") -> 1 | M38: =74.74*2 -> 149.48 | N38: =24.57*2 -> 49.14 | O38: =12*2 -> 24 | P38: =1.5*2 -> 3 | U38: =26+5 -> 31 | V38: TAXA DE PREPARO 2/2 R$ 13,00 | W38: =IF(F38=SUM(M38:U38),"OK","Diferente") -> OK | X38: =IF(W38="Diferente",F38-SUM(M38:U38),"")
B39: VICENTE DE PAULA GIFFONI FILHO | C39: 10 | D39: OK | E39: =SUM(M39:U39) -> 179.44 | F39: =E39 -> 179.44 | H39: Banco - Cora | L39: =IF(C39>=13,1,"") | M39: 103.43 | N39: 24.57 | O39: 12 | P39: 1.44 | R39: 5 | U39: 33 | V39: TAXA DE PREPARO 2/2 R$ 13,00; JANTAR 1 ESCALA FEV R$ 20,00 | W39: =IF(F39=SUM(M39:U39),"OK","Diferente") -> OK | X39: =IF(W39="Diferente",F39-SUM(M39:U39),"")
B40: FRANCINETE ALVES DE OLIVEIRA GIFFONI | C40: 10 | D40: OK | E40: =SUM(M40:U40) -> 589.44 | F40: =E40 -> 589.44 | H40: Banco - Cora | L40: =IF(C40>=13,1,"") | M40: 103.43 | N40: 24.57 | O40: 12 | P40: 1.44 | Q40: 5 | R40: 5 | U40: 438 | V40: TAXA DE PREPARO 2/2 R$ 13,00; 2 Parcela Expedição Bom Conselho R$ 325,00; DOAÇÃO CANTINA SANA R$ 100,00 | W40: =IF(F40=SUM(M40:U40),"OK","Diferente") -> OK | X40: =IF(W40="Diferente",F40-SUM(M40:U40),"")
B41: EMANUEL ALVES GIFFONI | C41: 10 | D41: OK | E41: =SUM(M41:U41) -> 164.44 | F41: =E41 -> 164.44 | H41: Banco - Cora | L41: =IF(C41>=13,1,"") | M41: 103.43 | N41: 24.57 | O41: 12 | P41: 1.44 | Q41: 5 | R41: 5 | U41: 13 | V41: TAXA DE PREPARO 2/2 R$ 13,00 | W41: =IF(F41=SUM(M41:U41),"OK","Diferente") -> OK | X41: =IF(W41="Diferente",F41-SUM(M41:U41),"")
B42: FLORA ALVES GIFFONI | C42: 10 | D42: OK | E42: =SUM(M42:U42) -> 82.59 | F42: =E42 -> 82.59 | H42: Banco - Cora | L42: =IF(C42>=13,1,"") | M42: 31.58 | N42: 24.57 | O42: 12 | P42: 1.44 | U42: 13 | V42: TAXA DE PREPARO 2/2 R$ 13,00 | W42: =IF(F42=SUM(M42:U42),"OK","Diferente") -> OK | X42: =IF(W42="Diferente",F42-SUM(M42:U42),"")
B43: JÔNATAS CAVALCANTE BRAÚNA | C43: 1 | D43: Parcial | E43: 233 | F43: =SUM(M43:U43) -> 200 | G43: Pagamento em 01/02 referente a mensalidade de novembro. Fevereiro ainda está pendente. | H43: Banco - Cora | L43: =IF(C43>=13,1,"") | M43: 151.99 | N43: 24.57 | O43: 12 | P43: 1.44 | R43: 5 | S43: 5 | V43: TAXA DE PREPARO 2/2 R$ 13,00; JANTAR 1 ESCALA FEV R$ 20,00 | W43: =IF(F43=SUM(M43:U43),"OK","Diferente") -> OK | X43: =IF(W43="Diferente",F43-SUM(M43:U43),"")
B44: LUCAS MAIA DANTAS | C44: 11 | D44: OK | E44: =SUM(M44:U44) -> 311.89 | F44: =E44 -> 311.89 | H44: Banco - Cora | L44: =IF(C44>=13,1,"") | M44: 125.88 | N44: 24.57 | O44: 12 | P44: 1.44 | Q44: 5 | R44: 10 | S44: 20 | T44: 100 | U44: 13 | V44: TAXA DE PREPARO 2/2 R$ 13,00 | W44: =IF(F44=SUM(M44:U44),"OK","Diferente") -> OK | X44: =IF(W44="Diferente",F44-SUM(M44:U44),"")
B45: EMANUELA CRISTINE PEREIRA FELIX DANTAS | C45: 11 | D45: OK | E45: =SUM(M45:U45) -> 175.44 | F45: =E45 -> 175.44 | H45: Banco - Cora | L45: =IF(C45>=13,1,"") | M45: 99.43 | N45: 24.57 | O45: 12 | P45: 1.44 | Q45: 5 | S45: 20 | U45: 13 | V45: TAXA DE PREPARO 2/2 R$ 13,00 | W45: =IF(F45=SUM(M45:U45),"OK","Diferente") -> OK | X45: =IF(W45="Diferente",F45-SUM(M45:U45),"")
B46: LUCAS CALDAS OLIVEIRA | C46: 4 | D46: OK | E46: =SUM(M46:U46) -> 165 | F46: =E46 -> 165 | H46: Banco - Cora | L46: =IF(C46>=13,1,"") | M46: 93.43 | N46: 24.57 | O46: 12 | P46: 2 | Q46: 5 | R46: 5 | S46: 10 | U46: 13 | V46: TAXA DE PREPARO 2/2 R$ 13,00 | W46: =IF(F46=SUM(M46:U46),"OK","Diferente") -> OK | X46: =IF(W46="Diferente",F46-SUM(M46:U46),"")
B47: GABRIELA ARAUJO HOLANDA PINTO | C47: 4 | D47: OK | E47: =SUM(M47:U47) -> 87 | F47: =E47 -> 87 | H47: Banco - Cora | L47: =IF(C47>=13,1,"") | M47: 43.93 | N47: 24.57 | O47: 12 | P47: 1.5 | S47: 5 | W47: =IF(F47=SUM(M47:U47),"OK","Diferente") -> OK | X47: =IF(W47="Diferente",F47-SUM(M47:U47),"")
B48: VALTERLIR PEREIRA DE LIMA | C48: 1 | D48: OK | E48: 244.99 | F48: =SUM(M48:U48) -> 507.98 | G48: Realizado o pagamento das mensalidades de janeiro e fevereiro. | H48: Banco - Cora | L48: =IF(C48>=13,1,"") | M48: =118.98*2 -> 237.96 | N48: =24.57*2 -> 49.14 | O48: =12*2 -> 24 | P48: =11.44*2 -> 22.88 | Q48: =5*2 -> 10 | R48: =10*2 -> 20 | U48: =68+10+66 -> 144 | V48: COMPRA DE ARCONDICIONADO 8/10 R$ 50,00; TAXA DE PREPARO 2/2 R$ 13,00 | W48: =IF(F48=SUM(M48:U48),"OK","Diferente") -> OK | X48: =IF(W48="Diferente",F48-SUM(M48:U48),"")
B49: MARIA LUCIA FERREIRA DA SILVA LIMA | C49: 1 | D49: OK | E49: 106.74 | F49: =SUM(M49:U49) -> 205.48 | H49: Banco - Cora | L49: =IF(C49>=13,1,"") | M49: =55.73*2 -> 111.46 | N49: =24.57*2 -> 49.14 | O49: =12*2 -> 24 | P49: =1.44*2 -> 2.88 | U49: 18 | V49: TAXA DE PREPARO 2/2 R$ 13,00 | W49: =IF(F49=SUM(M49:U49),"OK","Diferente") -> OK | X49: =IF(W49="Diferente",F49-SUM(M49:U49),"")
B50: SALOMÃO JOSÉ MARQUES MACIEL | C50: 4 | D50: OK | E50: =SUM(M50:U50) -> 107.76 | F50: =SUM(M50:U50) -> 107.76 | H50: Banco - Cora | L50: =IF(C50>=13,1,"") | M50: 58.19 | N50: 24.57 | O50: 12 | P50: - | Q50: - | R50: - | S50: - | U50: 13 | V50: TAXA DE PREPARO 2/2 R$ 13,00 | W50: =IF(F50=SUM(M50:U50),"OK","Diferente") -> OK | X50: =IF(W50="Diferente",F50-SUM(M50:U50),"")
B51: ANA CLARA SIMONETTI GOMES MACIEL | C51: 4 | D51: OK | E51: =SUM(M51:U51) -> 83.45 | F51: =SUM(M51:U51) -> 83.45 | H51: Banco - Cora | L51: =IF(C51>=13,1,"") | M51: 33.88 | N51: 24.57 | O51: 12 | P51: - | R51: - | U51: 13 | V51: TAXA DE PREPARO 2/2 R$ 13,00 | W51: =IF(F51=SUM(M51:U51),"OK","Diferente") -> OK | X51: =IF(W51="Diferente",F51-SUM(M51:U51),"")
B52: RAFAEL LUNA HONÓRIO | C52: 24 | D52: OK | E52: =SUM(M52:U52) -> 204.69 | F52: =E52 -> 204.69 | H52: Banco - Cora | L52: =IF(C52>=13,1,"") -> 1 | M52: 93.62 | N52: 24.57 | O52: 12 | P52: 1.5 | S52: 10 | U52: 63 | V52: COMPRA DE ARCONDICIONADO 8/10 R$ 50,00; TAXA DE PREPARO 2/2 R$ 13,00 | W52: =IF(F52=SUM(M52:U52),"OK","Diferente") -> OK | X52: =IF(W52="Diferente",F52-SUM(M52:U52),"")
B53: JULIA ROGERIO FIORE CHEUEN | C53: 24 | D53: OK | E53: =SUM(M53:U53) -> 144.69 | F53: =E53 -> 144.69 | H53: Banco - Cora | L53: =IF(C53>=13,1,"") -> 1 | M53: 93.62 | N53: 24.57 | O53: 12 | P53: 1.5 | U53: 13 | V53: TAXA DE PREPARO 2/2 R$ 13,00 | W53: =IF(F53=SUM(M53:U53),"OK","Diferente") -> OK | X53: =IF(W53="Diferente",F53-SUM(M53:U53),"")
B54: ISABELA CLAREANA PEREIRA FELIX | C54: 9 | D54: OK | E54: =SUM(M54:U54) -> 195.44 | F54: =E54 -> 195.44 | H54: Banco - Cora | L54: =IF(C54>=13,1,"") | M54: 139.43 | N54: 24.57 | O54: 12 | P54: 1.44 | Q54: 5 | U54: 13 | V54: TAXA DE PREPARO 2/2 R$ 13,00 | W54: =IF(F54=SUM(M54:U54),"OK","Diferente") -> OK | X54: =IF(W54="Diferente",F54-SUM(M54:U54),"")
B55: PEDRO KLECIUS FARIAS CARDOSO | C55: 7 | D55: OK | E55: =SUM(M55:U55) -> 259.29 | F55: =E55 -> 259.29 | H55: Banco - Cora | L55: =IF(C55>=13,1,"") | M55: 98.28 | N55: 24.57 | O55: 12 | P55: 1.44 | R55: 10 | T55: 100 | U55: 13 | V55: TAXA DE PREPARO 2/2 R$ 13,00 | W55: =IF(F55=SUM(M55:U55),"OK","Diferente") -> OK | X55: =IF(W55="Diferente",F55-SUM(M55:U55),"")
B56: GENILDA DA SILVA CARDOSO | C56: 7 | D56: OK | E56: =SUM(M56:U56) -> 159.29 | F56: =E56 -> 159.29 | H56: Banco - Cora | L56: =IF(C56>=13,1,"") | M56: 98.28 | N56: 24.57 | O56: 12 | P56: 1.44 | R56: 10 | U56: 13 | V56: TAXA DE PREPARO 2/2 R$ 13,00 | W56: =IF(F56=SUM(M56:U56),"OK","Diferente") -> OK | X56: =IF(W56="Diferente",F56-SUM(M56:U56),"")
B57: MANOEL MESSIAS DO NASCIMENTO NETO | C57: 18 | D57: OK | E57: 70 | F57: =SUM(M57:U57) -> 170 | H57: Banco - Cora | L57: =IF(C57>=13,1,"") -> 1 | M57: =13.93+100 -> 113.93 | N57: 24.57 | O57: 12 | P57: 1.5 | Q57: 5 | U57: 13 | V57: TAXA DE PREPARO 2/2 R$ 13,00 | W57: =IF(F57=SUM(M57:U57),"OK","Diferente") -> OK | X57: =IF(W57="Diferente",F57-SUM(M57:U57),"")
B58: BRANDA DE PÁDUA CARNEIRO VASCONCELOS LESSA | C58: 4 | D58: OK | E58: =SUM(M58:U58) -> 163.5 | F58: =E58 -> 163.5 | H58: Banco - Cora | L58: =IF(C58>=13,1,"") | M58: 93.43 | N58: 24.57 | O58: 12 | P58: 1.5 | R58: 10 | S58: 4 | T58: 5 | U58: 13 | V58: TAXA DE PREPARO 2/2 R$ 13,00 | W58: =IF(F58=SUM(M58:U58),"OK","Diferente") -> OK | X58: =IF(W58="Diferente",F58-SUM(M58:U58),"")
B59: MATEUS CHAVES LESSA DE CASTRO | C59: 4 | D59: OK | E59: =SUM(M59:U59) -> 162.5 | F59: =E59 -> 162.5 | H59: Banco - Cora | L59: =IF(C59>=13,1,"") | M59: 93.43 | N59: 24.57 | O59: 12 | P59: 1.5 | R59: 10 | S59: 3 | T59: 5 | U59: 13 | V59: TAXA DE PREPARO 2/2 R$ 13,00 | W59: =IF(F59=SUM(M59:U59),"OK","Diferente") -> OK | X59: =IF(W59="Diferente",F59-SUM(M59:U59),"")
B60: ROSSYANE MARIA OLIVEIRA DA COSTA | C60: 4 | D60: OK | E60: =SUM(M60:U60) -> 100 | F60: =E60 -> 100 | H60: Banco - Cora | L60: =IF(C60>=13,1,"") | M60: 61.93 | N60: 24.57 | O60: 12 | P60: 1.5 | W60: =IF(F60=SUM(M60:U60),"OK","Diferente") -> OK | X60: =IF(W60="Diferente",F60-SUM(M60:U60),"")
B61: ALINE MIRANDA DE OLIVEIRA | E61: =SUM(M61:U61) -> 75.37 | L61: =IF(C61>=13,1,"") | M61: 19.36 | N61: 24.57 | O61: 12 | P61: 1.44 | Q61: 5 | U61: 13 | V61: TAXA DE PREPARO 2/2 R$ 13,00 | W61: =IF(F61=SUM(M61:U61),"OK","Diferente") -> Diferente | X61: =IF(W61="Diferente",F61-SUM(M61:U61),"") -> -75.37
B62: ANTÔNIO RAMON DA SILVA MAIA | E62: =SUM(M62:U62) -> 85.75 | L62: =IF(C62>=13,1,"") | M62: 29.74 | N62: 24.57 | O62: 12 | P62: 1.44 | Q62: 5 | U62: 13 | V62: TAXA DE PREPARO 2/2 R$ 13,00 | W62: =IF(F62=SUM(M62:U62),"OK","Diferente") -> Diferente | X62: =IF(W62="Diferente",F62-SUM(M62:U62),"") -> -85.75
B63: RAFAELY MAIA SOMBRA CORDEIRO | E63: =SUM(M63:U63) -> 86 | L63: =IF(C63>=13,1,"") | M63: 29.93 | N63: 24.57 | O63: 12 | P63: 1.5 | Q63: 5 | U63: 13 | V63: TAXA DE PREPARO 2/2 R$ 13,00 | W63: =IF(F63=SUM(M63:U63),"OK","Diferente") -> Diferente | X63: =IF(W63="Diferente",F63-SUM(M63:U63),"") -> -86
B64: FRANCISCO HILTON DOS SANTOS JÚNIOR | E64: =SUM(M64:U64) -> 163 | L64: =IF(C64>=13,1,"") | M64: 61.99 | N64: 24.57 | O64: 12 | P64: 1.44 | U64: 63 | V64: TAXA AÇÃO ENTRE AMIGOS 3/4 R$ 50,00; TAXA DE PREPARO 2/2 R$ 13,00 | W64: =IF(F64=SUM(M64:U64),"OK","Diferente") -> Diferente | X64: =IF(W64="Diferente",F64-SUM(M64:U64),"") -> -163
B65: IANNA DARC GOMES MARTINS | E65: =SUM(M65:U65) -> 151.07 | L65: =IF(C65>=13,1,"") | M65: 100 | N65: 24.57 | O65: 12 | P65: 1.5 | U65: 13 | V65: TAXA DE PREPARO 2/2 R$ 13,00 | W65: =IF(F65=SUM(M65:U65),"OK","Diferente") -> Diferente | X65: =IF(W65="Diferente",F65-SUM(M65:U65),"") -> -151.07
B66: MARCIO WALLACE EVANGELISTA TEIXEIRA | C66: 4 | D66: OK | E66: =SUM(M66:U66) -> 281.82 | F66: =E66 -> 281.82 | H66: Banco - Cora | L66: =IF(C66>=13,1,"") | M66: 122.25 | N66: 24.57 | O66: 12 | P66: 10 | Q66: 5 | R66: 5 | S66: 15 | T66: 25 | U66: 63 | V66: COMPRA DE ARCONDICIONADO 8/10 R$ 50,00; TAXA DE PREPARO 2/2 R$ 13,00 | W66: =IF(F66=SUM(M66:U66),"OK","Diferente") -> OK | X66: =IF(W66="Diferente",F66-SUM(M66:U66),"")
B67: JULIANA DIAS PERDIGÃO TEIXEIRA | C67: 4 | D67: OK | E67: =SUM(M67:U67) -> 231.82 | F67: =E67 -> 231.82 | H67: Banco - Cora | L67: =IF(C67>=13,1,"") | M67: 122.25 | N67: 24.57 | O67: 12 | P67: 10 | Q67: 5 | R67: 5 | S67: 15 | T67: 25 | U67: 13 | V67: TAXA DE PREPARO 2/2 R$ 13,00 | W67: =IF(F67=SUM(M67:U67),"OK","Diferente") -> OK | X67: =IF(W67="Diferente",F67-SUM(M67:U67),"")
B68: MATEUS DE MIRANDA DINO | C68: 14 | D68: OK | E68: =SUM(M68:U68) -> 244.44 | F68: =E68 -> 244.44 | H68: Banco - Cora | L68: =IF(C68>=13,1,"") -> 1 | M68: 113.43 | N68: 24.57 | O68: 12 | P68: 1.44 | Q68: 5 | R68: 20 | S68: 5 | U68: 63 | V68: TAXA DE PREPARO 2/2 R$ 13,00; DOAÇÃO CANTINA SANA R$ 50,00 | W68: =IF(F68=SUM(M68:U68),"OK","Diferente") -> OK | X68: =IF(W68="Diferente",F68-SUM(M68:U68),"")
B69: VITOR SANTOS DE OLIVEIRA | C69: 6 | D69: OK | E69: =SUM(M69:U69) -> 78.67 | F69: =E69 -> 78.67 | H69: Banco - Cora | L69: =IF(C69>=13,1,"") | M69: 27.66 | N69: 24.57 | O69: 12 | P69: 1.44 | U69: 13 | V69: TAXA DE PREPARO 2/2 R$ 13,00 | W69: =IF(F69=SUM(M69:U69),"OK","Diferente") -> OK | X69: =IF(W69="Diferente",F69-SUM(M69:U69),"")
B70: CARMEM SILVIA DE CARVALHO RÊGO | C70: 11 | D70: OK | E70: =SUM(M70:U70) -> 133 | F70: =E70 -> 133 | H70: Banco - Cora | L70: =IF(C70>=13,1,"") | M70: 81.93 | N70: 24.57 | O70: 12 | P70: 1.5 | U70: 13 | V70: TAXA DE PREPARO 2/2 R$ 13,00 | W70: =IF(F70=SUM(M70:U70),"OK","Diferente") -> OK | X70: =IF(W70="Diferente",F70-SUM(M70:U70),"")
B71: ANTONIO GILARDO XAVIER DE OLIVEIRA | E71: =SUM(M71:U71) -> 65 | L71: =IF(C71>=13,1,"") | M71: 13.93 | N71: 24.57 | O71: 12 | P71: 1.5 | U71: 13 | V71: TAXA DE PREPARO 2/2 R$ 13,00 | W71: =IF(F71=SUM(M71:U71),"OK","Diferente") -> Diferente | X71: =IF(W71="Diferente",F71-SUM(M71:U71),"") -> -65
B72: MARIA EUZANIRA BARBOSA OLIVEIRA | E72: =SUM(M72:U72) -> 65 | L72: =IF(C72>=13,1,"") | M72: 13.93 | N72: 24.57 | O72: 12 | P72: 1.5 | U72: 13 | V72: TAXA DE PREPARO 2/2 R$ 13,00 | W72: =IF(F72=SUM(M72:U72),"OK","Diferente") -> Diferente | X72: =IF(W72="Diferente",F72-SUM(M72:U72),"") -> -65
B73: THAMIRES CALDAS OLIVEIRA | C73: 10 | D73: OK | E73: =SUM(M73:U73) -> 113 | F73: =E73 -> 113 | H73: Banco - Cora | L73: =IF(C73>=13,1,"") | M73: 56.93 | N73: 24.57 | O73: 12 | P73: 1.5 | Q73: 5 | U73: 13 | V73: TAXA DE PREPARO 2/2 R$ 13,00 | W73: =IF(F73=SUM(M73:U73),"OK","Diferente") -> OK | X73: =IF(W73="Diferente",F73-SUM(M73:U73),"")
B74: MARIA JOSILENE BEZERRA | C74: 5 | D74: OK | E74: =SUM(M74:U74) -> 213 | F74: =E74 -> 213 | H74: Banco - Cora | L74: =IF(C74>=13,1,"") | M74: 148.43 | N74: 24.57 | O74: 12 | P74: 5 | Q74: 10 | U74: 13 | V74: TAXA DE PREPARO 2/2 R$ 13,00 | W74: =IF(F74=SUM(M74:U74),"OK","Diferente") -> OK | X74: =IF(W74="Diferente",F74-SUM(M74:U74),"")
B75: WLLYSSES JOSE MARQUES MACIEL | E75: =SUM(M75:U75) -> 70.39 | L75: =IF(C75>=13,1,"") | M75: 19.32 | N75: 24.57 | O75: 12 | P75: 1.5 | U75: 13 | V75: TAXA DE PREPARO 2/2 R$ 13,00 | W75: =IF(F75=SUM(M75:U75),"OK","Diferente") -> Diferente | X75: =IF(W75="Diferente",F75-SUM(M75:U75),"") -> -70.39
B76: DAILANE DE SOUZA FLORÊNCIO | C76: 11 | D76: OK | E76: =SUM(M76:U76) -> 80.74 | F76: =E76 -> 80.74 | H76: Banco - Cora | L76: =IF(C76>=13,1,"") | M76: 29.67 | N76: 24.57 | O76: 12 | P76: 1.5 | U76: 13 | V76: TAXA DE PREPARO 2/2 R$ 13,00 | W76: =IF(F76=SUM(M76:U76),"OK","Diferente") -> OK | X76: =IF(W76="Diferente",F76-SUM(M76:U76),"")
B77: SAMUEL DANTAS MOREIRA | C77: 20 | D77: OK | E77: 107.43 | F77: =SUM(M77:U77) -> 224.86 | G77: Pagamento das mensalidades de janeiro e fevereiro | H77: Banco - Cora | L77: =IF(C77>=13,1,"") -> 1 | M77: =50.86*2 -> 101.72 | N77: =24.57*2 -> 49.14 | O77: =12*2 -> 24 | P77: =2*2 -> 4 | Q77: =5*2 -> 10 | U77: 36 | V77: TAXA DE PREPARO 2/2 R$ 13,00 | W77: =IF(F77=SUM(M77:U77),"OK","Diferente") -> OK | X77: =IF(W77="Diferente",F77-SUM(M77:U77),"")
B78: LORENA RODRIGUES SALES DANTAS | C78: 20 | D78: OK | E78: 106.57 | F78: =SUM(M78:U78) -> 213.14 | G78: Pagamento das mensalidades de janeiro e fevereiro | H78: Banco - Cora | L78: =IF(C78>=13,1,"") -> 1 | M78: =50*2 -> 100 | N78: =24.57*2 -> 49.14 | O78: =12*2 -> 24 | P78: =2*2 -> 4 | Q78: =5*2 -> 10 | U78: 26 | V78: TAXA DE PREPARO 2/2 R$ 13,00 | W78: =IF(F78=SUM(M78:U78),"OK","Diferente") -> OK | X78: =IF(W78="Diferente",F78-SUM(M78:U78),"")
B79: DAVID NASCIMENTO ALEXANDRINO | C79: 9 | D79: OK | E79: =SUM(M79:U79) -> 144.69 | F79: =E79 -> 144.69 | H79: Banco - Cora | L79: =IF(C79>=13,1,"") | M79: 93.62 | N79: 24.57 | O79: 12 | P79: 1.5 | U79: 13 | V79: TAXA DE PREPARO 2/2 R$ 13,00 | W79: =IF(F79=SUM(M79:U79),"OK","Diferente") -> OK | X79: =IF(W79="Diferente",F79-SUM(M79:U79),"")
B80: MARYNA RIOS PAIVA | C80: 9 | D80: OK | E80: =SUM(M80:U80) -> 144.69 | F80: =E80 -> 144.69 | H80: Banco - Cora | L80: =IF(C80>=13,1,"") | M80: 93.62 | N80: 24.57 | O80: 12 | P80: 1.5 | U80: 13 | V80: TAXA DE PREPARO 2/2 R$ 13,00 | W80: =IF(F80=SUM(M80:U80),"OK","Diferente") -> OK | X80: =IF(W80="Diferente",F80-SUM(M80:U80),"")
B81: FRANCILENE ALVES DE OLIVEIRA BRAGA | C81: 6 | D81: OK | E81: =SUM(M81:U81) -> 306.57 | F81: =E81 -> 306.57 | H81: Banco - Cora | L81: =IF(C81>=13,1,"") | M81: 100 | N81: 24.57 | O81: 12 | P81: 2 | S81: 5 | U81: 163 | V81: TAXA DOAÇÃO CONSTRUÇÃO R$ 150,00; TAXA DE PREPARO 2/2 R$ 13,00 | W81: =IF(F81=SUM(M81:U81),"OK","Diferente") -> OK | X81: =IF(W81="Diferente",F81-SUM(M81:U81),"")
B82: ANA ALVES BRAGA | C82: 6 | D82: OK | E82: =SUM(M82:U82) -> 156.57 | F82: =E82 -> 156.57 | H82: Banco - Cora | L82: =IF(C82>=13,1,"") | M82: 100 | N82: 24.57 | O82: 12 | P82: 2 | S82: 5 | U82: 13 | V82: TAXA DE PREPARO 2/2 R$ 13,00 | W82: =IF(F82=SUM(M82:U82),"OK","Diferente") -> OK | X82: =IF(W82="Diferente",F82-SUM(M82:U82),"")
B83: RAFAEL CASTELO BRANCO MOURAO DE ANDRADE | E83: =SUM(M83:U83) -> 263 | L83: =IF(C83>=13,1,"") | M83: 196.43 | N83: 24.57 | O83: 12 | P83: 2 | S83: 5 | T83: 10 | U83: 13 | V83: TAXA DE PREPARO 2/2 R$ 13,00 | W83: =IF(F83=SUM(M83:U83),"OK","Diferente") -> Diferente | X83: =IF(W83="Diferente",F83-SUM(M83:U83),"") -> -263
B84: RAFAEL BARBOSA DE SOUZA | C84: 4 | D84: OK | E84: =SUM(M84:U84) -> 260 | F84: =E84 -> 260 | H84: Banco - Cora | L84: =IF(C84>=13,1,"") | M84: 138.43 | N84: 24.57 | O84: 12 | P84: 2 | Q84: 5 | R84: 5 | S84: 10 | U84: 63 | V84: COMPRA DE ARCONDICIONADO 8/10 R$ 50,00; TAXA DE PREPARO 2/2 R$ 13,00 | W84: =IF(F84=SUM(M84:U84),"OK","Diferente") -> OK | X84: =IF(W84="Diferente",F84-SUM(M84:U84),"")
B85: SARAH GOMES PINHEIRO | C85: 4 | D85: OK | E85: =SUM(M85:U85) -> 210 | F85: =E85 -> 210 | H85: Banco - Cora | L85: =IF(C85>=13,1,"") | M85: 138.43 | N85: 24.57 | O85: 12 | P85: 2 | Q85: 5 | R85: 5 | S85: 10 | U85: 13 | V85: TAXA DE PREPARO 2/2 R$ 13,00 | W85: =IF(F85=SUM(M85:U85),"OK","Diferente") -> OK | X85: =IF(W85="Diferente",F85-SUM(M85:U85),"")
B86: YARA FREITAS DE CARVALHO DE AGUIAR | E86: =SUM(M86:U86) -> 125.23 | L86: =IF(C86>=13,1,"") | M86: 33.93 | N86: 24.57 | O86: 12 | P86: 1.5 | U86: 53.23 | V86: ACORDO MENSALIDADE 6/10 R$ 40,23; TAXA DE PREPARO 2/2 R$ 13,00 | W86: =IF(F86=SUM(M86:U86),"OK","Diferente") -> Diferente | X86: =IF(W86="Diferente",F86-SUM(M86:U86),"") -> -125.23
B87: POLLYANNA APARECIDA BATISTA VIANA | C87: 7 | D87: OK | E87: =SUM(M87:U87) -> 176.57 | F87: =E87 -> 176.57 | H87: Banco - Cora | L87: =IF(C87>=13,1,"") | M87: 120 | N87: 24.57 | O87: 12 | P87: 2 | S87: 5 | U87: 13 | V87: TAXA DE PREPARO 2/2 R$ 13,00 | W87: =IF(F87=SUM(M87:U87),"OK","Diferente") -> OK | X87: =IF(W87="Diferente",F87-SUM(M87:U87),"")
B88: JOÃO VIANA FILHO | C88: 7 | D88: OK | E88: =SUM(M88:U88) -> 176.57 | F88: =E88 -> 176.57 | H88: Banco - Cora | L88: =IF(C88>=13,1,"") | M88: 120 | N88: 24.57 | O88: 12 | P88: 2 | S88: 5 | U88: 13 | V88: TAXA DE PREPARO 2/2 R$ 13,00 | W88: =IF(F88=SUM(M88:U88),"OK","Diferente") -> OK | X88: =IF(W88="Diferente",F88-SUM(M88:U88),"")
B89: FRANCISCA SONIA COSTA | C89: 4 | D89: OK | E89: =SUM(M89:U89) -> 165 | F89: =E89 -> 165 | H89: Banco - Cora | L89: =IF(C89>=13,1,"") | M89: 108.43 | N89: 24.57 | O89: 12 | P89: 2 | S89: 5 | U89: 13 | V89: TAXA DE PREPARO 2/2 R$ 13,00 | W89: =IF(F89=SUM(M89:U89),"OK","Diferente") -> OK | X89: =IF(W89="Diferente",F89-SUM(M89:U89),"")
B90: RAQUEL DA SILVA MAIA | C90: 4 | D90: OK | E90: =SUM(M90:U90) -> 114.5 | F90: =E90 -> 114.5 | H90: Banco - Cora | L90: =IF(C90>=13,1,"") | M90: 63.43 | N90: 24.57 | O90: 12 | P90: 1.5 | U90: 13 | V90: TAXA DE PREPARO 2/2 R$ 13,00 | W90: =IF(F90=SUM(M90:U90),"OK","Diferente") -> OK | X90: =IF(W90="Diferente",F90-SUM(M90:U90),"")
B91: FRANCISCO ELEILTON MENDONÇA DO NASCIMENTO | C91: 4 | D91: OK | E91: =SUM(M91:U91) -> 164.5 | F91: =E91 -> 164.5 | H91: Banco - Cora | L91: =IF(C91>=13,1,"") | M91: 63.43 | N91: 24.57 | O91: 12 | P91: 1.5 | U91: 63 | V91: COMPRA DE ARCONDICIONADO 8/10 R$ 50,00; TAXA DE PREPARO 2/2 R$ 13,00 | W91: =IF(F91=SUM(M91:U91),"OK","Diferente") -> OK | X91: =IF(W91="Diferente",F91-SUM(M91:U91),"")
B92: MARIA ROSINELE FELIX DO NASCIMENTO | C92: 10 | D92: OK | E92: 160 | F92: =SUM(M92:U92) -> 325 | H92: Banco - Cora | L92: =IF(C92>=13,1,"") | M92: =93.93*2 -> 187.86 | N92: =24.57*2 -> 49.14 | O92: =12*2 -> 24 | P92: =1.5*2 -> 3 | Q92: =5*2 -> 10 | S92: =10*2 -> 20 | U92: =13*2+5 -> 31 | V92: TAXA DE PREPARO 2/2 R$ 13,00 | W92: =IF(F92=SUM(M92:U92),"OK","Diferente") -> OK | X92: =IF(W92="Diferente",F92-SUM(M92:U92),"")
B93: RARISNEIDE DA SILVA MAIA | C93: 11 | D93: OK | E93: 195 | F93: =195+170-2 -> 363 | H93: Banco - Cora | L93: =IF(C93>=13,1,"") | M93: =108.43*2 -> 216.86 | N93: =24.57*2 -> 49.14 | O93: =12*2 -> 24 | P93: 4 | S93: 10 | U93: =43+18-2 -> 59 | V93: TAXA DE PREPARO 2/2 R$ 13,00; DOAÇÃO CANTINA SANA R$ 30,00 | W93: =IF(F93=SUM(M93:U93),"OK","Diferente") -> OK | X93: =IF(W93="Diferente",F93-SUM(M93:U93),"")
B94: VITOR BISPO BRAÚNA | C94: 10 | D94: OK | E94: =SUM(M94:U94) -> 163 | F94: =E94 -> 163 | H94: Banco - Cora | L94: =IF(C94>=13,1,"") | M94: 113.43 | N94: 24.57 | O94: 12 | U94: 13 | V94: TAXA DE PREPARO 2/2 R$ 13,00 | W94: =IF(F94=SUM(M94:U94),"OK","Diferente") -> OK | X94: =IF(W94="Diferente",F94-SUM(M94:U94),"")
B95: WESLEY ALESSANDRO RIBEIRO SILVA | C95: 5 | D95: Parcial | E95: 24 | F95: =SUM(M95:U95) -> 48 | H95: Banco - Cora | L95: =IF(C95>=13,1,"") | M95: =-12.57*2 -> -25.14 | N95: =24.57*2 -> 49.14 | O95: =12*2 -> 24 | W95: =IF(F95=SUM(M95:U95),"OK","Diferente") -> OK | X95: =IF(W95="Diferente",F95-SUM(M95:U95),"")
B96: ANA GEORGINA OLIVEIRA PONTES COSTA | C96: 7 | D96: OK | E96: =SUM(M96:U96) -> 138 | F96: =E96 -> 138 | H96: Banco - Cora | L96: =IF(C96>=13,1,"") | M96: 88.43 | N96: 24.57 | O96: 12 | U96: 13 | V96: TAXA DE PREPARO 2/2 R$ 13,00 | W96: =IF(F96=SUM(M96:U96),"OK","Diferente") -> OK | X96: =IF(W96="Diferente",F96-SUM(M96:U96),"")
B97: MARCOS FELIPE DA SILVA MAIA | C97: 11 | D97: OK | E97: 63 | F97: =63+68 -> 131 | H97: Banco - Cora | L97: =IF(C97>=13,1,"") | M97: =13.43*2 -> 26.86 | N97: =24.57*2 -> 49.14 | O97: =12*2 -> 24 | U97: =26+5 -> 31 | V97: TAXA DE PREPARO 2/2 R$ 13,00 | W97: =IF(F97=SUM(M97:U97),"OK","Diferente") -> OK | X97: =IF(W97="Diferente",F97-SUM(M97:U97),"")
B98: JALSEY PEREIRA DE NAZARENO | C98: 10 | D98: OK | E98: =SUM(M98:U98) -> 143 | F98: =E98 -> 143 | H98: Banco - Cora | L98: =IF(C98>=13,1,"") | M98: 91.93 | N98: 24.57 | O98: 12 | P98: 1.5 | U98: 13 | V98: TAXA DE PREPARO 2/2 R$ 13,00 | W98: =IF(F98=SUM(M98:U98),"OK","Diferente") -> OK | X98: =IF(W98="Diferente",F98-SUM(M98:U98),"")
B99: SUZANA PAIVA BEZERRA DE NAZARENO | C99: 10 | D99: OK | E99: =SUM(M99:U99) -> 143 | F99: =E99 -> 143 | H99: Banco - Cora | L99: =IF(C99>=13,1,"") | M99: 91.93 | N99: 24.57 | O99: 12 | P99: 1.5 | U99: 13 | V99: TAXA DE PREPARO 2/2 R$ 13,00 | W99: =IF(F99=SUM(M99:U99),"OK","Diferente") -> OK | X99: =IF(W99="Diferente",F99-SUM(M99:U99),"")
B100: PEDRO VICTOR MIRANDA DE OLIVEIRA SALVIANO | E100: =SUM(M100:U100) -> 78 | L100: =IF(C100>=13,1,"") | M100: 26.43 | N100: 24.57 | O100: 12 | P100: 2 | U100: 13 | V100: TAXA DE PREPARO 2/2 R$ 13,00 | W100: =IF(F100=SUM(M100:U100),"OK","Diferente") -> Diferente | X100: =IF(W100="Diferente",F100-SUM(M100:U100),"") -> -78
B101: FRANCISCO RIBEIRO PINTO JÚNIOR | C101: 24 | D101: OK | E101: =SUM(M101:U101) -> 152 | F101: =E101 -> 152 | H101: Banco - Cora | L101: =IF(C101>=13,1,"") -> 1 | M101: 100.43 | N101: 24.57 | O101: 12 | P101: 2 | U101: 13 | V101: TAXA DE PREPARO 2/2 R$ 13,00 | W101: =IF(F101=SUM(M101:U101),"OK","Diferente") -> OK | X101: =IF(W101="Diferente",F101-SUM(M101:U101),"")
B102: MARIA EDUARDA ARAUJO HOLANDA PINTO | C102: 5 | D102: OK | E102: =SUM(M102:U102) -> 70 | F102: =E102 -> 70 | H102: Banco - Cora | L102: =IF(C102>=13,1,"") | M102: 31.43 | N102: 24.57 | O102: 12 | P102: 2 | W102: =IF(F102=SUM(M102:U102),"OK","Diferente") -> OK | X102: =IF(W102="Diferente",F102-SUM(M102:U102),"")
...

Sheet FEV-Despesas
B2: DESPESAS
B4: TOTAL | C4: - | D4: - | E4: =SUBTOTAL(9,E16,E63,E38,E147,E174,E180,E93,E6,E34,E236,E277,E186,E196,E206,E216,E226,E119) -> 0 | F4: =SUBTOTAL(9,F16,F63,F38,F137,F147,F174,F180,F93,F6,F34,F236,F277,F186,F196,F206,F216,F226,F119) -> 23123.13 | G4: - | H4: CAIXA | I4: COMPROVANTE | J4: PLANO DE CONTAS DG
C5: Data | D5: Efetivado | E5: Valor Previsto | F5: Valor Pago | G5: Observação
B6: NCL - Funcionários | C6: - | D6: - | E6: =SUM(E7:E15) -> 0 | F6: =SUMIF(D7:D15,"OK",F7:F15) -> 849.79
B7: Salário | C7: 1 | D7: OK | E7: 0 | F7: 286.63 | H7: Banco - Cora | I7: https://drive.google.com/open?id=1O6wt_FJqQeu9sRaLffH-7f8S0G1oTxGT&usp=drive_fs
B8: 13° salário | E8: 0 | F8: 0
B9: Férias | E9: 0 | F9: 0
B10: Encargos sociais | C10: 17 | D10: OK | E10: 0 | F10: 84.82 | G10: FGTS | H10: Banco - Cora | I10: https://drive.google.com/open?id=1_6Fp_ExyTvjqF1-M_cFw6x_XHF5SBwfd&usp=drive_fs
B11: Encargos sociais | C11: 18 | D11: OK | E11: 0 | F11: 374.25 | G11: INSS e PIS | H11: Banco - Cora | I11: https://drive.google.com/open?id=1PRSSbRhljf-e9cOSeCLfcLlcya7A-WGn&usp=drive_fs
B12: Encargos sociais | C12: 18 | D12: OK | E12: 0 | F12: 49.1 | G12: Darf Previdenciário Complementar | H12: Banco - Cora | I12: https://drive.google.com/open?id=1C0yr4ScNd5mr0j4PNPd0eYK7pwse8o-v&usp=drive_fs
B13: Encargos sociais | E13: 0 | F13: 0
B14: Cesta básica | C14: 1 | D14: OK | E14: 0 | F14: 54.99 | H14: Banco - Cora | I14: https://drive.google.com/open?id=1hHruZaR6cC30sU6q-7R-YHFyKmrXFSAy&usp=drive_fs
B15: Outras despesas | E15: 0 | F15: 0
B16: NCL - Repasses | C16: - | D16: - | E16: =SUM(E17:E33) -> 0 | F16: =SUMIF(D17:D33,"OK",F17:F33) -> 4132.98
B17: Diretoria Geral - FP | C17: 27 | D17: OK | E17: 0 | F17: 1380.48 | G17: Pagmento único de R$ 2.742,72 | H17: Banco - Cora | I17: https://drive.google.com/open?id=1BV1TM7EJJOxGzv3O6dWUL6FCUk_S1IqE&usp=drive_fs
B18: Diretoria Geral - FS | C18: 27 | D18: OK | E18: 0 | F18: 786.24 | H18: Banco - Cora
B19: Diretoria Geral - FA | C19: 27 | D19: OK | E19: 0 | F19: 96 | H19: Banco - Cora
B20: Diretoria Geral - FB | C20: 27 | D20: OK | E20: 0 | F20: 96 | H20: Banco - Cora
B21: Diretoria Geral - SUC | C21: 27 | D21: OK | E21: 0 | F21: 384 | H21: Banco - Cora
B22: 11a Região - Fundo Regional | C22: 14 | D22: OK | E22: 0 | F22: 313.92 | G22: Pagamento único de R$ 1.152,00 | H22: Banco - Cora | I22: https://drive.google.com/open?id=1Qev215rRAFtb-WX8wlSxfiZmjf01B-uq&usp=drive_fs
B23: 11a Região - Plantio | C23: 14 | D23: OK | E23: 0 | F23: 360 | H23: Banco - Cora
B24: 11a Região - Fundo de Beneficência | C24: 14 | D24: OK | E24: 0 | F24: 446.4 | H24: Banco - Cora
B25: 11a Região - Fundo de Reserva | C25: 14 | D25: OK | E25: 0 | F25: 31.68 | H25: Banco - Cora
B26: 11a Região - Servidor Vreal | E26: 0 | F26: 0
B27: 11a Região - Sala da Região | E27: 0 | F27: 0
B28: 11a Região - Extra | E28: 0 | F28: 0
B29: Novo Encanto | C29: 14 | D29: OK | E29: 0 | F29: 84 | H29: Banco - Cora | I29: https://drive.google.com/open?id=1a5hTa8y0XMozRz-dSa0UfTNgd1TXVSNN&usp=drive_fs
B30: Flor Divina | E30: 0 | F30: 0
B31: Memorial José Gabriel da Costa | E31: 0 | F31: 0
B32: 11a Região - Taxa Extra - Fazenda Bom Conselho | C32: 14 | D32: OK | E32: 0 | F32: 154.26 | G32: Parcela 1 de 5 | H32: Banco - Cora | I32: https://drive.google.com/open?id=1yMIEbscznedImJATd1aMtLmE74IOR5Pc&usp=drive_fs
B33: Outro repasse | E33: 0 | F33: 0
B34: NCL - Tarifas bancárias | C34: - | D34: - | E34: =SUM(E35:E37) -> 0 | F34: =SUMIF(D35:D37,"OK",F35:F37) -> 0.51
B35: IR Rendimento Pagbank | C35: 24 | D35: OK | E35: 0 | F35: 0.51 | H35: Banco - Pagbank | I35: https://drive.google.com/open?id=1EZKxuF5v6r4e1MWObNeB-OSTAhOjh2so&usp=drive_fs
B36: Tarifa 2 | E36: 0 | F36: 0
B37: Tarifa 3 | E37: 0 | F37: 0
B38: NCL - Despesas gerais | C38: - | D38: - | E38: =SUM(E39:E62) -> 0 | F38: =SUMIF(D39:D62,"OK",F39:F62) -> 4759.87
B39: Energia Elétrica | C39: 26 | D39: OK | E39: 0 | F39: 1366.01 | H39: Banco - Cora | I39: https://drive.google.com/open?id=1lkLy44LTEH8bIakW8xjzsl2Dvq7Pj4nw&usp=drive_fs
B40: Vigilância - 2a escala | C40: 16 | D40: OK | E40: 0 | F40: 650 | H40: Banco - Cora | I40: https://drive.google.com/open?id=1DkfAoPGLAksRJx39XhQZ5I7U-PW2DCPH&usp=drive_fs
B41: Vigilância - Extra | E41: 0 | F41: 0
B42: Contabilidade | E42: 0 | F42: 0
B43: Internet | C43: 17 | D43: OK | E43: 0 | F43: 84.9 | H43: Banco - Cora | I43: https://drive.google.com/open?id=1zcTOhjziZmZOazHr9soDf0vj6t6FzluS&usp=drive_fs
B44: Ar Condicionado Berçário | C44: 28 | D44: OK | E44: 0 | F44: 518 | G44: Parcela 8 de 10 | H44: Banco - Stone | I44: https://drive.google.com/open?id=1qM0bmoZb2tRtYR_dkQ9EOIt2CY2QrEgp&usp=drive_fs
B45: Mesa de som | C45: 28 | D45: OK | E45: 0 | F45: 212.9 | G45: Parcela 7 de 10 | H45: Banco - Cora | I45: https://drive.google.com/open?id=1fv7DPHWgAJ90vz5Z9Nz1vYkK6QuHHFIC&usp=drive_fs
B46: Cafeteira para cozinha | C46: 1 | D46: OK | E46: 0 | F46: 89.9 | H46: Banco - Cora | I46: https://drive.google.com/open?id=1SWRPL_XQ4U3I_el6ODCAtdMV9hiBqS0C&usp=drive_fs
B47: Almoço mutirão 10 de fevereiro | C47: 9 | D47: OK | E47: 0 | F47: 340 | H47: Banco - Cora | I47: https://drive.google.com/open?id=1RERbl7w2UXAn8Ac0mJoHHC54Q4ufAls7&usp=drive_fs
B48: Almoço mutirão 10 de fevereiro | C48: 9 | D48: OK | E48: 0 | F48: 155.16 | H48: Banco - Cora | I48: https://drive.google.com/open?id=1UcpZH2PTAFgTZ04X04oZikW8sWlTBVHr&usp=drive_fs
B49: Conserto bicicietas recebidas de doação | C49: 17 | D49: OK | E49: 0 | F49: =175 -> 175 | G49: Marcelo | H49: Banco - Cora | I49: https://drive.google.com/open?id=1yPQau5DqlkuT8rzI-LREwJYI2W27Wi0X&usp=drive_fs
B50: Jantar 10 de fevereiro | C50: 17 | D50: OK | E50: 0 | F50: 499 | H50: Banco - Cora | I50: https://drive.google.com/open?id=1AaH7sYx4Us13jdMCTKjkWbtzMP-EAgqB&usp=drive_fs
B51: Lembrancinha Aniv. M. Cassio | C51: 13 | D51: OK | E51: 0 | F51: 189 | G51: Gabi | H51: Banco - Cora | I51: https://drive.google.com/open?id=1ixgRGpDpS0EhZzTfMdQBWWsyol3anVpR&usp=drive_fs
B52: Frete de doações recebidas da receita federal | C52: 21 | D52: OK | E52: 0 | F52: 100 | H52: Banco - Cora | I52: https://drive.google.com/open?id=1vrjrq3eoP7iM4XdbTcyIheWhbMVvzfiD&usp=drive_fs
B53: Conserto de 3 celulares recebidos de doação | C53: 21 | D53: OK | E53: 0 | F53: 380 | G53: Marcelo | H53: Banco - Cora | I53: https://drive.google.com/open?id=1QtmrmcrHAkMPqWUwvUavu2A0tPnRZ9Vo&usp=drive_fs
B54: Despesa | E54: 0 | F54: 0
B55: Despesa | E55: 0 | F55: 0
B56: Despesa | E56: 0 | F56: 0
B57: Despesa | E57: 0 | F57: 0
B58: Despesa | E58: 0 | F58: 0
B59: Despesa | E59: 0 | F59: 0
B60: Despesa | E60: 0 | F60: 0
B61: Despesa | E61: 0 | F61: 0
B62: Despesa | E62: 0 | F62: 0
B63: NCL - Organ | C63: - | D63: - | E63: =SUM(E64:E92) -> 0 | F63: =SUMIF(D64:D92,"OK",F64:F92) -> 3437.61
B64: Lanche 1a escala | C64: 3 | D64: OK | E64: 0 | F64: 70 | G64: Sucos | H64: Banco - Cora | I64: https://drive.google.com/open?id=1XSPaxZsHs2ETNkZoubdK1KuQGDslR2YT&usp=drive_fs
B65: Lanche 1a escala | C65: 3 | D65: OK | E65: 0 | F65: 60.32 | G65: Bolos | H65: Banco - Cora | I65: https://drive.google.com/open?id=1wxOUDpvD9hlGn7MskIi_K76SpL1YDx_2&usp=drive_fs
B66: Lanche 1a escala | C66: 4 | D66: OK | E66: 0 | F66: 45 | G66: Água de coco | H66: Banco - Cora | I66: https://drive.google.com/open?id=14jgG_XXs40B0Jlmq5Yxj--UPkQR2N7Na&usp=drive_fs
B67: Lanche 1a escala | C67: 1 | D67: OK | E67: 0 | F67: 95.65 | G67: Este valor está lançado, porém não houve transação bancária. A C. Mônica solicitou que 4 compras da Organ realizadas por ela fossem abatidas do valor da mensalidade de janeiro. As 4 compras totalizam R$ 449,41, enquanto o valor da mensalidade é R$ 472,13. Dessa forma, foi lançado o valor de R$ 449,41 como receita de mensalidade para equiparar esta despesa. | H67: Banco - Cora | I67: https://drive.google.com/open?id=1vN2OKmi72TDB89I6IjHdlHYd4Z1gYPqY&usp=drive_fs
B68: Lanche 1a escala | C68: 1 | D68: OK | E68: 0 | F68: 148.25 | G68: Este valor está lançado, porém não houve transação bancária. A C. Mônica solicitou que 4 compras da Organ realizadas por ela fossem abatidas do valor da mensalidade de janeiro. As 4 compras totalizam R$ 449,41, enquanto o valor da mensalidade é R$ 472,13. Dessa forma, foi lançado o valor de R$ 449,41 como receita de mensalidade para equiparar esta despesa. | H68: Banco - Cora | I68: https://drive.google.com/open?id=1XFikbqKy32SczPI25V1bLCLRh10mhQrw&usp=drive_fs
B69: Lanche 1a escala | E69: 0 | F69: 0
B70: Lanche 1a escala | E70: 0 | F70: 0
B71: Lanche 1a escala | E71: 0 | F71: 0
B72: Lanche 2a escala | C72: 15 | D72: OK | E72: 0 | F72: 316.76 | H72: Banco - Cora | I72: https://drive.google.com/open?id=12uTj9_HSjfZGk17GE1L7DM8xHNgbjwjm&usp=drive_fs
B73: Lanche 2a escala | C73: 15 | D73: OK | E73: 0 | F73: 140 | G73: Sucos | H73: Banco - Cora | I73: https://drive.google.com/open?id=1QAB4baNTSUL2lGZqyEa8DpuraAYJ5o6G&usp=drive_fs
B74: Jantar 2a escala | C74: 15 | D74: OK | E74: 0 | F74: 131.69 | H74: Banco - Cora | I74: https://drive.google.com/open?id=1hmXMNMTl1tTJibMrNkII57pzEc9QhNLq&usp=drive_fs
B75: Lanche 2a escala | C75: 20 | D75: OK | E75: 0 | F75: 45 | G75: Euzanira | H75: Banco - Cora | I75: https://drive.google.com/open?id=14jgG_XXs40B0Jlmq5Yxj--UPkQR2N7Na&usp=drive_fs
B76: Lanche 1a escala de março + feriado | C76: 28 | D76: OK | E76: 0 | F76: 335 | G76: Sucos. Desse valor, temos R$ 90 referente a sessão de escala e R$ 245 referente ao feriado. | H76: Banco - Cora | I76: https://drive.google.com/open?id=1Mngk9E_Ns0wD52FbMvIKCsvUQGplnmZk&usp=drive_fs
B77: Lanche 2a escala | E77: 0 | F77: 0
B78: Lanche 2a escala | E78: 0 | F78: 0
B79: Lanche 2a escala | E79: 0 | F79: 0
B80: Mercado | C80: 1 | D80: OK | E80: 0 | F80: 145.57 | G80: Este valor está lançado, porém não houve transação bancária. A C. Mônica solicitou que 4 compras da Organ realizadas por ela fossem abatidas do valor da mensalidade de janeiro. As 4 compras totalizam R$ 449,41, enquanto o valor da mensalidade é R$ 472,13. Dessa forma, foi lançado o valor de R$ 449,41 como receita de mensalidade para equiparar esta despesa. | H80: Banco - Cora | I80: https://drive.google.com/open?id=1aoGS2cof2HrfgBlzqg1FKHIxtXyOSVP-&usp=drive_fs
B81: Mercado | C81: 10 | D81: OK | E81: 0 | F81: 267.7 | H81: Banco - Cora | I81: https://drive.google.com/open?id=1GkzUtyqCyzEFSaSKpa1622qQTh5RlHTg&usp=drive_fs
B82: Mercado | C82: 15 | D82: OK | E82: 0 | F82: 98.95 | G82: Lanche reunião de diretoria e tira gosto | H82: Banco - Cora | I82: https://drive.google.com/open?id=1bKloDsyijPDLPydlWzB_LxxuX_EuElZV&usp=drive_fs
B83: Mercado | C83: 14 | D83: OK | E83: 0 | F83: 164.9 | G83: Sacos de lixo | H83: Banco - Cora | I83: https://drive.google.com/open?id=1OT9YzvdI1mWv1rx0oVZ4jJLktVxkSDdK&usp=drive_fs
B84: Mercado | E84: 0 | F84: 0
B85: Água mineral | C85: 28 | D85: OK | E85: 0 | F85: 184 | H85: Banco - Cora | I85: https://drive.google.com/open?id=1pB6eTF_KtxS_i5oNsKg3N36kF7mtycv2&usp=drive_fs
B86: Água mineral | E86: 0 | F86: 0
B87: Jantar 1a escala | C87: 1 | D87: OK | E87: 0 | F87: 331.4 | H87: Banco - Cora | I87: https://drive.google.com/open?id=1O8g7NtH-cgVJu5t9f-0d8ZdEkyEIYQmH&usp=drive_fs
B88: Jantar 1a escala | C88: 5 | D88: OK | E88: 0 | F88: 48.38 | H88: Banco - Cora | I88: https://drive.google.com/open?id=1ALkyGby2dS61gylsutVZ8UFpExH25KBF&usp=drive_fs
B89: Jantar 1a escala | C89: 8 | D89: OK | E89: 0 | F89: 225.49 | H89: Banco - Cora | I89: https://drive.google.com/open?id=1snO2Uwa30PnDb8AlJxmSmHoolqxnp2Lf&usp=drive_fs
B90: Jantar 2a escala | C90: 15 | D90: OK | E90: 0 | F90: 405.61 | H90: Banco - Cora | I90: https://drive.google.com/open?id=1bfkKkev6CsRLnMhwPksk3ZmEBVsrgOOE&usp=drive_fs
B91: Outra despesa | C91: 1 | D91: OK | E91: 0 | F91: 59.94 | G91: Este valor está lançado, porém não houve transação bancária. A C. Mônica solicitou que 4 compras da Organ realizadas por ela fossem abatidas do valor da mensalidade de janeiro. As 4 compras totalizam R$ 449,41, enquanto o valor da mensalidade é R$ 472,13. Dessa forma, foi lançado o valor de R$ 449,41 como receita de mensalidade para equiparar esta despesa. | H91: Banco - Cora | I91: https://drive.google.com/open?id=1PColXYGRBBEw6Ey2f2UV0Tcb5uDUB4Yc&usp=drive_fs
B92: Outra despesa | C92: 9 | D92: OK | E92: 0 | F92: 118 | G92: 1 Botijão de gás | H92: Banco - Cora | I92: https://drive.google.com/open?id=1mfOvRjwW3fWcb9QDBEjTSfh9L2jIGf24&usp=drive_fs
B93: NCL - Preparo | C93: - | D93: - | E93: =SUM(E94,E110,E115) -> 0 | F93: =SUM(F94,F110,F115) -> 0
B94: Organ | E94: =SUM(E95:E108) -> 0 | F94: =SUMIF(D95:D109,"OK",F95:F109) -> 0
B95: Mercado - Sucos | E95: 0 | F95: 0
B96: Mercado - Alimentação | E96: 0 | F96: 0
B97: Mercado - Jantar sexta-feira | E97: 0 | F97: 0
B98: Mercado - Alimentação | E98: 0 | F98: 0
B99: Mercado - Alimentação | E99: 0 | F99: 0
B100: Mercado - Café da manhã | E100: 0 | F100: 0
B101: Mercado - Almoço sábado | E101: 0 | F101: 0
B102: Mercado - Almoço sábado | E102: 0 | F102: 0
...

Sheet MAR-Receitas
B2: RECEITAS
B4: TOTAL | E4: =SUM(E6,E127,E151,E175,E179) -> 19818.78 | F4: =SUM(F6,F127,F151,F175,F179) -> 25745.35 | H4: CAIXA | I4: PLANO DE CONTAS DG
C5: Data | D5: Efetivado | E5: Valor Previsto | F5: Valor Recebido | G5: Observação | J5: Inadimp. (qtd) | K5: Inadimp. (R$) | L5: % Atraso | M5: Núcleo | N5: Repasse DG | O5: Repasse 11a R | P5: Benef. NLT | Q5: NE NLT | R5: Plantio NLT | S5: FR Bilhete Aéreo | T5: FR Construção | U5: Taxa Extra | V5: Detalhamento Taxa Extra | X5: A receber:
B6: Mensalidade | C6: 10 | D6: - | E6: =SUM(E7:E126) -> 19818.78 | F6: =SUMIF(D7:D126,"OK",F7:F126)+SUMIF(D7:D126,"Parcial",F7:F126) -> 17374.56 | G6: - | J6: =(COUNTIF(D7:D126,"Pendente")+COUNTIF(D7:D126,"Parcial"))/COUNTA(B7:B126) -> 0.24489796 | K6: =IFERROR(-(X6/E6),"Pendente info") -> 0.17028394 | L6: =SUM(L7:L105)/COUNTA(B7:B105) -> 0.10204082 | M6: =SUMIF($D$7:$D$126,"OK",M7:M126)+SUMIF($D$7:$D$126,"Parcial",M7:M126) -> 8869.87 | N6: =SUMIF($D$7:$D$126,"OK",N7:N126)+SUMIF($D$7:$D$126,"Parcial",N7:N126) -> 1842.75 | O6: =SUMIF($D$7:$D$126,"OK",O7:O126)+SUMIF($D$7:$D$126,"Parcial",O7:O126) -> 900 | P6: =SUMIF($D$7:$D$126,"OK",P7:P126)+SUMIF($D$7:$D$126,"Parcial",P7:P126) -> 178.94 | Q6: =SUMIF($D$7:$D$126,"OK",Q7:Q126)+SUMIF($D$7:$D$126,"Parcial",Q7:Q126) -> 170 | R6: =SUMIF($D$7:$D$126,"OK",R7:R126)+SUMIF($D$7:$D$126,"Parcial",R7:R126) -> 205 | S6: =SUMIF($D$7:$D$126,"OK",S7:S126)+SUMIF($D$7:$D$126,"Parcial",S7:S126) -> 262 | T6: =SUMIF($D$7:$D$126,"OK",T7:T126)+SUMIF($D$7:$D$126,"Parcial",T7:T126) -> 600 | U6: =SUMIF($D$7:$D$126,"OK",U7:U126)+SUMIF($D$7:$D$126,"Parcial",U7:U126) -> 4346 | V6: - | W6: =IF(F6=SUM(M6:U6),"OK","Diferente") -> OK | X6: =SUM(X7:X126) -> -3374.82
B7: ELPÍDIO GOMES DE MOURA NETO | D7: OK | L7: =IF(C7>=13,1,"") | V7: 10 DE FEVEREIRO R$ 18,00; TAXA PREPARO 1/2 R$ 25,00; TAXA ENCONTRO CASAL DIREÇÃO R$ 30,00 | W7: =IF(F7=SUM(M7:U7),"OK","Diferente") -> OK | X7: =IF(W7="Diferente",F7-SUM(M7:U7),"")
B8: JULIANA COLLYER ARRUDA DE MOURA | D8: OK | L8: =IF(C8>=13,1,"") | V8: 10 DE FEVEREIRO R$ 18,00; TAXA PREPARO 1/2 R$ 25,00 | W8: =IF(F8=SUM(M8:U8),"OK","Diferente") -> OK | X8: =IF(W8="Diferente",F8-SUM(M8:U8),"")
B9: SILVERIA LOPES VASCONCELOS ARRUDA | D9: OK | L9: =IF(C9>=13,1,"") | V9: 10 DE FEVEREIRO R$ 18,00; TAXA PREPARO 1/2 R$ 25,00 | W9: =IF(F9=SUM(M9:U9),"OK","Diferente") -> OK | X9: =IF(W9="Diferente",F9-SUM(M9:U9),"")
B10: FRANCISCO DE ASSIS VASCONCELOS ARRUDA | D10: OK | L10: =IF(C10>=13,1,"") | V10: 10 DE FEVEREIRO R$ 18,00; TAXA PREPARO 1/2 R$ 25,00 | W10: =IF(F10=SUM(M10:U10),"OK","Diferente") -> OK | X10: =IF(W10="Diferente",F10-SUM(M10:U10),"")
B11: ANTÔNIO GONÇALVES DE LIMA FILHO | C11: 9 | D11: OK | E11: =SUM(M11:U11) -> 218.43 | F11: =E11 -> 218.43 | H11: Banco - Cora | L11: =IF(C11>=13,1,"") | M11: 130 | N11: 24.57 | O11: 12 | P11: 3.86 | Q11: 5 | U11: 43 | V11: 10 DE FEVEREIRO R$ 18,00; TAXA PREPARO 1/2 R$ 25,00 | W11: =IF(F11=SUM(M11:U11),"OK","Diferente") -> OK | X11: =IF(W11="Diferente",F11-SUM(M11:U11),"")
B12: SANDRA BORGES GONÇALVES DE LIMA | C12: 9 | D12: OK | E12: =SUM(M12:U12) -> 226.57 | F12: =E12 -> 226.57 | H12: Banco - Cora | L12: =IF(C12>=13,1,"") | M12: 130 | N12: 24.57 | O12: 12 | P12: 2 | U12: 58 | V12: 10 DE FEVEREIRO R$ 18,00; TAXA PREPARO 1/2 R$ 25,00; TAXA ENCONTRO CASAL DIREÇÃO R$ 15,00 | W12: =IF(F12=SUM(M12:U12),"OK","Diferente") -> OK | X12: =IF(W12="Diferente",F12-SUM(M12:U12),"")
B13: MARCELO DE CASTRO BRASIL | D13: Pendente | E13: =SUM(M13:U13) -> 421.49 | L13: =IF(C13>=13,1,"") | M13: 130.48 | N13: 24.57 | O13: 12 | P13: 1.44 | Q13: 10 | R13: 20 | S13: 50 | T13: 50 | U13: 123 | V13: COMPRA DE ARCONDICIONADO 9/10 R$ 50,00; 10 DE FEVEREIRO R$ 18,00; TAXA PREPARO 1/2 R$ 25,00; TAXA ENCONTRO CASAL DIREÇÃO R$ 30,00 | W13: =IF(F13=SUM(M13:U13),"OK","Diferente") -> Diferente | X13: =IF(W13="Diferente",F13-SUM(M13:U13),"") -> -421.49
B14: FLORA BORGES GONÇALVES LIMA BRASIL | D14: Pendente | E14: =SUM(M14:U14) -> 234.29 | L14: =IF(C14>=13,1,"") | M14: 98.28 | N14: 24.57 | O14: 12 | P14: 1.44 | Q14: 5 | T14: 50 | U14: 43 | V14: 10 DE FEVEREIRO R$ 18,00; TAXA PREPARO 1/2 R$ 25,00 | W14: =IF(F14=SUM(M14:U14),"OK","Diferente") -> Diferente | X14: =IF(W14="Diferente",F14-SUM(M14:U14),"") -> -234.29
B15: CÁSSIO PEREIRA COSTA SOUSA | C15: 6 | D15: Parcial | E15: 371.14 | F15: =SUM(M15:U15) -> 685.3 | G15: Mensalidades de janeiro a março totaliza R$ 1.036,98, adicionando R$ 170 da taxa do feriado do carnaval dá R$ 1.206,98. Deste valor, foi abatido R$ 866,29 de compras da Organ realizadas pela C. Mônica, restando um saldo a pagar de R$ 340,69. | H15: Banco - Cora | L15: =IF(C15>=13,1,"") | M15: =180.13+314.16 -> 494.29 | N15: 24.57 | O15: 12 | P15: 1.44 | Q15: 5 | R15: 5 | S15: 20 | U15: 123 | V15: COMPRA DE ARCONDICIONADO 9/10 R$ 50,00; 10 DE FEVEREIRO R$ 18,00; TAXA PREPARO 1/2 R$ 25,00; TAXA ENCONTRO CASAL DIREÇÃO R$ 30,00 | W15: =IF(F15=SUM(M15:U15),"OK","Diferente") -> OK | X15: =IF(W15="Diferente",F15-SUM(M15:U15),"")
B16: MÔNICA DE ARAUJO CAMPOS COSTA SOUSA | C16: 6 | D16: Parcial | E16: 180.99 | F16: =SUM(M16:U16) -> 180.99 | H16: Banco - Cora | L16: =IF(C16>=13,1,"") | M16: 89.98 | N16: 24.57 | O16: 12 | P16: 1.44 | Q16: 5 | R16: 5 | U16: 43 | V16: 10 DE FEVEREIRO R$ 18,00; TAXA PREPARO 1/2 R$ 25,00 | W16: =IF(F16=SUM(M16:U16),"OK","Diferente") -> OK | X16: =IF(W16="Diferente",F16-SUM(M16:U16),"")
B17: JOSÉ MAURÍCIO GUIMARÃES GOMES | C17: 1 | D17: OK | E17: =SUM(M17:U17) -> 307.19 | F17: =E17 -> 307.19 | H17: Banco - Cora | L17: =IF(C17>=13,1,"") | M17: 191.18 | N17: 24.57 | O17: 12 | P17: 1.44 | Q17: 5 | U17: 73 | V17: 10 DE FEVEREIRO R$ 18,00; TAXA PREPARO 1/2 R$ 25,00; TAXA ENCONTRO CASAL DIREÇÃO R$ 30,00 | W17: =IF(F17=SUM(M17:U17),"OK","Diferente") -> OK | X17: =IF(W17="Diferente",F17-SUM(M17:U17),"")
B18: TICIANE ARAGAO DA SILVEIRA GOMES | C18: 1 | D18: OK | E18: =SUM(M18:U18) -> 216.99 | F18: =E18 -> 216.99 | H18: Banco - Cora | L18: =IF(C18>=13,1,"") | M18: 135.98 | N18: 24.57 | O18: 12 | P18: 1.44 | U18: 43 | V18: 10 DE FEVEREIRO R$ 18,00; TAXA PREPARO 1/2 R$ 25,00 | W18: =IF(F18=SUM(M18:U18),"OK","Diferente") -> OK | X18: =IF(W18="Diferente",F18-SUM(M18:U18),"")
B19: SERVULO SIDNEY GLADIUS PAIVA PIMENTEL | C19: 1 | D19: OK | E19: =SUM(M19:U19) -> 514.29 | F19: =E19 -> 514.29 | H19: Banco - Cora | L19: =IF(C19>=13,1,"") | M19: 328.28 | N19: 24.57 | O19: 12 | P19: 11.44 | Q19: 5 | R19: 10 | T19: 50 | U19: 73 | V19: 10 DE FEVEREIRO R$ 18,00; TAXA PREPARO 1/2 R$ 25,00; TAXA ENCONTRO CASAL DIREÇÃO R$ 30,00 | W19: =IF(F19=SUM(M19:U19),"OK","Diferente") -> OK | X19: =IF(W19="Diferente",F19-SUM(M19:U19),"")
B20: MARIA DANIELLY RIOS DA SILVA PAIVA | C20: 1 | D20: OK | E20: =SUM(M20:U20) -> 474.29 | F20: =E20 -> 474.29 | H20: Banco - Cora | L20: =IF(C20>=13,1,"") | M20: 328.28 | N20: 24.57 | O20: 12 | P20: 1.44 | Q20: 5 | R20: 10 | T20: 50 | U20: 43 | V20: 10 DE FEVEREIRO R$ 18,00; TAXA PREPARO 1/2 R$ 25,00 | W20: =IF(F20=SUM(M20:U20),"OK","Diferente") -> OK | X20: =IF(W20="Diferente",F20-SUM(M20:U20),"")
B21: RÉGIS BEZERRA GOMES | C21: 11 | D21: OK | E21: =SUM(M21:U21) -> 321.99 | F21: =E21 -> 321.99 | H21: Banco - Cora | L21: =IF(C21>=13,1,"") | M21: 120.98 | N21: 24.57 | O21: 12 | P21: 1.44 | Q21: 5 | R21: 5 | T21: 30 | U21: 123 | V21: COMPRA DE ARCONDICIONADO 9/10 R$ 50,00; 10 DE FEVEREIRO R$ 18,00; TAXA PREPARO 1/2 R$ 25,00; TAXA ENCONTRO CASAL DIREÇÃO R$ 30,00 | W21: =IF(F21=SUM(M21:U21),"OK","Diferente") -> OK | X21: =IF(W21="Diferente",F21-SUM(M21:U21),"")
B22: ANA CAROLINA DE OLIVEIRA MARTINS GOMES | C22: 11 | D22: OK | E22: =SUM(M22:U22) -> 218.59 | F22: =E22 -> 218.59 | H22: Banco - Cora | L22: =IF(C22>=13,1,"") | M22: 102.58 | N22: 24.57 | O22: 12 | P22: 1.44 | Q22: 5 | T22: 30 | U22: 43 | V22: 10 DE FEVEREIRO R$ 18,00; TAXA PREPARO 1/2 R$ 25,00 | W22: =IF(F22=SUM(M22:U22),"OK","Diferente") -> OK | X22: =IF(W22="Diferente",F22-SUM(M22:U22),"")
B23: LINDAYANA DE SOUZA FLORÊNCIO | D23: Pendente | E23: =SUM(M23:U23) -> 208.34 | L23: =IF(C23>=13,1,"") | M23: 37.33 | N23: 24.57 | O23: 12 | P23: 1.44 | Q23: 5 | R23: 5 | U23: 123 | V23: COMPRA DE ARCONDICIONADO 9/10 R$ 50,00; 10 DE FEVEREIRO R$ 18,00; TAXA PREPARO 1/2 R$ 25,00; TAXA ENCONTRO CASAL DIREÇÃO R$ 30,00 | W23: =IF(F23=SUM(M23:U23),"OK","Diferente") -> Diferente | X23: =IF(W23="Diferente",F23-SUM(M23:U23),"") -> -208.34
B24: DAVI FLORENCIO DE SOUSA | D24: Pendente | E24: =SUM(M24:U24) -> 159.44 | L24: =IF(C24>=13,1,"") | M24: 53.43 | N24: 24.57 | O24: 12 | P24: 1.44 | Q24: 5 | R24: 5 | T24: 15 | U24: 43 | V24: 10 DE FEVEREIRO R$ 18,00; TAXA PREPARO 1/2 R$ 25,00 | W24: =IF(F24=SUM(M24:U24),"OK","Diferente") -> Diferente | X24: =IF(W24="Diferente",F24-SUM(M24:U24),"") -> -159.44
B25: JOAQUIM GARCEZ DE LIMA ROCHA | C25: 11 | D25: OK | E25: =SUM(M25:U25) -> 228 | F25: =E25 -> 228 | H25: Banco - Cora | L25: =IF(C25>=13,1,"") | M25: 131.99 | N25: 24.57 | O25: 12 | P25: 6.44 | R25: 10 | U25: 43 | V25: 10 DE FEVEREIRO R$ 18,00; TAXA PREPARO 1/2 R$ 25,00 | W25: =IF(F25=SUM(M25:U25),"OK","Diferente") -> OK | X25: =IF(W25="Diferente",F25-SUM(M25:U25),"")
B26: FRANCISCO SAULO STUDART ALBUQUERQUE | D26: Pendente | E26: =SUM(M26:U26) -> 153 | L26: =IF(C26>=13,1,"") | M26: 71.43 | N26: 24.57 | O26: 12 | P26: 2 | U26: 43 | V26: 10 DE FEVEREIRO R$ 18,00; TAXA PREPARO 1/2 R$ 25,00 | W26: =IF(F26=SUM(M26:U26),"OK","Diferente") -> Diferente | X26: =IF(W26="Diferente",F26-SUM(M26:U26),"") -> -153
B27: FRANCO COSTA E SILVA | C27: 11 | D27: OK | E27: =SUM(M27:U27) -> 338 | F27: =E27 -> 338 | H27: Banco - Cora | L27: =IF(C27>=13,1,"") | M27: 131.99 | N27: 24.57 | O27: 12 | P27: 11.44 | Q27: 5 | R27: 5 | S27: 10 | T27: 30 | U27: 108 | V27: COMPRA DE ARCONDICIONADO 9/10 R$ 50,00; 10 DE FEVEREIRO R$ 18,00; TAXA PREPARO 1/2 R$ 25,00; TAXA ENCONTRO CASAL DIREÇÃO R$ 15,00 | W27: =IF(F27=SUM(M27:U27),"OK","Diferente") -> OK | X27: =IF(W27="Diferente",F27-SUM(M27:U27),"")
B28: JULIANA SOARES MONTEIRO | C28: 11 | D28: OK | E28: =SUM(M28:U28) -> 263 | F28: =E28 -> 263 | H28: Banco - Cora | L28: =IF(C28>=13,1,"") | M28: 131.99 | N28: 24.57 | O28: 12 | P28: 1.44 | Q28: 5 | R28: 5 | S28: 10 | T28: 30 | U28: 43 | V28: 10 DE FEVEREIRO R$ 18,00; TAXA PREPARO 1/2 R$ 25,00 | W28: =IF(F28=SUM(M28:U28),"OK","Diferente") -> OK | X28: =IF(W28="Diferente",F28-SUM(M28:U28),"")
B29: HUGO UCHOA PASSOS ALENCAR | C29: 11 | D29: OK | E29: =SUM(M29:U29) -> 332.69 | F29: =E29 -> 332.69 | H29: Banco - Cora | L29: =IF(C29>=13,1,"") | M29: 116.68 | N29: 24.57 | O29: 12 | P29: 1.44 | Q29: 5 | R29: 10 | S29: 10 | T29: 30 | U29: 123 | V29: COMPRA DE ARCONDICIONADO 9/10 R$ 50,00; 10 DE FEVEREIRO R$ 18,00; TAXA PREPARO 1/2 R$ 25,00; TAXA ENCONTRO CASAL DIREÇÃO R$ 30,00 | W29: =IF(F29=SUM(M29:U29),"OK","Diferente") -> OK | X29: =IF(W29="Diferente",F29-SUM(M29:U29),"")
B30: MAIRI ALENCAR DE LACERDA FERRAZ UCHÔA | C30: 11 | D30: OK | E30: =SUM(M30:U30) -> 201.69 | F30: =E30 -> 201.69 | H30: Banco - Cora | L30: =IF(C30>=13,1,"") | M30: 70.68 | N30: 24.57 | O30: 12 | P30: 1.44 | R30: 10 | S30: 10 | T30: 30 | U30: 43 | V30: 10 DE FEVEREIRO R$ 18,00; TAXA PREPARO 1/2 R$ 25,00 | W30: =IF(F30=SUM(M30:U30),"OK","Diferente") -> OK | X30: =IF(W30="Diferente",F30-SUM(M30:U30),"")
B31: JOÃO CARLOS STUDART ANTERO | C31: 15 | D31: OK | E31: =SUM(M31:U31) -> 302.44 | F31: =E31 -> 302.44 | H31: Banco - Cora | L31: =IF(C31>=13,1,"") -> 1 | M31: 104.43 | N31: 24.57 | O31: 12 | P31: 1.44 | Q31: 5 | S31: 10 | T31: 10 | U31: 135 | V31: DOAÇÃO CANTINA SANA R$ 92,00; 10 DE FEVEREIRO R$ 18,00; TAXA PREPARO 1/2 R$ 25,00 | W31: =IF(F31=SUM(M31:U31),"OK","Diferente") -> OK | X31: =IF(W31="Diferente",F31-SUM(M31:U31),"")
B32: JANAÍNA SILVA LEITÃO STUDART ANTERO | C32: 15 | D32: OK | E32: =SUM(M32:U32) -> 210.44 | F32: =E32 -> 210.44 | H32: Banco - Cora | L32: =IF(C32>=13,1,"") -> 1 | M32: 104.43 | N32: 24.57 | O32: 12 | P32: 1.44 | Q32: 5 | S32: 10 | T32: 10 | U32: 43 | V32: 10 DE FEVEREIRO R$ 18,00; TAXA PREPARO 1/2 R$ 25,00 | W32: =IF(F32=SUM(M32:U32),"OK","Diferente") -> OK | X32: =IF(W32="Diferente",F32-SUM(M32:U32),"")
B33: JANAINA DE PÁDUA CARNEIRO VASCONCELOS GIFFONI | C33: 10 | D33: OK | E33: =SUM(M33:U33) -> 242.01 | F33: =E33 -> 242.01 | H33: Banco - Cora | L33: =IF(C33>=13,1,"") | M33: 156 | N33: 24.57 | O33: 12 | P33: 1.44 | Q33: 5 | U33: 43 | V33: 10 DE FEVEREIRO R$ 18,00; TAXA PREPARO 1/2 R$ 25,00 | W33: =IF(F33=SUM(M33:U33),"OK","Diferente") -> OK | X33: =IF(W33="Diferente",F33-SUM(M33:U33),"")
B34: VICENTE ALVES GIFFONI | C34: 10 | D34: OK | E34: =SUM(M34:U34) -> 342.01 | F34: =E34 -> 342.01 | H34: Banco - Cora | L34: =IF(C34>=13,1,"") | M34: 156 | N34: 24.57 | O34: 12 | P34: 11.44 | Q34: 5 | R34: 10 | U34: 123 | V34: COMPRA DE ARCONDICIONADO 9/10 R$ 50,00; 10 DE FEVEREIRO R$ 18,00; TAXA PREPARO 1/2 R$ 25,00; TAXA ENCONTRO CASAL DIREÇÃO R$ 30,00 | W34: =IF(F34=SUM(M34:U34),"OK","Diferente") -> OK | X34: =IF(W34="Diferente",F34-SUM(M34:U34),"")
B35: RAPHAEL BRUNO DANTAS MOREIRA | D35: Pendente | E35: =SUM(M35:U35) -> 483.4 | L35: =IF(C35>=13,1,"") | M35: 48.43 | N35: 24.57 | O35: 12 | P35: 2 | Q35: 0 | R35: 0 | U35: 396.4 | V35: ACORDO 2/4 R$ 396,40 | W35: =IF(F35=SUM(M35:U35),"OK","Diferente") -> Diferente | X35: =IF(W35="Diferente",F35-SUM(M35:U35),"") -> -483.4
B36: DAVI SILVINO MORAES | C36: 5 | D36: OK | E36: =SUM(M36:U36) -> 271.76 | F36: =E36 -> 271.76 | H36: Banco - Cora | L36: =IF(C36>=13,1,"") | M36: 132.19 | N36: 24.57 | O36: 12 | P36: 5 | Q36: 5 | R36: 10 | S36: 10 | T36: 30 | U36: 43 | V36: 10 DE FEVEREIRO R$ 18,00; TAXA PREPARO 1/2 R$ 25,00 | W36: =IF(F36=SUM(M36:U36),"OK","Diferente") -> OK | X36: =IF(W36="Diferente",F36-SUM(M36:U36),"")
B37: DIMARANJE JOSÉ MORAES | C37: 9 | D37: OK | E37: =SUM(M37:U37) -> 155.81 | F37: =E37 -> 155.81 | H37: Banco - Cora | L37: =IF(C37>=13,1,"") | M37: 74.74 | N37: 24.57 | O37: 12 | P37: 1.5 | U37: 43 | V37: 10 DE FEVEREIRO R$ 18,00; TAXA PREPARO 1/2 R$ 25,00 | W37: =IF(F37=SUM(M37:U37),"OK","Diferente") -> OK | X37: =IF(W37="Diferente",F37-SUM(M37:U37),"")
B38: SILVANE DA SILVA GONÇALVES | C38: 9 | D38: OK | E38: =SUM(M38:U38) -> 185.81 | F38: =E38 -> 185.81 | H38: Banco - Cora | L38: =IF(C38>=13,1,"") | M38: 74.74 | N38: 24.57 | O38: 12 | P38: 1.5 | U38: 73 | V38: 10 DE FEVEREIRO R$ 18,00; TAXA PREPARO 1/2 R$ 25,00; TAXA ENCONTRO CASAL DIREÇÃO R$ 30,00 | W38: =IF(F38=SUM(M38:U38),"OK","Diferente") -> OK | X38: =IF(W38="Diferente",F38-SUM(M38:U38),"")
B39: VICENTE DE PAULA GIFFONI FILHO | C39: 11 | D39: OK | E39: =SUM(M39:U39) -> 189.44 | F39: =SUM(M39:U39) -> 189.44 | H39: Banco - Cora | L39: =IF(C39>=13,1,"") | M39: 103.43 | N39: 24.57 | O39: 12 | P39: 1.44 | R39: 5 | U39: 43 | V39: 10 DE FEVEREIRO R$ 18,00; TAXA PREPARO 1/2 R$ 25,00 | W39: =IF(F39=SUM(M39:U39),"OK","Diferente") -> OK | X39: =IF(W39="Diferente",F39-SUM(M39:U39),"")
B40: FRANCINETE ALVES DE OLIVEIRA GIFFONI | C40: 11 | D40: OK | E40: =SUM(M40:U40) -> 194.44 | F40: =SUM(M40:U40) -> 194.44 | H40: Banco - Cora | L40: =IF(C40>=13,1,"") | M40: 103.43 | N40: 24.57 | O40: 12 | P40: 1.44 | Q40: 5 | R40: 5 | U40: 43 | V40: 10 DE FEVEREIRO R$ 18,00; TAXA PREPARO 1/2 R$ 25,00 | W40: =IF(F40=SUM(M40:U40),"OK","Diferente") -> OK | X40: =IF(W40="Diferente",F40-SUM(M40:U40),"")
B41: EMANUEL ALVES GIFFONI | C41: 11 | D41: OK | E41: =SUM(M41:U41) -> 194.44 | F41: =SUM(M41:U41) -> 194.44 | H41: Banco - Cora | L41: =IF(C41>=13,1,"") | M41: 103.43 | N41: 24.57 | O41: 12 | P41: 1.44 | Q41: 5 | R41: 5 | U41: 43 | V41: 10 DE FEVEREIRO R$ 18,00; TAXA PREPARO 1/2 R$ 25,00 | W41: =IF(F41=SUM(M41:U41),"OK","Diferente") -> OK | X41: =IF(W41="Diferente",F41-SUM(M41:U41),"")
B42: FLORA ALVES GIFFONI | C42: 11 | D42: OK | E42: =SUM(M42:U42) -> 112.59 | F42: =SUM(M42:U42) -> 112.59 | H42: Banco - Cora | L42: =IF(C42>=13,1,"") | M42: 31.58 | N42: 24.57 | O42: 12 | P42: 1.44 | U42: 43 | V42: 10 DE FEVEREIRO R$ 18,00; TAXA PREPARO 1/2 R$ 25,00 | W42: =IF(F42=SUM(M42:U42),"OK","Diferente") -> OK | X42: =IF(W42="Diferente",F42-SUM(M42:U42),"")
B43: JÔNATAS CAVALCANTE BRAÚNA | C43: 7 | D43: Parcial | E43: 243 | F43: =SUM(M43:U43) -> 418 | H43: Banco - Cora | L43: =IF(C43>=13,1,"") | M43: =151.99*2 -> 303.98 | N43: =24.57*2 -> 49.14 | O43: =12*2 -> 24 | P43: =1.44*2 -> 2.88 | R43: =5*2 -> 10 | S43: =5*2 -> 10 | U43: 18 | V43: 10 DE FEVEREIRO R$ 18,00; TAXA PREPARO 1/2 R$ 25,00 | W43: =IF(F43=SUM(M43:U43),"OK","Diferente") -> OK | X43: =IF(W43="Diferente",F43-SUM(M43:U43),"")
B44: LUCAS MAIA DANTAS | C44: 11 | D44: OK | E44: =SUM(M44:U44) -> 341.89 | F44: =E44 -> 341.89 | H44: Banco - Cora | L44: =IF(C44>=13,1,"") | M44: 125.88 | N44: 24.57 | O44: 12 | P44: 1.44 | Q44: 5 | R44: 10 | S44: 20 | T44: 100 | U44: 43 | V44: 10 DE FEVEREIRO R$ 18,00; TAXA PREPARO 1/2 R$ 25,00 | W44: =IF(F44=SUM(M44:U44),"OK","Diferente") -> OK | X44: =IF(W44="Diferente",F44-SUM(M44:U44),"")
B45: EMANUELA CRISTINE PEREIRA FELIX DANTAS | C45: 11 | D45: OK | E45: =SUM(M45:U45) -> 205.44 | F45: =E45 -> 205.44 | H45: Banco - Cora | L45: =IF(C45>=13,1,"") | M45: 99.43 | N45: 24.57 | O45: 12 | P45: 1.44 | Q45: 5 | S45: 20 | U45: 43 | V45: 10 DE FEVEREIRO R$ 18,00; TAXA PREPARO 1/2 R$ 25,00 | W45: =IF(F45=SUM(M45:U45),"OK","Diferente") -> OK | X45: =IF(W45="Diferente",F45-SUM(M45:U45),"")
B46: LUCAS CALDAS OLIVEIRA | C46: 1 | D46: OK | E46: =SUM(M46:U46) -> 195 | F46: =E46 -> 195 | H46: Banco - Cora | L46: =IF(C46>=13,1,"") | M46: 93.43 | N46: 24.57 | O46: 12 | P46: 2 | Q46: 5 | R46: 5 | S46: 10 | U46: 43 | V46: 10 DE FEVEREIRO R$ 18,00; TAXA PREPARO 1/2 R$ 25,00 | W46: =IF(F46=SUM(M46:U46),"OK","Diferente") -> OK | X46: =IF(W46="Diferente",F46-SUM(M46:U46),"")
B47: GABRIELA ARAUJO HOLANDA PINTO | C47: 1 | D47: OK | E47: =SUM(M47:U47) -> 130 | F47: =E47 -> 130 | H47: Banco - Cora | L47: =IF(C47>=13,1,"") | M47: 43.93 | N47: 24.57 | O47: 12 | P47: 1.5 | S47: 5 | U47: 43 | V47: 10 DE FEVEREIRO R$ 18,00; TAXA PREPARO 1/2 R$ 25,00 | W47: =IF(F47=SUM(M47:U47),"OK","Diferente") -> OK | X47: =IF(W47="Diferente",F47-SUM(M47:U47),"")
B48: VALTERLIR PEREIRA DE LIMA | C48: 10 | D48: OK | E48: =SUM(M48:U48) -> 275 | F48: =E48 -> 275 | H48: Banco - Cora | L48: =IF(C48>=13,1,"") | M48: 118.99 | N48: 24.57 | O48: 12 | P48: 11.44 | Q48: 5 | R48: 10 | U48: 93 | V48: COMPRA DE ARCONDICIONADO 9/10 R$ 50,00; 10 DE FEVEREIRO R$ 18,00; TAXA PREPARO 1/2 R$ 25,00 | W48: =IF(F48=SUM(M48:U48),"OK","Diferente") -> OK | X48: =IF(W48="Diferente",F48-SUM(M48:U48),"")
B49: MARIA LUCIA FERREIRA DA SILVA LIMA | C49: 10 | D49: OK | E49: =SUM(M49:U49) -> 136.74 | F49: =E49 -> 136.74 | H49: Banco - Cora | L49: =IF(C49>=13,1,"") | M49: 55.73 | N49: 24.57 | O49: 12 | P49: 1.44 | U49: 43 | V49: 10 DE FEVEREIRO R$ 18,00; TAXA PREPARO 1/2 R$ 25,00 | W49: =IF(F49=SUM(M49:U49),"OK","Diferente") -> OK | X49: =IF(W49="Diferente",F49-SUM(M49:U49),"")
B50: SALOMÃO JOSÉ MARQUES MACIEL | C50: 10 | D50: OK | E50: =SUM(M50:U50) -> 137.76 | F50: =E50 -> 137.76 | H50: Banco - Cora | L50: =IF(C50>=13,1,"") | M50: 58.19 | N50: 24.57 | O50: 12 | P50: - | Q50: - | R50: - | S50: - | U50: 43 | V50: 10 DE FEVEREIRO R$ 18,00; TAXA PREPARO 1/2 R$ 25,00 | W50: =IF(F50=SUM(M50:U50),"OK","Diferente") -> OK | X50: =IF(W50="Diferente",F50-SUM(M50:U50),"")
B51: ANA CLARA SIMONETTI GOMES MACIEL | C51: 10 | D51: OK | E51: =SUM(M51:U51) -> 113.45 | F51: =E51 -> 113.45 | H51: Banco - Cora | L51: =IF(C51>=13,1,"") | M51: 33.88 | N51: 24.57 | O51: 12 | P51: - | R51: - | U51: 43 | V51: 10 DE FEVEREIRO R$ 18,00; TAXA PREPARO 1/2 R$ 25,00 | W51: =IF(F51=SUM(M51:U51),"OK","Diferente") -> OK | X51: =IF(W51="Diferente",F51-SUM(M51:U51),"")
B52: RAFAEL LUNA HONÓRIO | D52: Pendente | E52: =SUM(M52:U52) -> 234.69 | L52: =IF(C52>=13,1,"") | M52: 93.62 | N52: 24.57 | O52: 12 | P52: 1.5 | S52: 10 | U52: 93 | V52: COMPRA DE ARCONDICIONADO 9/10 R$ 50,00; 10 DE FEVEREIRO R$ 18,00; TAXA PREPARO 1/2 R$ 25,00 | W52: =IF(F52=SUM(M52:U52),"OK","Diferente") -> Diferente | X52: =IF(W52="Diferente",F52-SUM(M52:U52),"") -> -234.69
B53: JULIA ROGERIO FIORE CHEUEN | D53: Pendente | E53: =SUM(M53:U53) -> 174.69 | L53: =IF(C53>=13,1,"") | M53: 93.62 | N53: 24.57 | O53: 12 | P53: 1.5 | U53: 43 | V53: 10 DE FEVEREIRO R$ 18,00; TAXA PREPARO 1/2 R$ 25,00 | W53: =IF(F53=SUM(M53:U53),"OK","Diferente") -> Diferente | X53: =IF(W53="Diferente",F53-SUM(M53:U53),"") -> -174.69
B54: ISABELA CLAREANA PEREIRA FELIX | C54: 3 | D54: OK | E54: =SUM(M54:U54) -> 225.44 | F54: =E54 -> 225.44 | H54: Banco - Cora | L54: =IF(C54>=13,1,"") | M54: 139.43 | N54: 24.57 | O54: 12 | P54: 1.44 | Q54: 5 | U54: 43 | V54: 10 DE FEVEREIRO R$ 18,00; TAXA PREPARO 1/2 R$ 25,00 | W54: =IF(F54=SUM(M54:U54),"OK","Diferente") -> OK | X54: =IF(W54="Diferente",F54-SUM(M54:U54),"")
B55: PEDRO KLECIUS FARIAS CARDOSO | C55: 3 | D55: OK | E55: =SUM(M55:U55) -> 689.29 | F55: =E55 -> 689.29 | H55: Banco - Cora | L55: =IF(C55>=13,1,"") | M55: 98.28 | N55: 24.57 | O55: 12 | P55: 1.44 | R55: 10 | T55: 100 | U55: 443 | V55: 10 DE FEVEREIRO R$ 18,00; TAXA PREPARO 1/2 R$ 25,00; DOAÇÃO R$ 400,00 | W55: =IF(F55=SUM(M55:U55),"OK","Diferente") -> OK | X55: =IF(W55="Diferente",F55-SUM(M55:U55),"")
B56: GENILDA DA SILVA CARDOSO | C56: 3 | D56: OK | E56: =SUM(M56:U56) -> 189.29 | F56: =E56 -> 189.29 | H56: Banco - Cora | L56: =IF(C56>=13,1,"") | M56: 98.28 | N56: 24.57 | O56: 12 | P56: 1.44 | R56: 10 | U56: 43 | V56: 10 DE FEVEREIRO R$ 18,00; TAXA PREPARO 1/2 R$ 25,00 | W56: =IF(F56=SUM(M56:U56),"OK","Diferente") -> OK | X56: =IF(W56="Diferente",F56-SUM(M56:U56),"")
B57: MANOEL MESSIAS DO NASCIMENTO NETO | D57: Pendente | E57: =SUM(M57:U57) -> 100 | L57: =IF(C57>=13,1,"") | M57: 13.93 | N57: 24.57 | O57: 12 | P57: 1.5 | Q57: 5 | U57: 43 | V57: 10 DE FEVEREIRO R$ 18,00; TAXA PREPARO 1/2 R$ 25,00 | W57: =IF(F57=SUM(M57:U57),"OK","Diferente") -> Diferente | X57: =IF(W57="Diferente",F57-SUM(M57:U57),"") -> -100
B58: BRANDA DE PÁDUA CARNEIRO VASCONCELOS LESSA | C58: 10 | D58: OK | E58: =SUM(M58:U58) -> 183.5 | F58: =E58 -> 183.5 | H58: Banco - Cora | L58: =IF(C58>=13,1,"") | M58: 93.43 | N58: 24.57 | O58: 12 | P58: 1.5 | R58: 0 | S58: 4 | T58: 5 | U58: 43 | V58: 10 DE FEVEREIRO R$ 18,00; TAXA PREPARO 1/2 R$ 25,00 | W58: =IF(F58=SUM(M58:U58),"OK","Diferente") -> OK | X58: =IF(W58="Diferente",F58-SUM(M58:U58),"")
B59: MATEUS CHAVES LESSA DE CASTRO | C59: 10 | D59: OK | E59: =SUM(M59:U59) -> 182.5 | F59: =E59 -> 182.5 | H59: Banco - Cora | L59: =IF(C59>=13,1,"") | M59: 93.43 | N59: 24.57 | O59: 12 | P59: 1.5 | R59: 0 | S59: 3 | T59: 5 | U59: 43 | V59: 10 DE FEVEREIRO R$ 18,00; TAXA PREPARO 1/2 R$ 25,00 | W59: =IF(F59=SUM(M59:U59),"OK","Diferente") -> OK | X59: =IF(W59="Diferente",F59-SUM(M59:U59),"")
B60: ROSSYANE MARIA OLIVEIRA DA COSTA | C60: 3 | D60: OK | E60: =SUM(M60:U60) -> 100 | F60: =E60 -> 100 | H60: Banco - Cora | L60: =IF(C60>=13,1,"") | M60: 61.93 | N60: 24.57 | O60: 12 | P60: 1.5 | W60: =IF(F60=SUM(M60:U60),"OK","Diferente") -> OK | X60: =IF(W60="Diferente",F60-SUM(M60:U60),"")
B61: ALINE MIRANDA DE OLIVEIRA | D61: Pendente | E61: =SUM(M61:U61) -> 105.37 | L61: =IF(C61>=13,1,"") | M61: 19.36 | N61: 24.57 | O61: 12 | P61: 1.44 | Q61: 5 | U61: 43 | V61: 10 DE FEVEREIRO R$ 18,00; TAXA PREPARO 1/2 R$ 25,00 | W61: =IF(F61=SUM(M61:U61),"OK","Diferente") -> Diferente | X61: =IF(W61="Diferente",F61-SUM(M61:U61),"") -> -105.37
B62: ANTÔNIO RAMON DA SILVA MAIA | D62: Pendente | E62: =SUM(M62:U62) -> 115.75 | L62: =IF(C62>=13,1,"") | M62: 29.74 | N62: 24.57 | O62: 12 | P62: 1.44 | Q62: 5 | U62: 43 | V62: 10 DE FEVEREIRO R$ 18,00; TAXA PREPARO 1/2 R$ 25,00 | W62: =IF(F62=SUM(M62:U62),"OK","Diferente") -> Diferente | X62: =IF(W62="Diferente",F62-SUM(M62:U62),"") -> -115.75
B63: RAFAELY MAIA SOMBRA CORDEIRO | D63: Pendente | E63: =SUM(M63:U63) -> 116 | L63: =IF(C63>=13,1,"") | M63: 29.93 | N63: 24.57 | O63: 12 | P63: 1.5 | Q63: 5 | U63: 43 | V63: 10 DE FEVEREIRO R$ 18,00; TAXA PREPARO 1/2 R$ 25,00 | W63: =IF(F63=SUM(M63:U63),"OK","Diferente") -> Diferente | X63: =IF(W63="Diferente",F63-SUM(M63:U63),"") -> -116
B64: FRANCISCO HILTON DOS SANTOS JÚNIOR | D64: Pendente | E64: =SUM(M64:U64) -> 193 | L64: =IF(C64>=13,1,"") | M64: 61.99 | N64: 24.57 | O64: 12 | P64: 1.44 | U64: 93 | V64: TAXA AÇÃO ENTRE AMIGOS 4/4 R$ 50,00; 10 DE FEVEREIRO R$ 18,00; TAXA PREPARO 1/2 R$ 25,00 | W64: =IF(F64=SUM(M64:U64),"OK","Diferente") -> Diferente | X64: =IF(W64="Diferente",F64-SUM(M64:U64),"") -> -193
B65: IANNA DARC GOMES MARTINS | C65: 7 | D65: Parcial | E65: 181.07 | F65: =SUM(M65:U65) -> 338.07 | G65: Pagamento referente a Dezembro. Março ainda pendente. | H65: Banco - Pagbank | L65: =IF(C65>=13,1,"") | M65: =100+157 -> 257 | N65: 24.57 | O65: 12 | P65: 1.5 | U65: 43 | V65: 10 DE FEVEREIRO R$ 18,00; TAXA PREPARO 1/2 R$ 25,00 | W65: =IF(F65=SUM(M65:U65),"OK","Diferente") -> OK | X65: =IF(W65="Diferente",F65-SUM(M65:U65),"")
B66: MARCIO WALLACE EVANGELISTA TEIXEIRA | C66: 1 | D66: OK | E66: =SUM(M66:U66) -> 311.82 | F66: =E66 -> 311.82 | H66: Banco - Cora | L66: =IF(C66>=13,1,"") | M66: 122.25 | N66: 24.57 | O66: 12 | P66: 10 | Q66: 5 | R66: 5 | S66: 15 | T66: 25 | U66: 93 | V66: COMPRA DE ARCONDICIONADO 9/10 R$ 50,00; 10 DE FEVEREIRO R$ 18,00; TAXA PREPARO 1/2 R$ 25,00 | W66: =IF(F66=SUM(M66:U66),"OK","Diferente") -> OK | X66: =IF(W66="Diferente",F66-SUM(M66:U66),"")
B67: JULIANA DIAS PERDIGÃO TEIXEIRA | C67: 1 | D67: OK | E67: =SUM(M67:U67) -> 261.82 | F67: =E67 -> 261.82 | H67: Banco - Cora | L67: =IF(C67>=13,1,"") | M67: 122.25 | N67: 24.57 | O67: 12 | P67: 10 | Q67: 5 | R67: 5 | S67: 15 | T67: 25 | U67: 43 | V67: 10 DE FEVEREIRO R$ 18,00; TAXA PREPARO 1/2 R$ 25,00 | W67: =IF(F67=SUM(M67:U67),"OK","Diferente") -> OK | X67: =IF(W67="Diferente",F67-SUM(M67:U67),"")
B68: MATEUS DE MIRANDA DINO | C68: 1 | D68: OK | E68: 274.44 | F68: =SUM(M68:U68) -> 558.88 | H68: Banco - Cora | L68: =IF(C68>=13,1,"") | M68: =113.43+284.44 -> 397.87 | N68: 24.57 | O68: 12 | P68: 1.44 | Q68: 5 | R68: 20 | S68: 5 | U68: 93 | V68: 10 DE FEVEREIRO R$ 18,00; TAXA PREPARO 1/2 R$ 25,00; CANTINA SANA R$ 50,00 | W68: =IF(F68=SUM(M68:U68),"OK","Diferente") -> OK | X68: =IF(W68="Diferente",F68-SUM(M68:U68),"")
B69: VITOR SANTOS DE OLIVEIRA | C69: 18 | D69: OK | E69: =SUM(M69:U69) -> 108.67 | F69: =E69 -> 108.67 | H69: Banco - Cora | L69: =IF(C69>=13,1,"") -> 1 | M69: 27.66 | N69: 24.57 | O69: 12 | P69: 1.44 | U69: 43 | V69: 10 DE FEVEREIRO R$ 18,00; TAXA PREPARO 1/2 R$ 25,00 | W69: =IF(F69=SUM(M69:U69),"OK","Diferente") -> OK | X69: =IF(W69="Diferente",F69-SUM(M69:U69),"")
B70: CARMEM SILVIA DE CARVALHO RÊGO | C70: 11 | D70: OK | E70: =SUM(M70:U70) -> 163 | F70: =E70 -> 163 | H70: Banco - Cora | L70: =IF(C70>=13,1,"") | M70: 81.93 | N70: 24.57 | O70: 12 | P70: 1.5 | U70: 43 | V70: 10 DE FEVEREIRO R$ 18,00; TAXA PREPARO 1/2 R$ 25,00 | W70: =IF(F70=SUM(M70:U70),"OK","Diferente") -> OK | X70: =IF(W70="Diferente",F70-SUM(M70:U70),"")
